Workbook

Sheet Player Details - Post 2025
J1: 2024 | K1: 2025 | L1: 2026 | M1: 2027 | N1: 2028 | O1: 2029 | P1: 2030
A3: Player Name | B3: Franchise | C3: Acq. Date | D3: Drop Date | E3: Contract Type | F3: Salary | G3: Contract Length | H3: Contract Starts | I3: Contract Ends | J3: 2024 Salary Hit | K3: =concatenate(K1, " Salary Hit") -> 2025 Salary Hit | L3: =concatenate(L1, " Salary Hit") -> 2026 Salary Hit | M3: =concatenate(M1, " Salary Hit") -> 2027 Salary Hit | N3: =concatenate(N1, " Salary Hit") -> 2028 Salary Hit | O3: =concatenate(O1, " Salary Hit") -> 2029 Salary Hit | P3: =concatenate(P1, " Salary Hit") -> 2030 Salary Hit
A4: Julio Rodriguez | B4: Brenden Freedman | C4: 45318 | E4: FA Contract | F4: 33100000 | G4: 5 | H4: 2024 | I4: =if(H4="","",if(or($E4="FA Contract",$E4="Dropped"),$H4+$G4-1,if($E4="YP Contract",$H4+2,if(and($E4="Minors",$G4<>"YP"),$H4+$G4-1,if(and($E4="Minors",$G4="YP"),$H4+2,""))))) -> 2028 | J4: 33100000 | K4: =if($E4="","",if($E4="Dropped",if(and(K$1<=$I4,K$1>=$H4),if(Year($D4)=K$1,$F4*0.8,if((year($D4)+1)=K$1,$F4*0.6,$F4*0.4)) ,""),if($E4="Minors",0,if($E4="FA Contract",if(and(K$1<=$I4,K$1>=$H4),$F4,""),if($E4="YP Contract",if(K$1=$H4,500000,if(K$1=($H4+1),1000000,if(K$1=($H4+2),1500000,"")))))))) -> 33100000 | L4: =if($E4="","",if($E4="Dropped",if(and(L$1<=$I4,L$1>=$H4),if(Year($D4)=L$1,$F4*0.8,if((year($D4)+1)=L$1,$F4*0.6,$F4*0.4)) ,""),if($E4="Minors",0,if($E4="FA Contract",if(and(L$1<=$I4,L$1>=$H4),$F4,""),if($E4="YP Contract",if(L$1=$H4,500000,if(L$1=($H4+1),1000000,if(L$1=($H4+2),1500000,"")))))))) -> 33100000 | M4: =if($E4="","",if($E4="Dropped",if(and(M$1<=$I4,M$1>=$H4),if(Year($D4)=M$1,$F4*0.8,if((year($D4)+1)=M$1,$F4*0.6,$F4*0.4)) ,""),if($E4="Minors",0,if($E4="FA Contract",if(and(M$1<=$I4,M$1>=$H4),$F4,""),if($E4="YP Contract",if(M$1=$H4,500000,if(M$1=($H4+1),1000000,if(M$1=($H4+2),1500000,"")))))))) -> 33100000 | N4: =if($E4="","",if($E4="Dropped",if(and(N$1<=$I4,N$1>=$H4),if(Year($D4)=N$1,$F4*0.8,if((year($D4)+1)=N$1,$F4*0.6,$F4*0.4)) ,""),if($E4="Minors",0,if($E4="FA Contract",if(and(N$1<=$I4,N$1>=$H4),$F4,""),if($E4="YP Contract",if(N$1=$H4,500000,if(N$1=($H4+1),1000000,if(N$1=($H4+2),1500000,"")))))))) -> 33100000 | O4: =if($E4="","",if($E4="Dropped",if(and(O$1<=$I4,O$1>=$H4),if(Year($D4)=O$1,$F4*0.8,if((year($D4)+1)=O$1,$F4*0.6,$F4*0.4)) ,""),if($E4="Minors",0,if($E4="FA Contract",if(and(O$1<=$I4,O$1>=$H4),$F4,""),if($E4="YP Contract",if(O$1=$H4,500000,if(O$1=($H4+1),1000000,if(O$1=($H4+2),1500000,"")))))))) | P4: =if($E4="","",if($E4="Dropped",if(and(P$1<=$I4,P$1>=$H4),if(Year($D4)=P$1,$F4*0.8,if((year($D4)+1)=P$1,$F4*0.6,$F4*0.4)) ,""),if($E4="Minors",0,if($E4="FA Contract",if(and(P$1<=$I4,P$1>=$H4),$F4,""),if($E4="YP Contract",if(P$1=$H4,500000,if(P$1=($H4+1),1000000,if(P$1=($H4+2),1500000,""))))))))
A5: Yoshinobu Yamamoto | B5: Brenden Freedman | C5: 45318 | E5: FA Contract | F5: 23800000 | G5: 4 | H5: 2024 | I5: =if(H5="","",if(or($E5="FA Contract",$E5="Dropped"),$H5+$G5-1,if($E5="YP Contract",$H5+2,if(and($E5="Minors",$G5<>"YP"),$H5+$G5-1,if(and($E5="Minors",$G5="YP"),$H5+2,""))))) -> 2027 | J5: 33100000 | K5: =if($E5="","",if($E5="Dropped",if(and(K$1<=$I5,K$1>=$H5),if(Year($D5)=K$1,$F5*0.8,if((year($D5)+1)=K$1,$F5*0.6,$F5*0.4)) ,""),if($E5="Minors",0,if($E5="FA Contract",if(and(K$1<=$I5,K$1>=$H5),$F5,""),if($E5="YP Contract",if(K$1=$H5,500000,if(K$1=($H5+1),1000000,if(K$1=($H5+2),1500000,"")))))))) -> 23800000 | L5: =if($E5="","",if($E5="Dropped",if(and(L$1<=$I5,L$1>=$H5),if(Year($D5)=L$1,$F5*0.8,if((year($D5)+1)=L$1,$F5*0.6,$F5*0.4)) ,""),if($E5="Minors",0,if($E5="FA Contract",if(and(L$1<=$I5,L$1>=$H5),$F5,""),if($E5="YP Contract",if(L$1=$H5,500000,if(L$1=($H5+1),1000000,if(L$1=($H5+2),1500000,"")))))))) -> 23800000 | M5: =if($E5="","",if($E5="Dropped",if(and(M$1<=$I5,M$1>=$H5),if(Year($D5)=M$1,$F5*0.8,if((year($D5)+1)=M$1,$F5*0.6,$F5*0.4)) ,""),if($E5="Minors",0,if($E5="FA Contract",if(and(M$1<=$I5,M$1>=$H5),$F5,""),if($E5="YP Contract",if(M$1=$H5,500000,if(M$1=($H5+1),1000000,if(M$1=($H5+2),1500000,"")))))))) -> 23800000 | N5: =if($E5="","",if($E5="Dropped",if(and(N$1<=$I5,N$1>=$H5),if(Year($D5)=N$1,$F5*0.8,if((year($D5)+1)=N$1,$F5*0.6,$F5*0.4)) ,""),if($E5="Minors",0,if($E5="FA Contract",if(and(N$1<=$I5,N$1>=$H5),$F5,""),if($E5="YP Contract",if(N$1=$H5,500000,if(N$1=($H5+1),1000000,if(N$1=($H5+2),1500000,"")))))))) | O5: =if($E5="","",if($E5="Dropped",if(and(O$1<=$I5,O$1>=$H5),if(Year($D5)=O$1,$F5*0.8,if((year($D5)+1)=O$1,$F5*0.6,$F5*0.4)) ,""),if($E5="Minors",0,if($E5="FA Contract",if(and(O$1<=$I5,O$1>=$H5),$F5,""),if($E5="YP Contract",if(O$1=$H5,500000,if(O$1=($H5+1),1000000,if(O$1=($H5+2),1500000,"")))))))) | P5: =if($E5="","",if($E5="Dropped",if(and(P$1<=$I5,P$1>=$H5),if(Year($D5)=P$1,$F5*0.8,if((year($D5)+1)=P$1,$F5*0.6,$F5*0.4)) ,""),if($E5="Minors",0,if($E5="FA Contract",if(and(P$1<=$I5,P$1>=$H5),$F5,""),if($E5="YP Contract",if(P$1=$H5,500000,if(P$1=($H5+1),1000000,if(P$1=($H5+2),1500000,""))))))))
A6: Jose Ramirez | B6: Brenden Freedman | C6: 45318 | E6: FA Contract | F6: 20000000 | G6: 4 | H6: 2024 | I6: =if(H6="","",if(or($E6="FA Contract",$E6="Dropped"),$H6+$G6-1,if($E6="YP Contract",$H6+2,if(and($E6="Minors",$G6<>"YP"),$H6+$G6-1,if(and($E6="Minors",$G6="YP"),$H6+2,""))))) -> 2027 | J6: 33100000 | K6: =if($E6="","",if($E6="Dropped",if(and(K$1<=$I6,K$1>=$H6),if(Year($D6)=K$1,$F6*0.8,if((year($D6)+1)=K$1,$F6*0.6,$F6*0.4)) ,""),if($E6="Minors",0,if($E6="FA Contract",if(and(K$1<=$I6,K$1>=$H6),$F6,""),if($E6="YP Contract",if(K$1=$H6,500000,if(K$1=($H6+1),1000000,if(K$1=($H6+2),1500000,"")))))))) -> 20000000 | L6: =if($E6="","",if($E6="Dropped",if(and(L$1<=$I6,L$1>=$H6),if(Year($D6)=L$1,$F6*0.8,if((year($D6)+1)=L$1,$F6*0.6,$F6*0.4)) ,""),if($E6="Minors",0,if($E6="FA Contract",if(and(L$1<=$I6,L$1>=$H6),$F6,""),if($E6="YP Contract",if(L$1=$H6,500000,if(L$1=($H6+1),1000000,if(L$1=($H6+2),1500000,"")))))))) -> 20000000 | M6: =if($E6="","",if($E6="Dropped",if(and(M$1<=$I6,M$1>=$H6),if(Year($D6)=M$1,$F6*0.8,if((year($D6)+1)=M$1,$F6*0.6,$F6*0.4)) ,""),if($E6="Minors",0,if($E6="FA Contract",if(and(M$1<=$I6,M$1>=$H6),$F6,""),if($E6="YP Contract",if(M$1=$H6,500000,if(M$1=($H6+1),1000000,if(M$1=($H6+2),1500000,"")))))))) -> 20000000 | N6: =if($E6="","",if($E6="Dropped",if(and(N$1<=$I6,N$1>=$H6),if(Year($D6)=N$1,$F6*0.8,if((year($D6)+1)=N$1,$F6*0.6,$F6*0.4)) ,""),if($E6="Minors",0,if($E6="FA Contract",if(and(N$1<=$I6,N$1>=$H6),$F6,""),if($E6="YP Contract",if(N$1=$H6,500000,if(N$1=($H6+1),1000000,if(N$1=($H6+2),1500000,"")))))))) | O6: =if($E6="","",if($E6="Dropped",if(and(O$1<=$I6,O$1>=$H6),if(Year($D6)=O$1,$F6*0.8,if((year($D6)+1)=O$1,$F6*0.6,$F6*0.4)) ,""),if($E6="Minors",0,if($E6="FA Contract",if(and(O$1<=$I6,O$1>=$H6),$F6,""),if($E6="YP Contract",if(O$1=$H6,500000,if(O$1=($H6+1),1000000,if(O$1=($H6+2),1500000,"")))))))) | P6: =if($E6="","",if($E6="Dropped",if(and(P$1<=$I6,P$1>=$H6),if(Year($D6)=P$1,$F6*0.8,if((year($D6)+1)=P$1,$F6*0.6,$F6*0.4)) ,""),if($E6="Minors",0,if($E6="FA Contract",if(and(P$1<=$I6,P$1>=$H6),$F6,""),if($E6="YP Contract",if(P$1=$H6,500000,if(P$1=($H6+1),1000000,if(P$1=($H6+2),1500000,""))))))))
A7: Kodai Senga | B7: Brenden Freedman | C7: 45318 | E7: FA Contract | F7: 10900000 | G7: 2 | H7: 2024 | I7: =if(H7="","",if(or($E7="FA Contract",$E7="Dropped"),$H7+$G7-1,if($E7="YP Contract",$H7+2,if(and($E7="Minors",$G7<>"YP"),$H7+$G7-1,if(and($E7="Minors",$G7="YP"),$H7+2,""))))) -> 2025 | J7: 33100000 | K7: =if($E7="","",if($E7="Dropped",if(and(K$1<=$I7,K$1>=$H7),if(Year($D7)=K$1,$F7*0.8,if((year($D7)+1)=K$1,$F7*0.6,$F7*0.4)) ,""),if($E7="Minors",0,if($E7="FA Contract",if(and(K$1<=$I7,K$1>=$H7),$F7,""),if($E7="YP Contract",if(K$1=$H7,500000,if(K$1=($H7+1),1000000,if(K$1=($H7+2),1500000,"")))))))) -> 10900000 | L7: =if($E7="","",if($E7="Dropped",if(and(L$1<=$I7,L$1>=$H7),if(Year($D7)=L$1,$F7*0.8,if((year($D7)+1)=L$1,$F7*0.6,$F7*0.4)) ,""),if($E7="Minors",0,if($E7="FA Contract",if(and(L$1<=$I7,L$1>=$H7),$F7,""),if($E7="YP Contract",if(L$1=$H7,500000,if(L$1=($H7+1),1000000,if(L$1=($H7+2),1500000,"")))))))) | M7: =if($E7="","",if($E7="Dropped",if(and(M$1<=$I7,M$1>=$H7),if(Year($D7)=M$1,$F7*0.8,if((year($D7)+1)=M$1,$F7*0.6,$F7*0.4)) ,""),if($E7="Minors",0,if($E7="FA Contract",if(and(M$1<=$I7,M$1>=$H7),$F7,""),if($E7="YP Contract",if(M$1=$H7,500000,if(M$1=($H7+1),1000000,if(M$1=($H7+2),1500000,"")))))))) | N7: =if($E7="","",if($E7="Dropped",if(and(N$1<=$I7,N$1>=$H7),if(Year($D7)=N$1,$F7*0.8,if((year($D7)+1)=N$1,$F7*0.6,$F7*0.4)) ,""),if($E7="Minors",0,if($E7="FA Contract",if(and(N$1<=$I7,N$1>=$H7),$F7,""),if($E7="YP Contract",if(N$1=$H7,500000,if(N$1=($H7+1),1000000,if(N$1=($H7+2),1500000,"")))))))) | O7: =if($E7="","",if($E7="Dropped",if(and(O$1<=$I7,O$1>=$H7),if(Year($D7)=O$1,$F7*0.8,if((year($D7)+1)=O$1,$F7*0.6,$F7*0.4)) ,""),if($E7="Minors",0,if($E7="FA Contract",if(and(O$1<=$I7,O$1>=$H7),$F7,""),if($E7="YP Contract",if(O$1=$H7,500000,if(O$1=($H7+1),1000000,if(O$1=($H7+2),1500000,"")))))))) | P7: =if($E7="","",if($E7="Dropped",if(and(P$1<=$I7,P$1>=$H7),if(Year($D7)=P$1,$F7*0.8,if((year($D7)+1)=P$1,$F7*0.6,$F7*0.4)) ,""),if($E7="Minors",0,if($E7="FA Contract",if(and(P$1<=$I7,P$1>=$H7),$F7,""),if($E7="YP Contract",if(P$1=$H7,500000,if(P$1=($H7+1),1000000,if(P$1=($H7+2),1500000,""))))))))
A8: Cade Smith | B8: Brenden Freedman | C8: 45691 | E8: FA Contract | F8: 6000000 | G8: 3 | H8: 2025 | I8: =if(H8="","",if(or($E8="FA Contract",$E8="Dropped"),$H8+$G8-1,if($E8="YP Contract",$H8+2,if(and($E8="Minors",$G8<>"YP"),$H8+$G8-1,if(and($E8="Minors",$G8="YP"),$H8+2,""))))) -> 2027 | J8: 33100000 | K8: =if($E8="","",if($E8="Dropped",if(and(K$1<=$I8,K$1>=$H8),if(Year($D8)=K$1,$F8*0.8,if((year($D8)+1)=K$1,$F8*0.6,$F8*0.4)) ,""),if($E8="Minors",0,if($E8="FA Contract",if(and(K$1<=$I8,K$1>=$H8),$F8,""),if($E8="YP Contract",if(K$1=$H8,500000,if(K$1=($H8+1),1000000,if(K$1=($H8+2),1500000,"")))))))) -> 6000000 | L8: =if($E8="","",if($E8="Dropped",if(and(L$1<=$I8,L$1>=$H8),if(Year($D8)=L$1,$F8*0.8,if((year($D8)+1)=L$1,$F8*0.6,$F8*0.4)) ,""),if($E8="Minors",0,if($E8="FA Contract",if(and(L$1<=$I8,L$1>=$H8),$F8,""),if($E8="YP Contract",if(L$1=$H8,500000,if(L$1=($H8+1),1000000,if(L$1=($H8+2),1500000,"")))))))) -> 6000000 | M8: =if($E8="","",if($E8="Dropped",if(and(M$1<=$I8,M$1>=$H8),if(Year($D8)=M$1,$F8*0.8,if((year($D8)+1)=M$1,$F8*0.6,$F8*0.4)) ,""),if($E8="Minors",0,if($E8="FA Contract",if(and(M$1<=$I8,M$1>=$H8),$F8,""),if($E8="YP Contract",if(M$1=$H8,500000,if(M$1=($H8+1),1000000,if(M$1=($H8+2),1500000,"")))))))) -> 6000000 | N8: =if($E8="","",if($E8="Dropped",if(and(N$1<=$I8,N$1>=$H8),if(Year($D8)=N$1,$F8*0.8,if((year($D8)+1)=N$1,$F8*0.6,$F8*0.4)) ,""),if($E8="Minors",0,if($E8="FA Contract",if(and(N$1<=$I8,N$1>=$H8),$F8,""),if($E8="YP Contract",if(N$1=$H8,500000,if(N$1=($H8+1),1000000,if(N$1=($H8+2),1500000,"")))))))) | O8: =if($E8="","",if($E8="Dropped",if(and(O$1<=$I8,O$1>=$H8),if(Year($D8)=O$1,$F8*0.8,if((year($D8)+1)=O$1,$F8*0.6,$F8*0.4)) ,""),if($E8="Minors",0,if($E8="FA Contract",if(and(O$1<=$I8,O$1>=$H8),$F8,""),if($E8="YP Contract",if(O$1=$H8,500000,if(O$1=($H8+1),1000000,if(O$1=($H8+2),1500000,"")))))))) | P8: =if($E8="","",if($E8="Dropped",if(and(P$1<=$I8,P$1>=$H8),if(Year($D8)=P$1,$F8*0.8,if((year($D8)+1)=P$1,$F8*0.6,$F8*0.4)) ,""),if($E8="Minors",0,if($E8="FA Contract",if(and(P$1<=$I8,P$1>=$H8),$F8,""),if($E8="YP Contract",if(P$1=$H8,500000,if(P$1=($H8+1),1000000,if(P$1=($H8+2),1500000,""))))))))
A9: George Springer | B9: Brenden Freedman | C9: 45318 | E9: FA Contract | F9: 5100000 | G9: 3 | H9: 2024 | I9: =if(H9="","",if(or($E9="FA Contract",$E9="Dropped"),$H9+$G9-1,if($E9="YP Contract",$H9+2,if(and($E9="Minors",$G9<>"YP"),$H9+$G9-1,if(and($E9="Minors",$G9="YP"),$H9+2,""))))) -> 2026 | J9: 33100000 | K9: =if($E9="","",if($E9="Dropped",if(and(K$1<=$I9,K$1>=$H9),if(Year($D9)=K$1,$F9*0.8,if((year($D9)+1)=K$1,$F9*0.6,$F9*0.4)) ,""),if($E9="Minors",0,if($E9="FA Contract",if(and(K$1<=$I9,K$1>=$H9),$F9,""),if($E9="YP Contract",if(K$1=$H9,500000,if(K$1=($H9+1),1000000,if(K$1=($H9+2),1500000,"")))))))) -> 5100000 | L9: =if($E9="","",if($E9="Dropped",if(and(L$1<=$I9,L$1>=$H9),if(Year($D9)=L$1,$F9*0.8,if((year($D9)+1)=L$1,$F9*0.6,$F9*0.4)) ,""),if($E9="Minors",0,if($E9="FA Contract",if(and(L$1<=$I9,L$1>=$H9),$F9,""),if($E9="YP Contract",if(L$1=$H9,500000,if(L$1=($H9+1),1000000,if(L$1=($H9+2),1500000,"")))))))) -> 5100000 | M9: =if($E9="","",if($E9="Dropped",if(and(M$1<=$I9,M$1>=$H9),if(Year($D9)=M$1,$F9*0.8,if((year($D9)+1)=M$1,$F9*0.6,$F9*0.4)) ,""),if($E9="Minors",0,if($E9="FA Contract",if(and(M$1<=$I9,M$1>=$H9),$F9,""),if($E9="YP Contract",if(M$1=$H9,500000,if(M$1=($H9+1),1000000,if(M$1=($H9+2),1500000,"")))))))) | N9: =if($E9="","",if($E9="Dropped",if(and(N$1<=$I9,N$1>=$H9),if(Year($D9)=N$1,$F9*0.8,if((year($D9)+1)=N$1,$F9*0.6,$F9*0.4)) ,""),if($E9="Minors",0,if($E9="FA Contract",if(and(N$1<=$I9,N$1>=$H9),$F9,""),if($E9="YP Contract",if(N$1=$H9,500000,if(N$1=($H9+1),1000000,if(N$1=($H9+2),1500000,"")))))))) | O9: =if($E9="","",if($E9="Dropped",if(and(O$1<=$I9,O$1>=$H9),if(Year($D9)=O$1,$F9*0.8,if((year($D9)+1)=O$1,$F9*0.6,$F9*0.4)) ,""),if($E9="Minors",0,if($E9="FA Contract",if(and(O$1<=$I9,O$1>=$H9),$F9,""),if($E9="YP Contract",if(O$1=$H9,500000,if(O$1=($H9+1),1000000,if(O$1=($H9+2),1500000,"")))))))) | P9: =if($E9="","",if($E9="Dropped",if(and(P$1<=$I9,P$1>=$H9),if(Year($D9)=P$1,$F9*0.8,if((year($D9)+1)=P$1,$F9*0.6,$F9*0.4)) ,""),if($E9="Minors",0,if($E9="FA Contract",if(and(P$1<=$I9,P$1>=$H9),$F9,""),if($E9="YP Contract",if(P$1=$H9,500000,if(P$1=($H9+1),1000000,if(P$1=($H9+2),1500000,""))))))))
A10: JT Realmuto | B10: Brenden Freedman | C10: 45356 | E10: FA Contract | F10: 5000000 | G10: 2 | H10: 2024 | I10: =if(H10="","",if(or($E10="FA Contract",$E10="Dropped"),$H10+$G10-1,if($E10="YP Contract",$H10+2,if(and($E10="Minors",$G10<>"YP"),$H10+$G10-1,if(and($E10="Minors",$G10="YP"),$H10+2,""))))) -> 2025 | J10: 33100000 | K10: =if($E10="","",if($E10="Dropped",if(and(K$1<=$I10,K$1>=$H10),if(Year($D10)=K$1,$F10*0.8,if((year($D10)+1)=K$1,$F10*0.6,$F10*0.4)) ,""),if($E10="Minors",0,if($E10="FA Contract",if(and(K$1<=$I10,K$1>=$H10),$F10,""),if($E10="YP Contract",if(K$1=$H10,500000,if(K$1=($H10+1),1000000,if(K$1=($H10+2),1500000,"")))))))) -> 5000000 | L10: =if($E10="","",if($E10="Dropped",if(and(L$1<=$I10,L$1>=$H10),if(Year($D10)=L$1,$F10*0.8,if((year($D10)+1)=L$1,$F10*0.6,$F10*0.4)) ,""),if($E10="Minors",0,if($E10="FA Contract",if(and(L$1<=$I10,L$1>=$H10),$F10,""),if($E10="YP Contract",if(L$1=$H10,500000,if(L$1=($H10+1),1000000,if(L$1=($H10+2),1500000,"")))))))) | M10: =if($E10="","",if($E10="Dropped",if(and(M$1<=$I10,M$1>=$H10),if(Year($D10)=M$1,$F10*0.8,if((year($D10)+1)=M$1,$F10*0.6,$F10*0.4)) ,""),if($E10="Minors",0,if($E10="FA Contract",if(and(M$1<=$I10,M$1>=$H10),$F10,""),if($E10="YP Contract",if(M$1=$H10,500000,if(M$1=($H10+1),1000000,if(M$1=($H10+2),1500000,"")))))))) | N10: =if($E10="","",if($E10="Dropped",if(and(N$1<=$I10,N$1>=$H10),if(Year($D10)=N$1,$F10*0.8,if((year($D10)+1)=N$1,$F10*0.6,$F10*0.4)) ,""),if($E10="Minors",0,if($E10="FA Contract",if(and(N$1<=$I10,N$1>=$H10),$F10,""),if($E10="YP Contract",if(N$1=$H10,500000,if(N$1=($H10+1),1000000,if(N$1=($H10+2),1500000,"")))))))) | O10: =if($E10="","",if($E10="Dropped",if(and(O$1<=$I10,O$1>=$H10),if(Year($D10)=O$1,$F10*0.8,if((year($D10)+1)=O$1,$F10*0.6,$F10*0.4)) ,""),if($E10="Minors",0,if($E10="FA Contract",if(and(O$1<=$I10,O$1>=$H10),$F10,""),if($E10="YP Contract",if(O$1=$H10,500000,if(O$1=($H10+1),1000000,if(O$1=($H10+2),1500000,"")))))))) | P10: =if($E10="","",if($E10="Dropped",if(and(P$1<=$I10,P$1>=$H10),if(Year($D10)=P$1,$F10*0.8,if((year($D10)+1)=P$1,$F10*0.6,$F10*0.4)) ,""),if($E10="Minors",0,if($E10="FA Contract",if(and(P$1<=$I10,P$1>=$H10),$F10,""),if($E10="YP Contract",if(P$1=$H10,500000,if(P$1=($H10+1),1000000,if(P$1=($H10+2),1500000,""))))))))
A11: Nathaniel Lowe | B11: Brenden Freedman | C11: 45356 | E11: FA Contract | F11: 5000000 | G11: 2 | H11: 2024 | I11: =if(H11="","",if(or($E11="FA Contract",$E11="Dropped"),$H11+$G11-1,if($E11="YP Contract",$H11+2,if(and($E11="Minors",$G11<>"YP"),$H11+$G11-1,if(and($E11="Minors",$G11="YP"),$H11+2,""))))) -> 2025 | J11: 33100000 | K11: =if($E11="","",if($E11="Dropped",if(and(K$1<=$I11,K$1>=$H11),if(Year($D11)=K$1,$F11*0.8,if((year($D11)+1)=K$1,$F11*0.6,$F11*0.4)) ,""),if($E11="Minors",0,if($E11="FA Contract",if(and(K$1<=$I11,K$1>=$H11),$F11,""),if($E11="YP Contract",if(K$1=$H11,500000,if(K$1=($H11+1),1000000,if(K$1=($H11+2),1500000,"")))))))) -> 5000000 | L11: =if($E11="","",if($E11="Dropped",if(and(L$1<=$I11,L$1>=$H11),if(Year($D11)=L$1,$F11*0.8,if((year($D11)+1)=L$1,$F11*0.6,$F11*0.4)) ,""),if($E11="Minors",0,if($E11="FA Contract",if(and(L$1<=$I11,L$1>=$H11),$F11,""),if($E11="YP Contract",if(L$1=$H11,500000,if(L$1=($H11+1),1000000,if(L$1=($H11+2),1500000,"")))))))) | M11: =if($E11="","",if($E11="Dropped",if(and(M$1<=$I11,M$1>=$H11),if(Year($D11)=M$1,$F11*0.8,if((year($D11)+1)=M$1,$F11*0.6,$F11*0.4)) ,""),if($E11="Minors",0,if($E11="FA Contract",if(and(M$1<=$I11,M$1>=$H11),$F11,""),if($E11="YP Contract",if(M$1=$H11,500000,if(M$1=($H11+1),1000000,if(M$1=($H11+2),1500000,"")))))))) | N11: =if($E11="","",if($E11="Dropped",if(and(N$1<=$I11,N$1>=$H11),if(Year($D11)=N$1,$F11*0.8,if((year($D11)+1)=N$1,$F11*0.6,$F11*0.4)) ,""),if($E11="Minors",0,if($E11="FA Contract",if(and(N$1<=$I11,N$1>=$H11),$F11,""),if($E11="YP Contract",if(N$1=$H11,500000,if(N$1=($H11+1),1000000,if(N$1=($H11+2),1500000,"")))))))) | O11: =if($E11="","",if($E11="Dropped",if(and(O$1<=$I11,O$1>=$H11),if(Year($D11)=O$1,$F11*0.8,if((year($D11)+1)=O$1,$F11*0.6,$F11*0.4)) ,""),if($E11="Minors",0,if($E11="FA Contract",if(and(O$1<=$I11,O$1>=$H11),$F11,""),if($E11="YP Contract",if(O$1=$H11,500000,if(O$1=($H11+1),1000000,if(O$1=($H11+2),1500000,"")))))))) | P11: =if($E11="","",if($E11="Dropped",if(and(P$1<=$I11,P$1>=$H11),if(Year($D11)=P$1,$F11*0.8,if((year($D11)+1)=P$1,$F11*0.6,$F11*0.4)) ,""),if($E11="Minors",0,if($E11="FA Contract",if(and(P$1<=$I11,P$1>=$H11),$F11,""),if($E11="YP Contract",if(P$1=$H11,500000,if(P$1=($H11+1),1000000,if(P$1=($H11+2),1500000,""))))))))
A12: Ronel Blanco | B12: Brenden Freedman | C12: 45721 | E12: FA Contract | F12: 5000000 | G12: 2 | H12: 2025 | I12: =if(H12="","",if(or($E12="FA Contract",$E12="Dropped"),$H12+$G12-1,if($E12="YP Contract",$H12+2,if(and($E12="Minors",$G12<>"YP"),$H12+$G12-1,if(and($E12="Minors",$G12="YP"),$H12+2,""))))) -> 2026 | J12: 33100000 | K12: =if($E12="","",if($E12="Dropped",if(and(K$1<=$I12,K$1>=$H12),if(Year($D12)=K$1,$F12*0.8,if((year($D12)+1)=K$1,$F12*0.6,$F12*0.4)) ,""),if($E12="Minors",0,if($E12="FA Contract",if(and(K$1<=$I12,K$1>=$H12),$F12,""),if($E12="YP Contract",if(K$1=$H12,500000,if(K$1=($H12+1),1000000,if(K$1=($H12+2),1500000,"")))))))) -> 5000000 | L12: =if($E12="","",if($E12="Dropped",if(and(L$1<=$I12,L$1>=$H12),if(Year($D12)=L$1,$F12*0.8,if((year($D12)+1)=L$1,$F12*0.6,$F12*0.4)) ,""),if($E12="Minors",0,if($E12="FA Contract",if(and(L$1<=$I12,L$1>=$H12),$F12,""),if($E12="YP Contract",if(L$1=$H12,500000,if(L$1=($H12+1),1000000,if(L$1=($H12+2),1500000,"")))))))) -> 5000000 | M12: =if($E12="","",if($E12="Dropped",if(and(M$1<=$I12,M$1>=$H12),if(Year($D12)=M$1,$F12*0.8,if((year($D12)+1)=M$1,$F12*0.6,$F12*0.4)) ,""),if($E12="Minors",0,if($E12="FA Contract",if(and(M$1<=$I12,M$1>=$H12),$F12,""),if($E12="YP Contract",if(M$1=$H12,500000,if(M$1=($H12+1),1000000,if(M$1=($H12+2),1500000,"")))))))) | N12: =if($E12="","",if($E12="Dropped",if(and(N$1<=$I12,N$1>=$H12),if(Year($D12)=N$1,$F12*0.8,if((year($D12)+1)=N$1,$F12*0.6,$F12*0.4)) ,""),if($E12="Minors",0,if($E12="FA Contract",if(and(N$1<=$I12,N$1>=$H12),$F12,""),if($E12="YP Contract",if(N$1=$H12,500000,if(N$1=($H12+1),1000000,if(N$1=($H12+2),1500000,"")))))))) | O12: =if($E12="","",if($E12="Dropped",if(and(O$1<=$I12,O$1>=$H12),if(Year($D12)=O$1,$F12*0.8,if((year($D12)+1)=O$1,$F12*0.6,$F12*0.4)) ,""),if($E12="Minors",0,if($E12="FA Contract",if(and(O$1<=$I12,O$1>=$H12),$F12,""),if($E12="YP Contract",if(O$1=$H12,500000,if(O$1=($H12+1),1000000,if(O$1=($H12+2),1500000,"")))))))) | P12: =if($E12="","",if($E12="Dropped",if(and(P$1<=$I12,P$1>=$H12),if(Year($D12)=P$1,$F12*0.8,if((year($D12)+1)=P$1,$F12*0.6,$F12*0.4)) ,""),if($E12="Minors",0,if($E12="FA Contract",if(and(P$1<=$I12,P$1>=$H12),$F12,""),if($E12="YP Contract",if(P$1=$H12,500000,if(P$1=($H12+1),1000000,if(P$1=($H12+2),1500000,""))))))))
A13: Dansby Swanson | B13: Brenden Freedman | C13: 45318 | E13: FA Contract | F13: 4600000 | G13: 3 | H13: 2024 | I13: =if(H13="","",if(or($E13="FA Contract",$E13="Dropped"),$H13+$G13-1,if($E13="YP Contract",$H13+2,if(and($E13="Minors",$G13<>"YP"),$H13+$G13-1,if(and($E13="Minors",$G13="YP"),$H13+2,""))))) -> 2026 | J13: 33100000 | K13: =if($E13="","",if($E13="Dropped",if(and(K$1<=$I13,K$1>=$H13),if(Year($D13)=K$1,$F13*0.8,if((year($D13)+1)=K$1,$F13*0.6,$F13*0.4)) ,""),if($E13="Minors",0,if($E13="FA Contract",if(and(K$1<=$I13,K$1>=$H13),$F13,""),if($E13="YP Contract",if(K$1=$H13,500000,if(K$1=($H13+1),1000000,if(K$1=($H13+2),1500000,"")))))))) -> 4600000 | L13: =if($E13="","",if($E13="Dropped",if(and(L$1<=$I13,L$1>=$H13),if(Year($D13)=L$1,$F13*0.8,if((year($D13)+1)=L$1,$F13*0.6,$F13*0.4)) ,""),if($E13="Minors",0,if($E13="FA Contract",if(and(L$1<=$I13,L$1>=$H13),$F13,""),if($E13="YP Contract",if(L$1=$H13,500000,if(L$1=($H13+1),1000000,if(L$1=($H13+2),1500000,"")))))))) -> 4600000 | M13: =if($E13="","",if($E13="Dropped",if(and(M$1<=$I13,M$1>=$H13),if(Year($D13)=M$1,$F13*0.8,if((year($D13)+1)=M$1,$F13*0.6,$F13*0.4)) ,""),if($E13="Minors",0,if($E13="FA Contract",if(and(M$1<=$I13,M$1>=$H13),$F13,""),if($E13="YP Contract",if(M$1=$H13,500000,if(M$1=($H13+1),1000000,if(M$1=($H13+2),1500000,"")))))))) | N13: =if($E13="","",if($E13="Dropped",if(and(N$1<=$I13,N$1>=$H13),if(Year($D13)=N$1,$F13*0.8,if((year($D13)+1)=N$1,$F13*0.6,$F13*0.4)) ,""),if($E13="Minors",0,if($E13="FA Contract",if(and(N$1<=$I13,N$1>=$H13),$F13,""),if($E13="YP Contract",if(N$1=$H13,500000,if(N$1=($H13+1),1000000,if(N$1=($H13+2),1500000,"")))))))) | O13: =if($E13="","",if($E13="Dropped",if(and(O$1<=$I13,O$1>=$H13),if(Year($D13)=O$1,$F13*0.8,if((year($D13)+1)=O$1,$F13*0.6,$F13*0.4)) ,""),if($E13="Minors",0,if($E13="FA Contract",if(and(O$1<=$I13,O$1>=$H13),$F13,""),if($E13="YP Contract",if(O$1=$H13,500000,if(O$1=($H13+1),1000000,if(O$1=($H13+2),1500000,"")))))))) | P13: =if($E13="","",if($E13="Dropped",if(and(P$1<=$I13,P$1>=$H13),if(Year($D13)=P$1,$F13*0.8,if((year($D13)+1)=P$1,$F13*0.6,$F13*0.4)) ,""),if($E13="Minors",0,if($E13="FA Contract",if(and(P$1<=$I13,P$1>=$H13),$F13,""),if($E13="YP Contract",if(P$1=$H13,500000,if(P$1=($H13+1),1000000,if(P$1=($H13+2),1500000,""))))))))
A14: Dean Kremer | B14: Brenden Freedman | C14: 45356 | E14: FA Contract | F14: 4000000 | G14: 2 | H14: 2024 | I14: =if(H14="","",if(or($E14="FA Contract",$E14="Dropped"),$H14+$G14-1,if($E14="YP Contract",$H14+2,if(and($E14="Minors",$G14<>"YP"),$H14+$G14-1,if(and($E14="Minors",$G14="YP"),$H14+2,""))))) -> 2025 | J14: 33100000 | K14: =if($E14="","",if($E14="Dropped",if(and(K$1<=$I14,K$1>=$H14),if(Year($D14)=K$1,$F14*0.8,if((year($D14)+1)=K$1,$F14*0.6,$F14*0.4)) ,""),if($E14="Minors",0,if($E14="FA Contract",if(and(K$1<=$I14,K$1>=$H14),$F14,""),if($E14="YP Contract",if(K$1=$H14,500000,if(K$1=($H14+1),1000000,if(K$1=($H14+2),1500000,"")))))))) -> 4000000 | L14: =if($E14="","",if($E14="Dropped",if(and(L$1<=$I14,L$1>=$H14),if(Year($D14)=L$1,$F14*0.8,if((year($D14)+1)=L$1,$F14*0.6,$F14*0.4)) ,""),if($E14="Minors",0,if($E14="FA Contract",if(and(L$1<=$I14,L$1>=$H14),$F14,""),if($E14="YP Contract",if(L$1=$H14,500000,if(L$1=($H14+1),1000000,if(L$1=($H14+2),1500000,"")))))))) | M14: =if($E14="","",if($E14="Dropped",if(and(M$1<=$I14,M$1>=$H14),if(Year($D14)=M$1,$F14*0.8,if((year($D14)+1)=M$1,$F14*0.6,$F14*0.4)) ,""),if($E14="Minors",0,if($E14="FA Contract",if(and(M$1<=$I14,M$1>=$H14),$F14,""),if($E14="YP Contract",if(M$1=$H14,500000,if(M$1=($H14+1),1000000,if(M$1=($H14+2),1500000,"")))))))) | N14: =if($E14="","",if($E14="Dropped",if(and(N$1<=$I14,N$1>=$H14),if(Year($D14)=N$1,$F14*0.8,if((year($D14)+1)=N$1,$F14*0.6,$F14*0.4)) ,""),if($E14="Minors",0,if($E14="FA Contract",if(and(N$1<=$I14,N$1>=$H14),$F14,""),if($E14="YP Contract",if(N$1=$H14,500000,if(N$1=($H14+1),1000000,if(N$1=($H14+2),1500000,"")))))))) | O14: =if($E14="","",if($E14="Dropped",if(and(O$1<=$I14,O$1>=$H14),if(Year($D14)=O$1,$F14*0.8,if((year($D14)+1)=O$1,$F14*0.6,$F14*0.4)) ,""),if($E14="Minors",0,if($E14="FA Contract",if(and(O$1<=$I14,O$1>=$H14),$F14,""),if($E14="YP Contract",if(O$1=$H14,500000,if(O$1=($H14+1),1000000,if(O$1=($H14+2),1500000,"")))))))) | P14: =if($E14="","",if($E14="Dropped",if(and(P$1<=$I14,P$1>=$H14),if(Year($D14)=P$1,$F14*0.8,if((year($D14)+1)=P$1,$F14*0.6,$F14*0.4)) ,""),if($E14="Minors",0,if($E14="FA Contract",if(and(P$1<=$I14,P$1>=$H14),$F14,""),if($E14="YP Contract",if(P$1=$H14,500000,if(P$1=($H14+1),1000000,if(P$1=($H14+2),1500000,""))))))))
A15: Craig Kimbrel | B15: Brenden Freedman | C15: 45356 | E15: FA Contract | F15: 3000000 | G15: 2 | H15: 2024 | I15: =if(H15="","",if(or($E15="FA Contract",$E15="Dropped"),$H15+$G15-1,if($E15="YP Contract",$H15+2,if(and($E15="Minors",$G15<>"YP"),$H15+$G15-1,if(and($E15="Minors",$G15="YP"),$H15+2,""))))) -> 2025 | J15: 33100000 | K15: =if($E15="","",if($E15="Dropped",if(and(K$1<=$I15,K$1>=$H15),if(Year($D15)=K$1,$F15*0.8,if((year($D15)+1)=K$1,$F15*0.6,$F15*0.4)) ,""),if($E15="Minors",0,if($E15="FA Contract",if(and(K$1<=$I15,K$1>=$H15),$F15,""),if($E15="YP Contract",if(K$1=$H15,500000,if(K$1=($H15+1),1000000,if(K$1=($H15+2),1500000,"")))))))) -> 3000000 | L15: =if($E15="","",if($E15="Dropped",if(and(L$1<=$I15,L$1>=$H15),if(Year($D15)=L$1,$F15*0.8,if((year($D15)+1)=L$1,$F15*0.6,$F15*0.4)) ,""),if($E15="Minors",0,if($E15="FA Contract",if(and(L$1<=$I15,L$1>=$H15),$F15,""),if($E15="YP Contract",if(L$1=$H15,500000,if(L$1=($H15+1),1000000,if(L$1=($H15+2),1500000,"")))))))) | M15: =if($E15="","",if($E15="Dropped",if(and(M$1<=$I15,M$1>=$H15),if(Year($D15)=M$1,$F15*0.8,if((year($D15)+1)=M$1,$F15*0.6,$F15*0.4)) ,""),if($E15="Minors",0,if($E15="FA Contract",if(and(M$1<=$I15,M$1>=$H15),$F15,""),if($E15="YP Contract",if(M$1=$H15,500000,if(M$1=($H15+1),1000000,if(M$1=($H15+2),1500000,"")))))))) | N15: =if($E15="","",if($E15="Dropped",if(and(N$1<=$I15,N$1>=$H15),if(Year($D15)=N$1,$F15*0.8,if((year($D15)+1)=N$1,$F15*0.6,$F15*0.4)) ,""),if($E15="Minors",0,if($E15="FA Contract",if(and(N$1<=$I15,N$1>=$H15),$F15,""),if($E15="YP Contract",if(N$1=$H15,500000,if(N$1=($H15+1),1000000,if(N$1=($H15+2),1500000,"")))))))) | O15: =if($E15="","",if($E15="Dropped",if(and(O$1<=$I15,O$1>=$H15),if(Year($D15)=O$1,$F15*0.8,if((year($D15)+1)=O$1,$F15*0.6,$F15*0.4)) ,""),if($E15="Minors",0,if($E15="FA Contract",if(and(O$1<=$I15,O$1>=$H15),$F15,""),if($E15="YP Contract",if(O$1=$H15,500000,if(O$1=($H15+1),1000000,if(O$1=($H15+2),1500000,"")))))))) | P15: =if($E15="","",if($E15="Dropped",if(and(P$1<=$I15,P$1>=$H15),if(Year($D15)=P$1,$F15*0.8,if((year($D15)+1)=P$1,$F15*0.6,$F15*0.4)) ,""),if($E15="Minors",0,if($E15="FA Contract",if(and(P$1<=$I15,P$1>=$H15),$F15,""),if($E15="YP Contract",if(P$1=$H15,500000,if(P$1=($H15+1),1000000,if(P$1=($H15+2),1500000,""))))))))
... A20: Triston McKenzie | B20: Brenden Freedman | C20: 45318 | E20: FA Contract | F20: 2000000 | G20: 2 | H20: 2024 | I20: =if(H20="","",if(or($E20="FA Contract",$E20="Dropped"),$H20+$G20-1,if($E20="YP Contract",$H20+2,if(and($E20="Minors",$G20<>"YP"),$H20+$G20-1,if(and($E20="Minors",$G20="YP"),$H20+2,""))))) -> 2025 | J20: 33100000 | K20: =if($E20="","",if($E20="Dropped",if(and(K$1<=$I20,K$1>=$H20),if(Year($D20)=K$1,$F20*0.8,if((year($D20)+1)=K$1,$F20*0.6,$F20*0.4)) ,""),if($E20="Minors",0,if($E20="FA Contract",if(and(K$1<=$I20,K$1>=$H20),$F20,""),if($E20="YP Contract",if(K$1=$H20,500000,if(K$1=($H20+1),1000000,if(K$1=($H20+2),1500000,"")))))))) -> 2000000 | L20: =if($E20="","",if($E20="Dropped",if(and(L$1<=$I20,L$1>=$H20),if(Year($D20)=L$1,$F20*0.8,if((year($D20)+1)=L$1,$F20*0.6,$F20*0.4)) ,""),if($E20="Minors",0,if($E20="FA Contract",if(and(L$1<=$I20,L$1>=$H20),$F20,""),if($E20="YP Contract",if(L$1=$H20,500000,if(L$1=($H20+1),1000000,if(L$1=($H20+2),1500000,"")))))))) | M20: =if($E20="","",if($E20="Dropped",if(and(M$1<=$I20,M$1>=$H20),if(Year($D20)=M$1,$F20*0.8,if((year($D20)+1)=M$1,$F20*0.6,$F20*0.4)) ,""),if($E20="Minors",0,if($E20="FA Contract",if(and(M$1<=$I20,M$1>=$H20),$F20,""),if($E20="YP Contract",if(M$1=$H20,500000,if(M$1=($H20+1),1000000,if(M$1=($H20+2),1500000,"")))))))) | N20: =if($E20="","",if($E20="Dropped",if(and(N$1<=$I20,N$1>=$H20),if(Year($D20)=N$1,$F20*0.8,if((year($D20)+1)=N$1,$F20*0.6,$F20*0.4)) ,""),if($E20="Minors",0,if($E20="FA Contract",if(and(N$1<=$I20,N$1>=$H20),$F20,""),if($E20="YP Contract",if(N$1=$H20,500000,if(N$1=($H20+1),1000000,if(N$1=($H20+2),1500000,"")))))))) | O20: =if($E20="","",if($E20="Dropped",if(and(O$1<=$I20,O$1>=$H20),if(Year($D20)=O$1,$F20*0.8,if((year($D20)+1)=O$1,$F20*0.6,$F20*0.4)) ,""),if($E20="Minors",0,if($E20="FA Contract",if(and(O$1<=$I20,O$1>=$H20),$F20,""),if($E20="YP Contract",if(O$1=$H20,500000,if(O$1=($H20+1),1000000,if(O$1=($H20+2),1500000,"")))))))) | P20: =if($E20="","",if($E20="Dropped",if(and(P$1<=$I20,P$1>=$H20),if(Year($D20)=P$1,$F20*0.8,if((year($D20)+1)=P$1,$F20*0.6,$F20*0.4)) ,""),if($E20="Minors",0,if($E20="FA Contract",if(and(P$1<=$I20,P$1>=$H20),$F20,""),if($E20="YP Contract",if(P$1=$H20,500000,if(P$1=($H20+1),1000000,if(P$1=($H20+2),1500000,""))))))))
A21: Whitt Merrifield | B21: Brenden Freedman | C21: 45356 | D21: 45761 | E21: Dropped | F21: 2500000 | G21: 2 | H21: 2024 | I21: =if(H21="","",if(or($E21="FA Contract",$E21="Dropped"),$H21+$G21-1,if($E21="YP Contract",$H21+2,if(and($E21="Minors",$G21<>"YP"),$H21+$G21-1,if(and($E21="Minors",$G21="YP"),$H21+2,""))))) -> 2025 | J21: 33100000 | K21: =if($E21="","",if($E21="Dropped",if(and(K$1<=$I21,K$1>=$H21),if(Year($D21)=K$1,$F21*0.8,if((year($D21)+1)=K$1,$F21*0.6,$F21*0.4)) ,""),if($E21="Minors",0,if($E21="FA Contract",if(and(K$1<=$I21,K$1>=$H21),$F21,""),if($E21="YP Contract",if(K$1=$H21,500000,if(K$1=($H21+1),1000000,if(K$1=($H21+2),1500000,"")))))))) -> 2000000 | L21: =if($E21="","",if($E21="Dropped",if(and(L$1<=$I21,L$1>=$H21),if(Year($D21)=L$1,$F21*0.8,if((year($D21)+1)=L$1,$F21*0.6,$F21*0.4)) ,""),if($E21="Minors",0,if($E21="FA Contract",if(and(L$1<=$I21,L$1>=$H21),$F21,""),if($E21="YP Contract",if(L$1=$H21,500000,if(L$1=($H21+1),1000000,if(L$1=($H21+2),1500000,"")))))))) | M21: =if($E21="","",if($E21="Dropped",if(and(M$1<=$I21,M$1>=$H21),if(Year($D21)=M$1,$F21*0.8,if((year($D21)+1)=M$1,$F21*0.6,$F21*0.4)) ,""),if($E21="Minors",0,if($E21="FA Contract",if(and(M$1<=$I21,M$1>=$H21),$F21,""),if($E21="YP Contract",if(M$1=$H21,500000,if(M$1=($H21+1),1000000,if(M$1=($H21+2),1500000,"")))))))) | N21: =if($E21="","",if($E21="Dropped",if(and(N$1<=$I21,N$1>=$H21),if(Year($D21)=N$1,$F21*0.8,if((year($D21)+1)=N$1,$F21*0.6,$F21*0.4)) ,""),if($E21="Minors",0,if($E21="FA Contract",if(and(N$1<=$I21,N$1>=$H21),$F21,""),if($E21="YP Contract",if(N$1=$H21,500000,if(N$1=($H21+1),1000000,if(N$1=($H21+2),1500000,"")))))))) | O21: =if($E21="","",if($E21="Dropped",if(and(O$1<=$I21,O$1>=$H21),if(Year($D21)=O$1,$F21*0.8,if((year($D21)+1)=O$1,$F21*0.6,$F21*0.4)) ,""),if($E21="Minors",0,if($E21="FA Contract",if(and(O$1<=$I21,O$1>=$H21),$F21,""),if($E21="YP Contract",if(O$1=$H21,500000,if(O$1=($H21+1),1000000,if(O$1=($H21+2),1500000,"")))))))) | P21: =if($E21="","",if($E21="Dropped",if(and(P$1<=$I21,P$1>=$H21),if(Year($D21)=P$1,$F21*0.8,if((year($D21)+1)=P$1,$F21*0.6,$F21*0.4)) ,""),if($E21="Minors",0,if($E21="FA Contract",if(and(P$1<=$I21,P$1>=$H21),$F21,""),if($E21="YP Contract",if(P$1=$H21,500000,if(P$1=($H21+1),1000000,if(P$1=($H21+2),1500000,""))))))))
A22: AJ Minter | B22: Brenden Freedman | C22: 45356 | E22: FA Contract | F22: 1500000 | G22: 2 | H22: 2024 | I22: =if(H22="","",if(or($E22="FA Contract",$E22="Dropped"),$H22+$G22-1,if($E22="YP Contract",$H22+2,if(and($E22="Minors",$G22<>"YP"),$H22+$G22-1,if(and($E22="Minors",$G22="YP"),$H22+2,""))))) -> 2025 | J22: 33100000 | K22: =if($E22="","",if($E22="Dropped",if(and(K$1<=$I22,K$1>=$H22),if(Year($D22)=K$1,$F22*0.8,if((year($D22)+1)=K$1,$F22*0.6,$F22*0.4)) ,""),if($E22="Minors",0,if($E22="FA Contract",if(and(K$1<=$I22,K$1>=$H22),$F22,""),if($E22="YP Contract",if(K$1=$H22,500000,if(K$1=($H22+1),1000000,if(K$1=($H22+2),1500000,"")))))))) -> 1500000 | L22: =if($E22="","",if($E22="Dropped",if(and(L$1<=$I22,L$1>=$H22),if(Year($D22)=L$1,$F22*0.8,if((year($D22)+1)=L$1,$F22*0.6,$F22*0.4)) ,""),if($E22="Minors",0,if($E22="FA Contract",if(and(L$1<=$I22,L$1>=$H22),$F22,""),if($E22="YP Contract",if(L$1=$H22,500000,if(L$1=($H22+1),1000000,if(L$1=($H22+2),1500000,"")))))))) | M22: =if($E22="","",if($E22="Dropped",if(and(M$1<=$I22,M$1>=$H22),if(Year($D22)=M$1,$F22*0.8,if((year($D22)+1)=M$1,$F22*0.6,$F22*0.4)) ,""),if($E22="Minors",0,if($E22="FA Contract",if(and(M$1<=$I22,M$1>=$H22),$F22,""),if($E22="YP Contract",if(M$1=$H22,500000,if(M$1=($H22+1),1000000,if(M$1=($H22+2),1500000,"")))))))) | N22: =if($E22="","",if($E22="Dropped",if(and(N$1<=$I22,N$1>=$H22),if(Year($D22)=N$1,$F22*0.8,if((year($D22)+1)=N$1,$F22*0.6,$F22*0.4)) ,""),if($E22="Minors",0,if($E22="FA Contract",if(and(N$1<=$I22,N$1>=$H22),$F22,""),if($E22="YP Contract",if(N$1=$H22,500000,if(N$1=($H22+1),1000000,if(N$1=($H22+2),1500000,"")))))))) | O22: =if($E22="","",if($E22="Dropped",if(and(O$1<=$I22,O$1>=$H22),if(Year($D22)=O$1,$F22*0.8,if((year($D22)+1)=O$1,$F22*0.6,$F22*0.4)) ,""),if($E22="Minors",0,if($E22="FA Contract",if(and(O$1<=$I22,O$1>=$H22),$F22,""),if($E22="YP Contract",if(O$1=$H22,500000,if(O$1=($H22+1),1000000,if(O$1=($H22+2),1500000,"")))))))) | P22: =if($E22="","",if($E22="Dropped",if(and(P$1<=$I22,P$1>=$H22),if(Year($D22)=P$1,$F22*0.8,if((year($D22)+1)=P$1,$F22*0.6,$F22*0.4)) ,""),if($E22="Minors",0,if($E22="FA Contract",if(and(P$1<=$I22,P$1>=$H22),$F22,""),if($E22="YP Contract",if(P$1=$H22,500000,if(P$1=($H22+1),1000000,if(P$1=($H22+2),1500000,""))))))))
A23: Alex Verdugo | B23: Brenden Freedman | C23: 45356 | E23: FA Contract | F23: 1500000 | G23: 2 | H23: 2024 | I23: =if(H23="","",if(or($E23="FA Contract",$E23="Dropped"),$H23+$G23-1,if($E23="YP Contract",$H23+2,if(and($E23="Minors",$G23<>"YP"),$H23+$G23-1,if(and($E23="Minors",$G23="YP"),$H23+2,""))))) -> 2025 | J23: 33100000 | K23: =if($E23="","",if($E23="Dropped",if(and(K$1<=$I23,K$1>=$H23),if(Year($D23)=K$1,$F23*0.8,if((year($D23)+1)=K$1,$F23*0.6,$F23*0.4)) ,""),if($E23="Minors",0,if($E23="FA Contract",if(and(K$1<=$I23,K$1>=$H23),$F23,""),if($E23="YP Contract",if(K$1=$H23,500000,if(K$1=($H23+1),1000000,if(K$1=($H23+2),1500000,"")))))))) -> 1500000 | L23: =if($E23="","",if($E23="Dropped",if(and(L$1<=$I23,L$1>=$H23),if(Year($D23)=L$1,$F23*0.8,if((year($D23)+1)=L$1,$F23*0.6,$F23*0.4)) ,""),if($E23="Minors",0,if($E23="FA Contract",if(and(L$1<=$I23,L$1>=$H23),$F23,""),if($E23="YP Contract",if(L$1=$H23,500000,if(L$1=($H23+1),1000000,if(L$1=($H23+2),1500000,"")))))))) | M23: =if($E23="","",if($E23="Dropped",if(and(M$1<=$I23,M$1>=$H23),if(Year($D23)=M$1,$F23*0.8,if((year($D23)+1)=M$1,$F23*0.6,$F23*0.4)) ,""),if($E23="Minors",0,if($E23="FA Contract",if(and(M$1<=$I23,M$1>=$H23),$F23,""),if($E23="YP Contract",if(M$1=$H23,500000,if(M$1=($H23+1),1000000,if(M$1=($H23+2),1500000,"")))))))) | N23: =if($E23="","",if($E23="Dropped",if(and(N$1<=$I23,N$1>=$H23),if(Year($D23)=N$1,$F23*0.8,if((year($D23)+1)=N$1,$F23*0.6,$F23*0.4)) ,""),if($E23="Minors",0,if($E23="FA Contract",if(and(N$1<=$I23,N$1>=$H23),$F23,""),if($E23="YP Contract",if(N$1=$H23,500000,if(N$1=($H23+1),1000000,if(N$1=($H23+2),1500000,"")))))))) | O23: =if($E23="","",if($E23="Dropped",if(and(O$1<=$I23,O$1>=$H23),if(Year($D23)=O$1,$F23*0.8,if((year($D23)+1)=O$1,$F23*0.6,$F23*0.4)) ,""),if($E23="Minors",0,if($E23="FA Contract",if(and(O$1<=$I23,O$1>=$H23),$F23,""),if($E23="YP Contract",if(O$1=$H23,500000,if(O$1=($H23+1),1000000,if(O$1=($H23+2),1500000,"")))))))) | P23: =if($E23="","",if($E23="Dropped",if(and(P$1<=$I23,P$1>=$H23),if(Year($D23)=P$1,$F23*0.8,if((year($D23)+1)=P$1,$F23*0.6,$F23*0.4)) ,""),if($E23="Minors",0,if($E23="FA Contract",if(and(P$1<=$I23,P$1>=$H23),$F23,""),if($E23="YP Contract",if(P$1=$H23,500000,if(P$1=($H23+1),1000000,if(P$1=($H23+2),1500000,""))))))))
A24: Brandon Pfadt | B24: Brenden Freedman | C24: 45343 | E24: YP Contract | F24: YP | G24: YP | H24: 2023 | I24: =if(H24="","",if(or($E24="FA Contract",$E24="Dropped"),$H24+$G24-1,if($E24="YP Contract",$H24+2,if(and($E24="Minors",$G24<>"YP"),$H24+$G24-1,if(and($E24="Minors",$G24="YP"),$H24+2,""))))) -> 2025 | J24: 33100000 | K24: =if($E24="","",if($E24="Dropped",if(and(K$1<=$I24,K$1>=$H24),if(Year($D24)=K$1,$F24*0.8,if((year($D24)+1)=K$1,$F24*0.6,$F24*0.4)) ,""),if($E24="Minors",0,if($E24="FA Contract",if(and(K$1<=$I24,K$1>=$H24),$F24,""),if($E24="YP Contract",if(K$1=$H24,500000,if(K$1=($H24+1),1000000,if(K$1=($H24+2),1500000,"")))))))) -> 1500000 | L24: =if($E24="","",if($E24="Dropped",if(and(L$1<=$I24,L$1>=$H24),if(Year($D24)=L$1,$F24*0.8,if((year($D24)+1)=L$1,$F24*0.6,$F24*0.4)) ,""),if($E24="Minors",0,if($E24="FA Contract",if(and(L$1<=$I24,L$1>=$H24),$F24,""),if($E24="YP Contract",if(L$1=$H24,500000,if(L$1=($H24+1),1000000,if(L$1=($H24+2),1500000,"")))))))) | M24: =if($E24="","",if($E24="Dropped",if(and(M$1<=$I24,M$1>=$H24),if(Year($D24)=M$1,$F24*0.8,if((year($D24)+1)=M$1,$F24*0.6,$F24*0.4)) ,""),if($E24="Minors",0,if($E24="FA Contract",if(and(M$1<=$I24,M$1>=$H24),$F24,""),if($E24="YP Contract",if(M$1=$H24,500000,if(M$1=($H24+1),1000000,if(M$1=($H24+2),1500000,"")))))))) | N24: =if($E24="","",if($E24="Dropped",if(and(N$1<=$I24,N$1>=$H24),if(Year($D24)=N$1,$F24*0.8,if((year($D24)+1)=N$1,$F24*0.6,$F24*0.4)) ,""),if($E24="Minors",0,if($E24="FA Contract",if(and(N$1<=$I24,N$1>=$H24),$F24,""),if($E24="YP Contract",if(N$1=$H24,500000,if(N$1=($H24+1),1000000,if(N$1=($H24+2),1500000,"")))))))) | O24: =if($E24="","",if($E24="Dropped",if(and(O$1<=$I24,O$1>=$H24),if(Year($D24)=O$1,$F24*0.8,if((year($D24)+1)=O$1,$F24*0.6,$F24*0.4)) ,""),if($E24="Minors",0,if($E24="FA Contract",if(and(O$1<=$I24,O$1>=$H24),$F24,""),if($E24="YP Contract",if(O$1=$H24,500000,if(O$1=($H24+1),1000000,if(O$1=($H24+2),1500000,"")))))))) | P24: =if($E24="","",if($E24="Dropped",if(and(P$1<=$I24,P$1>=$H24),if(Year($D24)=P$1,$F24*0.8,if((year($D24)+1)=P$1,$F24*0.6,$F24*0.4)) ,""),if($E24="Minors",0,if($E24="FA Contract",if(and(P$1<=$I24,P$1>=$H24),$F24,""),if($E24="YP Contract",if(P$1=$H24,500000,if(P$1=($H24+1),1000000,if(P$1=($H24+2),1500000,""))))))))
A25: Ezequiel Tovar | B25: Brenden Freedman | C25: 45343 | E25: YP Contract | F25: YP | G25: YP | H25: 2023 | I25: =if(H25="","",if(or($E25="FA Contract",$E25="Dropped"),$H25+$G25-1,if($E25="YP Contract",$H25+2,if(and($E25="Minors",$G25<>"YP"),$H25+$G25-1,if(and($E25="Minors",$G25="YP"),$H25+2,""))))) -> 2025 | J25: 33100000 | K25: =if($E25="","",if($E25="Dropped",if(and(K$1<=$I25,K$1>=$H25),if(Year($D25)=K$1,$F25*0.8,if((year($D25)+1)=K$1,$F25*0.6,$F25*0.4)) ,""),if($E25="Minors",0,if($E25="FA Contract",if(and(K$1<=$I25,K$1>=$H25),$F25,""),if($E25="YP Contract",if(K$1=$H25,500000,if(K$1=($H25+1),1000000,if(K$1=($H25+2),1500000,"")))))))) -> 1500000 | L25: =if($E25="","",if($E25="Dropped",if(and(L$1<=$I25,L$1>=$H25),if(Year($D25)=L$1,$F25*0.8,if((year($D25)+1)=L$1,$F25*0.6,$F25*0.4)) ,""),if($E25="Minors",0,if($E25="FA Contract",if(and(L$1<=$I25,L$1>=$H25),$F25,""),if($E25="YP Contract",if(L$1=$H25,500000,if(L$1=($H25+1),1000000,if(L$1=($H25+2),1500000,"")))))))) | M25: =if($E25="","",if($E25="Dropped",if(and(M$1<=$I25,M$1>=$H25),if(Year($D25)=M$1,$F25*0.8,if((year($D25)+1)=M$1,$F25*0.6,$F25*0.4)) ,""),if($E25="Minors",0,if($E25="FA Contract",if(and(M$1<=$I25,M$1>=$H25),$F25,""),if($E25="YP Contract",if(M$1=$H25,500000,if(M$1=($H25+1),1000000,if(M$1=($H25+2),1500000,"")))))))) | N25: =if($E25="","",if($E25="Dropped",if(and(N$1<=$I25,N$1>=$H25),if(Year($D25)=N$1,$F25*0.8,if((year($D25)+1)=N$1,$F25*0.6,$F25*0.4)) ,""),if($E25="Minors",0,if($E25="FA Contract",if(and(N$1<=$I25,N$1>=$H25),$F25,""),if($E25="YP Contract",if(N$1=$H25,500000,if(N$1=($H25+1),1000000,if(N$1=($H25+2),1500000,"")))))))) | O25: =if($E25="","",if($E25="Dropped",if(and(O$1<=$I25,O$1>=$H25),if(Year($D25)=O$1,$F25*0.8,if((year($D25)+1)=O$1,$F25*0.6,$F25*0.4)) ,""),if($E25="Minors",0,if($E25="FA Contract",if(and(O$1<=$I25,O$1>=$H25),$F25,""),if($E25="YP Contract",if(O$1=$H25,500000,if(O$1=($H25+1),1000000,if(O$1=($H25+2),1500000,"")))))))) | P25: =if($E25="","",if($E25="Dropped",if(and(P$1<=$I25,P$1>=$H25),if(Year($D25)=P$1,$F25*0.8,if((year($D25)+1)=P$1,$F25*0.6,$F25*0.4)) ,""),if($E25="Minors",0,if($E25="FA Contract",if(and(P$1<=$I25,P$1>=$H25),$F25,""),if($E25="YP Contract",if(P$1=$H25,500000,if(P$1=($H25+1),1000000,if(P$1=($H25+2),1500000,""))))))))
A26: Reese Olson | B26: Brenden Freedman | C26: 45343 | E26: YP Contract | F26: YP | G26: YP | H26: 2023 | I26: =if(H26="","",if(or($E26="FA Contract",$E26="Dropped"),$H26+$G26-1,if($E26="YP Contract",$H26+2,if(and($E26="Minors",$G26<>"YP"),$H26+$G26-1,if(and($E26="Minors",$G26="YP"),$H26+2,""))))) -> 2025 | J26: 33100000 | K26: =if($E26="","",if($E26="Dropped",if(and(K$1<=$I26,K$1>=$H26),if(Year($D26)=K$1,$F26*0.8,if((year($D26)+1)=K$1,$F26*0.6,$F26*0.4)) ,""),if($E26="Minors",0,if($E26="FA Contract",if(and(K$1<=$I26,K$1>=$H26),$F26,""),if($E26="YP Contract",if(K$1=$H26,500000,if(K$1=($H26+1),1000000,if(K$1=($H26+2),1500000,"")))))))) -> 1500000 | L26: =if($E26="","",if($E26="Dropped",if(and(L$1<=$I26,L$1>=$H26),if(Year($D26)=L$1,$F26*0.8,if((year($D26)+1)=L$1,$F26*0.6,$F26*0.4)) ,""),if($E26="Minors",0,if($E26="FA Contract",if(and(L$1<=$I26,L$1>=$H26),$F26,""),if($E26="YP Contract",if(L$1=$H26,500000,if(L$1=($H26+1),1000000,if(L$1=($H26+2),1500000,"")))))))) | M26: =if($E26="","",if($E26="Dropped",if(and(M$1<=$I26,M$1>=$H26),if(Year($D26)=M$1,$F26*0.8,if((year($D26)+1)=M$1,$F26*0.6,$F26*0.4)) ,""),if($E26="Minors",0,if($E26="FA Contract",if(and(M$1<=$I26,M$1>=$H26),$F26,""),if($E26="YP Contract",if(M$1=$H26,500000,if(M$1=($H26+1),1000000,if(M$1=($H26+2),1500000,"")))))))) | N26: =if($E26="","",if($E26="Dropped",if(and(N$1<=$I26,N$1>=$H26),if(Year($D26)=N$1,$F26*0.8,if((year($D26)+1)=N$1,$F26*0.6,$F26*0.4)) ,""),if($E26="Minors",0,if($E26="FA Contract",if(and(N$1<=$I26,N$1>=$H26),$F26,""),if($E26="YP Contract",if(N$1=$H26,500000,if(N$1=($H26+1),1000000,if(N$1=($H26+2),1500000,"")))))))) | O26: =if($E26="","",if($E26="Dropped",if(and(O$1<=$I26,O$1>=$H26),if(Year($D26)=O$1,$F26*0.8,if((year($D26)+1)=O$1,$F26*0.6,$F26*0.4)) ,""),if($E26="Minors",0,if($E26="FA Contract",if(and(O$1<=$I26,O$1>=$H26),$F26,""),if($E26="YP Contract",if(O$1=$H26,500000,if(O$1=($H26+1),1000000,if(O$1=($H26+2),1500000,"")))))))) | P26: =if($E26="","",if($E26="Dropped",if(and(P$1<=$I26,P$1>=$H26),if(Year($D26)=P$1,$F26*0.8,if((year($D26)+1)=P$1,$F26*0.6,$F26*0.4)) ,""),if($E26="Minors",0,if($E26="FA Contract",if(and(P$1<=$I26,P$1>=$H26),$F26,""),if($E26="YP Contract",if(P$1=$H26,500000,if(P$1=($H26+1),1000000,if(P$1=($H26+2),1500000,""))))))))
A27: Gavin Stone | B27: Brenden Freedman | C27: 45346 | E27: YP Contract | F27: YP | G27: YP | H27: 2024 | I27: =if(H27="","",if(or($E27="FA Contract",$E27="Dropped"),$H27+$G27-1,if($E27="YP Contract",$H27+2,if(and($E27="Minors",$G27<>"YP"),$H27+$G27-1,if(and($E27="Minors",$G27="YP"),$H27+2,""))))) -> 2026 | J27: 33100000 | K27: =if($E27="","",if($E27="Dropped",if(and(K$1<=$I27,K$1>=$H27),if(Year($D27)=K$1,$F27*0.8,if((year($D27)+1)=K$1,$F27*0.6,$F27*0.4)) ,""),if($E27="Minors",0,if($E27="FA Contract",if(and(K$1<=$I27,K$1>=$H27),$F27,""),if($E27="YP Contract",if(K$1=$H27,500000,if(K$1=($H27+1),1000000,if(K$1=($H27+2),1500000,"")))))))) -> 1000000 | L27: =if($E27="","",if($E27="Dropped",if(and(L$1<=$I27,L$1>=$H27),if(Year($D27)=L$1,$F27*0.8,if((year($D27)+1)=L$1,$F27*0.6,$F27*0.4)) ,""),if($E27="Minors",0,if($E27="FA Contract",if(and(L$1<=$I27,L$1>=$H27),$F27,""),if($E27="YP Contract",if(L$1=$H27,500000,if(L$1=($H27+1),1000000,if(L$1=($H27+2),1500000,"")))))))) -> 1500000 | M27: =if($E27="","",if($E27="Dropped",if(and(M$1<=$I27,M$1>=$H27),if(Year($D27)=M$1,$F27*0.8,if((year($D27)+1)=M$1,$F27*0.6,$F27*0.4)) ,""),if($E27="Minors",0,if($E27="FA Contract",if(and(M$1<=$I27,M$1>=$H27),$F27,""),if($E27="YP Contract",if(M$1=$H27,500000,if(M$1=($H27+1),1000000,if(M$1=($H27+2),1500000,"")))))))) | N27: =if($E27="","",if($E27="Dropped",if(and(N$1<=$I27,N$1>=$H27),if(Year($D27)=N$1,$F27*0.8,if((year($D27)+1)=N$1,$F27*0.6,$F27*0.4)) ,""),if($E27="Minors",0,if($E27="FA Contract",if(and(N$1<=$I27,N$1>=$H27),$F27,""),if($E27="YP Contract",if(N$1=$H27,500000,if(N$1=($H27+1),1000000,if(N$1=($H27+2),1500000,"")))))))) | O27: =if($E27="","",if($E27="Dropped",if(and(O$1<=$I27,O$1>=$H27),if(Year($D27)=O$1,$F27*0.8,if((year($D27)+1)=O$1,$F27*0.6,$F27*0.4)) ,""),if($E27="Minors",0,if($E27="FA Contract",if(and(O$1<=$I27,O$1>=$H27),$F27,""),if($E27="YP Contract",if(O$1=$H27,500000,if(O$1=($H27+1),1000000,if(O$1=($H27+2),1500000,"")))))))) | P27: =if($E27="","",if($E27="Dropped",if(and(P$1<=$I27,P$1>=$H27),if(Year($D27)=P$1,$F27*0.8,if((year($D27)+1)=P$1,$F27*0.6,$F27*0.4)) ,""),if($E27="Minors",0,if($E27="FA Contract",if(and(P$1<=$I27,P$1>=$H27),$F27,""),if($E27="YP Contract",if(P$1=$H27,500000,if(P$1=($H27+1),1000000,if(P$1=($H27+2),1500000,""))))))))
A28: Ivan Herrera | B28: Brenden Freedman | C28: 45350 | E28: YP Contract | F28: YP | G28: YP | H28: 2024 | I28: =if(H28="","",if(or($E28="FA Contract",$E28="Dropped"),$H28+$G28-1,if($E28="YP Contract",$H28+2,if(and($E28="Minors",$G28<>"YP"),$H28+$G28-1,if(and($E28="Minors",$G28="YP"),$H28+2,""))))) -> 2026 | J28: 33100000 | K28: =if($E28="","",if($E28="Dropped",if(and(K$1<=$I28,K$1>=$H28),if(Year($D28)=K$1,$F28*0.8,if((year($D28)+1)=K$1,$F28*0.6,$F28*0.4)) ,""),if($E28="Minors",0,if($E28="FA Contract",if(and(K$1<=$I28,K$1>=$H28),$F28,""),if($E28="YP Contract",if(K$1=$H28,500000,if(K$1=($H28+1),1000000,if(K$1=($H28+2),1500000,"")))))))) -> 1000000 | L28: =if($E28="","",if($E28="Dropped",if(and(L$1<=$I28,L$1>=$H28),if(Year($D28)=L$1,$F28*0.8,if((year($D28)+1)=L$1,$F28*0.6,$F28*0.4)) ,""),if($E28="Minors",0,if($E28="FA Contract",if(and(L$1<=$I28,L$1>=$H28),$F28,""),if($E28="YP Contract",if(L$1=$H28,500000,if(L$1=($H28+1),1000000,if(L$1=($H28+2),1500000,"")))))))) -> 1500000 | M28: =if($E28="","",if($E28="Dropped",if(and(M$1<=$I28,M$1>=$H28),if(Year($D28)=M$1,$F28*0.8,if((year($D28)+1)=M$1,$F28*0.6,$F28*0.4)) ,""),if($E28="Minors",0,if($E28="FA Contract",if(and(M$1<=$I28,M$1>=$H28),$F28,""),if($E28="YP Contract",if(M$1=$H28,500000,if(M$1=($H28+1),1000000,if(M$1=($H28+2),1500000,"")))))))) | N28: =if($E28="","",if($E28="Dropped",if(and(N$1<=$I28,N$1>=$H28),if(Year($D28)=N$1,$F28*0.8,if((year($D28)+1)=N$1,$F28*0.6,$F28*0.4)) ,""),if($E28="Minors",0,if($E28="FA Contract",if(and(N$1<=$I28,N$1>=$H28),$F28,""),if($E28="YP Contract",if(N$1=$H28,500000,if(N$1=($H28+1),1000000,if(N$1=($H28+2),1500000,"")))))))) | O28: =if($E28="","",if($E28="Dropped",if(and(O$1<=$I28,O$1>=$H28),if(Year($D28)=O$1,$F28*0.8,if((year($D28)+1)=O$1,$F28*0.6,$F28*0.4)) ,""),if($E28="Minors",0,if($E28="FA Contract",if(and(O$1<=$I28,O$1>=$H28),$F28,""),if($E28="YP Contract",if(O$1=$H28,500000,if(O$1=($H28+1),1000000,if(O$1=($H28+2),1500000,"")))))))) | P28: =if($E28="","",if($E28="Dropped",if(and(P$1<=$I28,P$1>=$H28),if(Year($D28)=P$1,$F28*0.8,if((year($D28)+1)=P$1,$F28*0.6,$F28*0.4)) ,""),if($E28="Minors",0,if($E28="FA Contract",if(and(P$1<=$I28,P$1>=$H28),$F28,""),if($E28="YP Contract",if(P$1=$H28,500000,if(P$1=($H28+1),1000000,if(P$1=($H28+2),1500000,""))))))))
A29: Jackson Holliday | B29: Brenden Freedman | C29: 45343 | E29: YP Contract | F29: YP | G29: YP | H29: 2024 | I29: =if(H29="","",if(or($E29="FA Contract",$E29="Dropped"),$H29+$G29-1,if($E29="YP Contract",$H29+2,if(and($E29="Minors",$G29<>"YP"),$H29+$G29-1,if(and($E29="Minors",$G29="YP"),$H29+2,""))))) -> 2026 | J29: 33100000 | K29: =if($E29="","",if($E29="Dropped",if(and(K$1<=$I29,K$1>=$H29),if(Year($D29)=K$1,$F29*0.8,if((year($D29)+1)=K$1,$F29*0.6,$F29*0.4)) ,""),if($E29="Minors",0,if($E29="FA Contract",if(and(K$1<=$I29,K$1>=$H29),$F29,""),if($E29="YP Contract",if(K$1=$H29,500000,if(K$1=($H29+1),1000000,if(K$1=($H29+2),1500000,"")))))))) -> 1000000 | L29: =if($E29="","",if($E29="Dropped",if(and(L$1<=$I29,L$1>=$H29),if(Year($D29)=L$1,$F29*0.8,if((year($D29)+1)=L$1,$F29*0.6,$F29*0.4)) ,""),if($E29="Minors",0,if($E29="FA Contract",if(and(L$1<=$I29,L$1>=$H29),$F29,""),if($E29="YP Contract",if(L$1=$H29,500000,if(L$1=($H29+1),1000000,if(L$1=($H29+2),1500000,"")))))))) -> 1500000 | M29: =if($E29="","",if($E29="Dropped",if(and(M$1<=$I29,M$1>=$H29),if(Year($D29)=M$1,$F29*0.8,if((year($D29)+1)=M$1,$F29*0.6,$F29*0.4)) ,""),if($E29="Minors",0,if($E29="FA Contract",if(and(M$1<=$I29,M$1>=$H29),$F29,""),if($E29="YP Contract",if(M$1=$H29,500000,if(M$1=($H29+1),1000000,if(M$1=($H29+2),1500000,"")))))))) | N29: =if($E29="","",if($E29="Dropped",if(and(N$1<=$I29,N$1>=$H29),if(Year($D29)=N$1,$F29*0.8,if((year($D29)+1)=N$1,$F29*0.6,$F29*0.4)) ,""),if($E29="Minors",0,if($E29="FA Contract",if(and(N$1<=$I29,N$1>=$H29),$F29,""),if($E29="YP Contract",if(N$1=$H29,500000,if(N$1=($H29+1),1000000,if(N$1=($H29+2),1500000,"")))))))) | O29: =if($E29="","",if($E29="Dropped",if(and(O$1<=$I29,O$1>=$H29),if(Year($D29)=O$1,$F29*0.8,if((year($D29)+1)=O$1,$F29*0.6,$F29*0.4)) ,""),if($E29="Minors",0,if($E29="FA Contract",if(and(O$1<=$I29,O$1>=$H29),$F29,""),if($E29="YP Contract",if(O$1=$H29,500000,if(O$1=($H29+1),1000000,if(O$1=($H29+2),1500000,"")))))))) | P29: =if($E29="","",if($E29="Dropped",if(and(P$1<=$I29,P$1>=$H29),if(Year($D29)=P$1,$F29*0.8,if((year($D29)+1)=P$1,$F29*0.6,$F29*0.4)) ,""),if($E29="Minors",0,if($E29="FA Contract",if(and(P$1<=$I29,P$1>=$H29),$F29,""),if($E29="YP Contract",if(P$1=$H29,500000,if(P$1=($H29+1),1000000,if(P$1=($H29+2),1500000,""))))))))
A30: Jose Siri | B30: Brenden Freedman | C30: 45356 | E30: FA Contract | F30: 1000000 | G30: 2 | H30: 2024 | I30: =if(H30="","",if(or($E30="FA Contract",$E30="Dropped"),$H30+$G30-1,if($E30="YP Contract",$H30+2,if(and($E30="Minors",$G30<>"YP"),$H30+$G30-1,if(and($E30="Minors",$G30="YP"),$H30+2,""))))) -> 2025 | J30: 33100000 | K30: =if($E30="","",if($E30="Dropped",if(and(K$1<=$I30,K$1>=$H30),if(Year($D30)=K$1,$F30*0.8,if((year($D30)+1)=K$1,$F30*0.6,$F30*0.4)) ,""),if($E30="Minors",0,if($E30="FA Contract",if(and(K$1<=$I30,K$1>=$H30),$F30,""),if($E30="YP Contract",if(K$1=$H30,500000,if(K$1=($H30+1),1000000,if(K$1=($H30+2),1500000,"")))))))) -> 1000000 | L30: =if($E30="","",if($E30="Dropped",if(and(L$1<=$I30,L$1>=$H30),if(Year($D30)=L$1,$F30*0.8,if((year($D30)+1)=L$1,$F30*0.6,$F30*0.4)) ,""),if($E30="Minors",0,if($E30="FA Contract",if(and(L$1<=$I30,L$1>=$H30),$F30,""),if($E30="YP Contract",if(L$1=$H30,500000,if(L$1=($H30+1),1000000,if(L$1=($H30+2),1500000,"")))))))) | M30: =if($E30="","",if($E30="Dropped",if(and(M$1<=$I30,M$1>=$H30),if(Year($D30)=M$1,$F30*0.8,if((year($D30)+1)=M$1,$F30*0.6,$F30*0.4)) ,""),if($E30="Minors",0,if($E30="FA Contract",if(and(M$1<=$I30,M$1>=$H30),$F30,""),if($E30="YP Contract",if(M$1=$H30,500000,if(M$1=($H30+1),1000000,if(M$1=($H30+2),1500000,"")))))))) | N30: =if($E30="","",if($E30="Dropped",if(and(N$1<=$I30,N$1>=$H30),if(Year($D30)=N$1,$F30*0.8,if((year($D30)+1)=N$1,$F30*0.6,$F30*0.4)) ,""),if($E30="Minors",0,if($E30="FA Contract",if(and(N$1<=$I30,N$1>=$H30),$F30,""),if($E30="YP Contract",if(N$1=$H30,500000,if(N$1=($H30+1),1000000,if(N$1=($H30+2),1500000,"")))))))) | O30: =if($E30="","",if($E30="Dropped",if(and(O$1<=$I30,O$1>=$H30),if(Year($D30)=O$1,$F30*0.8,if((year($D30)+1)=O$1,$F30*0.6,$F30*0.4)) ,""),if($E30="Minors",0,if($E30="FA Contract",if(and(O$1<=$I30,O$1>=$H30),$F30,""),if($E30="YP Contract",if(O$1=$H30,500000,if(O$1=($H30+1),1000000,if(O$1=($H30+2),1500000,"")))))))) | P30: =if($E30="","",if($E30="Dropped",if(and(P$1<=$I30,P$1>=$H30),if(Year($D30)=P$1,$F30*0.8,if((year($D30)+1)=P$1,$F30*0.6,$F30*0.4)) ,""),if($E30="Minors",0,if($E30="FA Contract",if(and(P$1<=$I30,P$1>=$H30),$F30,""),if($E30="YP Contract",if(P$1=$H30,500000,if(P$1=($H30+1),1000000,if(P$1=($H30+2),1500000,""))))))))
A31: Kerbert Ruiz | B31: Brenden Freedman | C31: 45356 | E31: FA Contract | F31: 1000000 | G31: 2 | H31: 2024 | I31: =if(H31="","",if(or($E31="FA Contract",$E31="Dropped"),$H31+$G31-1,if($E31="YP Contract",$H31+2,if(and($E31="Minors",$G31<>"YP"),$H31+$G31-1,if(and($E31="Minors",$G31="YP"),$H31+2,""))))) -> 2025 | J31: 33100000 | K31: =if($E31="","",if($E31="Dropped",if(and(K$1<=$I31,K$1>=$H31),if(Year($D31)=K$1,$F31*0.8,if((year($D31)+1)=K$1,$F31*0.6,$F31*0.4)) ,""),if($E31="Minors",0,if($E31="FA Contract",if(and(K$1<=$I31,K$1>=$H31),$F31,""),if($E31="YP Contract",if(K$1=$H31,500000,if(K$1=($H31+1),1000000,if(K$1=($H31+2),1500000,"")))))))) -> 1000000 | L31: =if($E31="","",if($E31="Dropped",if(and(L$1<=$I31,L$1>=$H31),if(Year($D31)=L$1,$F31*0.8,if((year($D31)+1)=L$1,$F31*0.6,$F31*0.4)) ,""),if($E31="Minors",0,if($E31="FA Contract",if(and(L$1<=$I31,L$1>=$H31),$F31,""),if($E31="YP Contract",if(L$1=$H31,500000,if(L$1=($H31+1),1000000,if(L$1=($H31+2),1500000,"")))))))) | M31: =if($E31="","",if($E31="Dropped",if(and(M$1<=$I31,M$1>=$H31),if(Year($D31)=M$1,$F31*0.8,if((year($D31)+1)=M$1,$F31*0.6,$F31*0.4)) ,""),if($E31="Minors",0,if($E31="FA Contract",if(and(M$1<=$I31,M$1>=$H31),$F31,""),if($E31="YP Contract",if(M$1=$H31,500000,if(M$1=($H31+1),1000000,if(M$1=($H31+2),1500000,"")))))))) | N31: =if($E31="","",if($E31="Dropped",if(and(N$1<=$I31,N$1>=$H31),if(Year($D31)=N$1,$F31*0.8,if((year($D31)+1)=N$1,$F31*0.6,$F31*0.4)) ,""),if($E31="Minors",0,if($E31="FA Contract",if(and(N$1<=$I31,N$1>=$H31),$F31,""),if($E31="YP Contract",if(N$1=$H31,500000,if(N$1=($H31+1),1000000,if(N$1=($H31+2),1500000,"")))))))) | O31: =if($E31="","",if($E31="Dropped",if(and(O$1<=$I31,O$1>=$H31),if(Year($D31)=O$1,$F31*0.8,if((year($D31)+1)=O$1,$F31*0.6,$F31*0.4)) ,""),if($E31="Minors",0,if($E31="FA Contract",if(and(O$1<=$I31,O$1>=$H31),$F31,""),if($E31="YP Contract",if(O$1=$H31,500000,if(O$1=($H31+1),1000000,if(O$1=($H31+2),1500000,"")))))))) | P31: =if($E31="","",if($E31="Dropped",if(and(P$1<=$I31,P$1>=$H31),if(Year($D31)=P$1,$F31*0.8,if((year($D31)+1)=P$1,$F31*0.6,$F31*0.4)) ,""),if($E31="Minors",0,if($E31="FA Contract",if(and(P$1<=$I31,P$1>=$H31),$F31,""),if($E31="YP Contract",if(P$1=$H31,500000,if(P$1=($H31+1),1000000,if(P$1=($H31+2),1500000,""))))))))
A32: Chase Burns | B32: Brenden Freedman | C32: 45684 | E32: YP Contract | F32: YP | G32: YP | H32: 2025 | I32: =if(H32="","",if(or($E32="FA Contract",$E32="Dropped"),$H32+$G32-1,if($E32="YP Contract",$H32+2,if(and($E32="Minors",$G32<>"YP"),$H32+$G32-1,if(and($E32="Minors",$G32="YP"),$H32+2,""))))) -> 2027 | J32: 33100000 | K32: =if($E32="","",if($E32="Dropped",if(and(K$1<=$I32,K$1>=$H32),if(Year($D32)=K$1,$F32*0.8,if((year($D32)+1)=K$1,$F32*0.6,$F32*0.4)) ,""),if($E32="Minors",0,if($E32="FA Contract",if(and(K$1<=$I32,K$1>=$H32),$F32,""),if($E32="YP Contract",if(K$1=$H32,500000,if(K$1=($H32+1),1000000,if(K$1=($H32+2),1500000,"")))))))) -> 500000 | L32: =if($E32="","",if($E32="Dropped",if(and(L$1<=$I32,L$1>=$H32),if(Year($D32)=L$1,$F32*0.8,if((year($D32)+1)=L$1,$F32*0.6,$F32*0.4)) ,""),if($E32="Minors",0,if($E32="FA Contract",if(and(L$1<=$I32,L$1>=$H32),$F32,""),if($E32="YP Contract",if(L$1=$H32,500000,if(L$1=($H32+1),1000000,if(L$1=($H32+2),1500000,"")))))))) -> 1000000 | M32: =if($E32="","",if($E32="Dropped",if(and(M$1<=$I32,M$1>=$H32),if(Year($D32)=M$1,$F32*0.8,if((year($D32)+1)=M$1,$F32*0.6,$F32*0.4)) ,""),if($E32="Minors",0,if($E32="FA Contract",if(and(M$1<=$I32,M$1>=$H32),$F32,""),if($E32="YP Contract",if(M$1=$H32,500000,if(M$1=($H32+1),1000000,if(M$1=($H32+2),1500000,"")))))))) -> 1500000 | N32: =if($E32="","",if($E32="Dropped",if(and(N$1<=$I32,N$1>=$H32),if(Year($D32)=N$1,$F32*0.8,if((year($D32)+1)=N$1,$F32*0.6,$F32*0.4)) ,""),if($E32="Minors",0,if($E32="FA Contract",if(and(N$1<=$I32,N$1>=$H32),$F32,""),if($E32="YP Contract",if(N$1=$H32,500000,if(N$1=($H32+1),1000000,if(N$1=($H32+2),1500000,"")))))))) | O32: =if($E32="","",if($E32="Dropped",if(and(O$1<=$I32,O$1>=$H32),if(Year($D32)=O$1,$F32*0.8,if((year($D32)+1)=O$1,$F32*0.6,$F32*0.4)) ,""),if($E32="Minors",0,if($E32="FA Contract",if(and(O$1<=$I32,O$1>=$H32),$F32,""),if($E32="YP Contract",if(O$1=$H32,500000,if(O$1=($H32+1),1000000,if(O$1=($H32+2),1500000,"")))))))) | P32: =if($E32="","",if($E32="Dropped",if(and(P$1<=$I32,P$1>=$H32),if(Year($D32)=P$1,$F32*0.8,if((year($D32)+1)=P$1,$F32*0.6,$F32*0.4)) ,""),if($E32="Minors",0,if($E32="FA Contract",if(and(P$1<=$I32,P$1>=$H32),$F32,""),if($E32="YP Contract",if(P$1=$H32,500000,if(P$1=($H32+1),1000000,if(P$1=($H32+2),1500000,""))))))))
A33: Colby Thomas | B33: Brenden Freedman | C33: 45698 | E33: YP Contract | F33: YP | G33: YP | H33: 2025 | I33: =if(H33="","",if(or($E33="FA Contract",$E33="Dropped"),$H33+$G33-1,if($E33="YP Contract",$H33+2,if(and($E33="Minors",$G33<>"YP"),$H33+$G33-1,if(and($E33="Minors",$G33="YP"),$H33+2,""))))) -> 2027 | J33: 33100000 | K33: =if($E33="","",if($E33="Dropped",if(and(K$1<=$I33,K$1>=$H33),if(Year($D33)=K$1,$F33*0.8,if((year($D33)+1)=K$1,$F33*0.6,$F33*0.4)) ,""),if($E33="Minors",0,if($E33="FA Contract",if(and(K$1<=$I33,K$1>=$H33),$F33,""),if($E33="YP Contract",if(K$1=$H33,500000,if(K$1=($H33+1),1000000,if(K$1=($H33+2),1500000,"")))))))) -> 500000 | L33: =if($E33="","",if($E33="Dropped",if(and(L$1<=$I33,L$1>=$H33),if(Year($D33)=L$1,$F33*0.8,if((year($D33)+1)=L$1,$F33*0.6,$F33*0.4)) ,""),if($E33="Minors",0,if($E33="FA Contract",if(and(L$1<=$I33,L$1>=$H33),$F33,""),if($E33="YP Contract",if(L$1=$H33,500000,if(L$1=($H33+1),1000000,if(L$1=($H33+2),1500000,"")))))))) -> 1000000 | M33: =if($E33="","",if($E33="Dropped",if(and(M$1<=$I33,M$1>=$H33),if(Year($D33)=M$1,$F33*0.8,if((year($D33)+1)=M$1,$F33*0.6,$F33*0.4)) ,""),if($E33="Minors",0,if($E33="FA Contract",if(and(M$1<=$I33,M$1>=$H33),$F33,""),if($E33="YP Contract",if(M$1=$H33,500000,if(M$1=($H33+1),1000000,if(M$1=($H33+2),1500000,"")))))))) -> 1500000 | N33: =if($E33="","",if($E33="Dropped",if(and(N$1<=$I33,N$1>=$H33),if(Year($D33)=N$1,$F33*0.8,if((year($D33)+1)=N$1,$F33*0.6,$F33*0.4)) ,""),if($E33="Minors",0,if($E33="FA Contract",if(and(N$1<=$I33,N$1>=$H33),$F33,""),if($E33="YP Contract",if(N$1=$H33,500000,if(N$1=($H33+1),1000000,if(N$1=($H33+2),1500000,"")))))))) | O33: =if($E33="","",if($E33="Dropped",if(and(O$1<=$I33,O$1>=$H33),if(Year($D33)=O$1,$F33*0.8,if((year($D33)+1)=O$1,$F33*0.6,$F33*0.4)) ,""),if($E33="Minors",0,if($E33="FA Contract",if(and(O$1<=$I33,O$1>=$H33),$F33,""),if($E33="YP Contract",if(O$1=$H33,500000,if(O$1=($H33+1),1000000,if(O$1=($H33+2),1500000,"")))))))) | P33: =if($E33="","",if($E33="Dropped",if(and(P$1<=$I33,P$1>=$H33),if(Year($D33)=P$1,$F33*0.8,if((year($D33)+1)=P$1,$F33*0.6,$F33*0.4)) ,""),if($E33="Minors",0,if($E33="FA Contract",if(and(P$1<=$I33,P$1>=$H33),$F33,""),if($E33="YP Contract",if(P$1=$H33,500000,if(P$1=($H33+1),1000000,if(P$1=($H33+2),1500000,""))))))))
A34: Dalton Rushing | B34: Brenden Freedman | C34: 45343 | E34: YP Contract | F34: YP | G34: YP | H34: 2025 | I34: =if(H34="","",if(or($E34="FA Contract",$E34="Dropped"),$H34+$G34-1,if($E34="YP Contract",$H34+2,if(and($E34="Minors",$G34<>"YP"),$H34+$G34-1,if(and($E34="Minors",$G34="YP"),$H34+2,""))))) -> 2027 | J34: 33100000 | K34: =if($E34="","",if($E34="Dropped",if(and(K$1<=$I34,K$1>=$H34),if(Year($D34)=K$1,$F34*0.8,if((year($D34)+1)=K$1,$F34*0.6,$F34*0.4)) ,""),if($E34="Minors",0,if($E34="FA Contract",if(and(K$1<=$I34,K$1>=$H34),$F34,""),if($E34="YP Contract",if(K$1=$H34,500000,if(K$1=($H34+1),1000000,if(K$1=($H34+2),1500000,"")))))))) -> 500000 | L34: =if($E34="","",if($E34="Dropped",if(and(L$1<=$I34,L$1>=$H34),if(Year($D34)=L$1,$F34*0.8,if((year($D34)+1)=L$1,$F34*0.6,$F34*0.4)) ,""),if($E34="Minors",0,if($E34="FA Contract",if(and(L$1<=$I34,L$1>=$H34),$F34,""),if($E34="YP Contract",if(L$1=$H34,500000,if(L$1=($H34+1),1000000,if(L$1=($H34+2),1500000,"")))))))) -> 1000000 | M34: =if($E34="","",if($E34="Dropped",if(and(M$1<=$I34,M$1>=$H34),if(Year($D34)=M$1,$F34*0.8,if((year($D34)+1)=M$1,$F34*0.6,$F34*0.4)) ,""),if($E34="Minors",0,if($E34="FA Contract",if(and(M$1<=$I34,M$1>=$H34),$F34,""),if($E34="YP Contract",if(M$1=$H34,500000,if(M$1=($H34+1),1000000,if(M$1=($H34+2),1500000,"")))))))) -> 1500000 | N34: =if($E34="","",if($E34="Dropped",if(and(N$1<=$I34,N$1>=$H34),if(Year($D34)=N$1,$F34*0.8,if((year($D34)+1)=N$1,$F34*0.6,$F34*0.4)) ,""),if($E34="Minors",0,if($E34="FA Contract",if(and(N$1<=$I34,N$1>=$H34),$F34,""),if($E34="YP Contract",if(N$1=$H34,500000,if(N$1=($H34+1),1000000,if(N$1=($H34+2),1500000,"")))))))) | O34: =if($E34="","",if($E34="Dropped",if(and(O$1<=$I34,O$1>=$H34),if(Year($D34)=O$1,$F34*0.8,if((year($D34)+1)=O$1,$F34*0.6,$F34*0.4)) ,""),if($E34="Minors",0,if($E34="FA Contract",if(and(O$1<=$I34,O$1>=$H34),$F34,""),if($E34="YP Contract",if(O$1=$H34,500000,if(O$1=($H34+1),1000000,if(O$1=($H34+2),1500000,"")))))))) | P34: =if($E34="","",if($E34="Dropped",if(and(P$1<=$I34,P$1>=$H34),if(Year($D34)=P$1,$F34*0.8,if((year($D34)+1)=P$1,$F34*0.6,$F34*0.4)) ,""),if($E34="Minors",0,if($E34="FA Contract",if(and(P$1<=$I34,P$1>=$H34),$F34,""),if($E34="YP Contract",if(P$1=$H34,500000,if(P$1=($H34+1),1000000,if(P$1=($H34+2),1500000,""))))))))
A35: Dylan Crews | B35: Brenden Freedman | C35: 45343 | E35: YP Contract | F35: YP | G35: YP | H35: 2025 | I35: =if(H35="","",if(or($E35="FA Contract",$E35="Dropped"),$H35+$G35-1,if($E35="YP Contract",$H35+2,if(and($E35="Minors",$G35<>"YP"),$H35+$G35-1,if(and($E35="Minors",$G35="YP"),$H35+2,""))))) -> 2027 | J35: 33100000 | K35: =if($E35="","",if($E35="Dropped",if(and(K$1<=$I35,K$1>=$H35),if(Year($D35)=K$1,$F35*0.8,if((year($D35)+1)=K$1,$F35*0.6,$F35*0.4)) ,""),if($E35="Minors",0,if($E35="FA Contract",if(and(K$1<=$I35,K$1>=$H35),$F35,""),if($E35="YP Contract",if(K$1=$H35,500000,if(K$1=($H35+1),1000000,if(K$1=($H35+2),1500000,"")))))))) -> 500000 | L35: =if($E35="","",if($E35="Dropped",if(and(L$1<=$I35,L$1>=$H35),if(Year($D35)=L$1,$F35*0.8,if((year($D35)+1)=L$1,$F35*0.6,$F35*0.4)) ,""),if($E35="Minors",0,if($E35="FA Contract",if(and(L$1<=$I35,L$1>=$H35),$F35,""),if($E35="YP Contract",if(L$1=$H35,500000,if(L$1=($H35+1),1000000,if(L$1=($H35+2),1500000,"")))))))) -> 1000000 | M35: =if($E35="","",if($E35="Dropped",if(and(M$1<=$I35,M$1>=$H35),if(Year($D35)=M$1,$F35*0.8,if((year($D35)+1)=M$1,$F35*0.6,$F35*0.4)) ,""),if($E35="Minors",0,if($E35="FA Contract",if(and(M$1<=$I35,M$1>=$H35),$F35,""),if($E35="YP Contract",if(M$1=$H35,500000,if(M$1=($H35+1),1000000,if(M$1=($H35+2),1500000,"")))))))) -> 1500000 | N35: =if($E35="","",if($E35="Dropped",if(and(N$1<=$I35,N$1>=$H35),if(Year($D35)=N$1,$F35*0.8,if((year($D35)+1)=N$1,$F35*0.6,$F35*0.4)) ,""),if($E35="Minors",0,if($E35="FA Contract",if(and(N$1<=$I35,N$1>=$H35),$F35,""),if($E35="YP Contract",if(N$1=$H35,500000,if(N$1=($H35+1),1000000,if(N$1=($H35+2),1500000,"")))))))) | O35: =if($E35="","",if($E35="Dropped",if(and(O$1<=$I35,O$1>=$H35),if(Year($D35)=O$1,$F35*0.8,if((year($D35)+1)=O$1,$F35*0.6,$F35*0.4)) ,""),if($E35="Minors",0,if($E35="FA Contract",if(and(O$1<=$I35,O$1>=$H35),$F35,""),if($E35="YP Contract",if(O$1=$H35,500000,if(O$1=($H35+1),1000000,if(O$1=($H35+2),1500000,"")))))))) | P35: =if($E35="","",if($E35="Dropped",if(and(P$1<=$I35,P$1>=$H35),if(Year($D35)=P$1,$F35*0.8,if((year($D35)+1)=P$1,$F35*0.6,$F35*0.4)) ,""),if($E35="Minors",0,if($E35="FA Contract",if(and(P$1<=$I35,P$1>=$H35),$F35,""),if($E35="YP Contract",if(P$1=$H35,500000,if(P$1=($H35+1),1000000,if(P$1=($H35+2),1500000,""))))))))
A36: Jace Jung | B36: Brenden Freedman | C36: 45343 | E36: YP Contract | F36: YP | G36: YP | H36: 2025 | I36: =if(H36="","",if(or($E36="FA Contract",$E36="Dropped"),$H36+$G36-1,if($E36="YP Contract",$H36+2,if(and($E36="Minors",$G36<>"YP"),$H36+$G36-1,if(and($E36="Minors",$G36="YP"),$H36+2,""))))) -> 2027 | J36: 33100000 | K36: =if($E36="","",if($E36="Dropped",if(and(K$1<=$I36,K$1>=$H36),if(Year($D36)=K$1,$F36*0.8,if((year($D36)+1)=K$1,$F36*0.6,$F36*0.4)) ,""),if($E36="Minors",0,if($E36="FA Contract",if(and(K$1<=$I36,K$1>=$H36),$F36,""),if($E36="YP Contract",if(K$1=$H36,500000,if(K$1=($H36+1),1000000,if(K$1=($H36+2),1500000,"")))))))) -> 500000 | L36: =if($E36="","",if($E36="Dropped",if(and(L$1<=$I36,L$1>=$H36),if(Year($D36)=L$1,$F36*0.8,if((year($D36)+1)=L$1,$F36*0.6,$F36*0.4)) ,""),if($E36="Minors",0,if($E36="FA Contract",if(and(L$1<=$I36,L$1>=$H36),$F36,""),if($E36="YP Contract",if(L$1=$H36,500000,if(L$1=($H36+1),1000000,if(L$1=($H36+2),1500000,"")))))))) -> 1000000 | M36: =if($E36="","",if($E36="Dropped",if(and(M$1<=$I36,M$1>=$H36),if(Year($D36)=M$1,$F36*0.8,if((year($D36)+1)=M$1,$F36*0.6,$F36*0.4)) ,""),if($E36="Minors",0,if($E36="FA Contract",if(and(M$1<=$I36,M$1>=$H36),$F36,""),if($E36="YP Contract",if(M$1=$H36,500000,if(M$1=($H36+1),1000000,if(M$1=($H36+2),1500000,"")))))))) -> 1500000 | N36: =if($E36="","",if($E36="Dropped",if(and(N$1<=$I36,N$1>=$H36),if(Year($D36)=N$1,$F36*0.8,if((year($D36)+1)=N$1,$F36*0.6,$F36*0.4)) ,""),if($E36="Minors",0,if($E36="FA Contract",if(and(N$1<=$I36,N$1>=$H36),$F36,""),if($E36="YP Contract",if(N$1=$H36,500000,if(N$1=($H36+1),1000000,if(N$1=($H36+2),1500000,"")))))))) | O36: =if($E36="","",if($E36="Dropped",if(and(O$1<=$I36,O$1>=$H36),if(Year($D36)=O$1,$F36*0.8,if((year($D36)+1)=O$1,$F36*0.6,$F36*0.4)) ,""),if($E36="Minors",0,if($E36="FA Contract",if(and(O$1<=$I36,O$1>=$H36),$F36,""),if($E36="YP Contract",if(O$1=$H36,500000,if(O$1=($H36+1),1000000,if(O$1=($H36+2),1500000,"")))))))) | P36: =if($E36="","",if($E36="Dropped",if(and(P$1<=$I36,P$1>=$H36),if(Year($D36)=P$1,$F36*0.8,if((year($D36)+1)=P$1,$F36*0.6,$F36*0.4)) ,""),if($E36="Minors",0,if($E36="FA Contract",if(and(P$1<=$I36,P$1>=$H36),$F36,""),if($E36="YP Contract",if(P$1=$H36,500000,if(P$1=($H36+1),1000000,if(P$1=($H36+2),1500000,""))))))))
A37: Jacob Melton | B37: Brenden Freedman | C37: 45350 | E37: YP Contract | F37: YP | G37: YP | H37: 2025 | I37: =if(H37="","",if(or($E37="FA Contract",$E37="Dropped"),$H37+$G37-1,if($E37="YP Contract",$H37+2,if(and($E37="Minors",$G37<>"YP"),$H37+$G37-1,if(and($E37="Minors",$G37="YP"),$H37+2,""))))) -> 2027 | J37: 33100000 | K37: =if($E37="","",if($E37="Dropped",if(and(K$1<=$I37,K$1>=$H37),if(Year($D37)=K$1,$F37*0.8,if((year($D37)+1)=K$1,$F37*0.6,$F37*0.4)) ,""),if($E37="Minors",0,if($E37="FA Contract",if(and(K$1<=$I37,K$1>=$H37),$F37,""),if($E37="YP Contract",if(K$1=$H37,500000,if(K$1=($H37+1),1000000,if(K$1=($H37+2),1500000,"")))))))) -> 500000 | L37: =if($E37="","",if($E37="Dropped",if(and(L$1<=$I37,L$1>=$H37),if(Year($D37)=L$1,$F37*0.8,if((year($D37)+1)=L$1,$F37*0.6,$F37*0.4)) ,""),if($E37="Minors",0,if($E37="FA Contract",if(and(L$1<=$I37,L$1>=$H37),$F37,""),if($E37="YP Contract",if(L$1=$H37,500000,if(L$1=($H37+1),1000000,if(L$1=($H37+2),1500000,"")))))))) -> 1000000 | M37: =if($E37="","",if($E37="Dropped",if(and(M$1<=$I37,M$1>=$H37),if(Year($D37)=M$1,$F37*0.8,if((year($D37)+1)=M$1,$F37*0.6,$F37*0.4)) ,""),if($E37="Minors",0,if($E37="FA Contract",if(and(M$1<=$I37,M$1>=$H37),$F37,""),if($E37="YP Contract",if(M$1=$H37,500000,if(M$1=($H37+1),1000000,if(M$1=($H37+2),1500000,"")))))))) -> 1500000 | N37: =if($E37="","",if($E37="Dropped",if(and(N$1<=$I37,N$1>=$H37),if(Year($D37)=N$1,$F37*0.8,if((year($D37)+1)=N$1,$F37*0.6,$F37*0.4)) ,""),if($E37="Minors",0,if($E37="FA Contract",if(and(N$1<=$I37,N$1>=$H37),$F37,""),if($E37="YP Contract",if(N$1=$H37,500000,if(N$1=($H37+1),1000000,if(N$1=($H37+2),1500000,"")))))))) | O37: =if($E37="","",if($E37="Dropped",if(and(O$1<=$I37,O$1>=$H37),if(Year($D37)=O$1,$F37*0.8,if((year($D37)+1)=O$1,$F37*0.6,$F37*0.4)) ,""),if($E37="Minors",0,if($E37="FA Contract",if(and(O$1<=$I37,O$1>=$H37),$F37,""),if($E37="YP Contract",if(O$1=$H37,500000,if(O$1=($H37+1),1000000,if(O$1=($H37+2),1500000,"")))))))) | P37: =if($E37="","",if($E37="Dropped",if(and(P$1<=$I37,P$1>=$H37),if(Year($D37)=P$1,$F37*0.8,if((year($D37)+1)=P$1,$F37*0.6,$F37*0.4)) ,""),if($E37="Minors",0,if($E37="FA Contract",if(and(P$1<=$I37,P$1>=$H37),$F37,""),if($E37="YP Contract",if(P$1=$H37,500000,if(P$1=($H37+1),1000000,if(P$1=($H37+2),1500000,""))))))))
A38: Jose Caballero | B38: Brenden Freedman | C38: 45721 | E38: FA Contract | F38: 500000 | G38: 1 | H38: 2025 | I38: =if(H38="","",if(or($E38="FA Contract",$E38="Dropped"),$H38+$G38-1,if($E38="YP Contract",$H38+2,if(and($E38="Minors",$G38<>"YP"),$H38+$G38-1,if(and($E38="Minors",$G38="YP"),$H38+2,""))))) -> 2025 | J38: 33100000 | K38: =if($E38="","",if($E38="Dropped",if(and(K$1<=$I38,K$1>=$H38),if(Year($D38)=K$1,$F38*0.8,if((year($D38)+1)=K$1,$F38*0.6,$F38*0.4)) ,""),if($E38="Minors",0,if($E38="FA Contract",if(and(K$1<=$I38,K$1>=$H38),$F38,""),if($E38="YP Contract",if(K$1=$H38,500000,if(K$1=($H38+1),1000000,if(K$1=($H38+2),1500000,"")))))))) -> 500000 | L38: =if($E38="","",if($E38="Dropped",if(and(L$1<=$I38,L$1>=$H38),if(Year($D38)=L$1,$F38*0.8,if((year($D38)+1)=L$1,$F38*0.6,$F38*0.4)) ,""),if($E38="Minors",0,if($E38="FA Contract",if(and(L$1<=$I38,L$1>=$H38),$F38,""),if($E38="YP Contract",if(L$1=$H38,500000,if(L$1=($H38+1),1000000,if(L$1=($H38+2),1500000,"")))))))) | M38: =if($E38="","",if($E38="Dropped",if(and(M$1<=$I38,M$1>=$H38),if(Year($D38)=M$1,$F38*0.8,if((year($D38)+1)=M$1,$F38*0.6,$F38*0.4)) ,""),if($E38="Minors",0,if($E38="FA Contract",if(and(M$1<=$I38,M$1>=$H38),$F38,""),if($E38="YP Contract",if(M$1=$H38,500000,if(M$1=($H38+1),1000000,if(M$1=($H38+2),1500000,"")))))))) | N38: =if($E38="","",if($E38="Dropped",if(and(N$1<=$I38,N$1>=$H38),if(Year($D38)=N$1,$F38*0.8,if((year($D38)+1)=N$1,$F38*0.6,$F38*0.4)) ,""),if($E38="Minors",0,if($E38="FA Contract",if(and(N$1<=$I38,N$1>=$H38),$F38,""),if($E38="YP Contract",if(N$1=$H38,500000,if(N$1=($H38+1),1000000,if(N$1=($H38+2),1500000,"")))))))) | O38: =if($E38="","",if($E38="Dropped",if(and(O$1<=$I38,O$1>=$H38),if(Year($D38)=O$1,$F38*0.8,if((year($D38)+1)=O$1,$F38*0.6,$F38*0.4)) ,""),if($E38="Minors",0,if($E38="FA Contract",if(and(O$1<=$I38,O$1>=$H38),$F38,""),if($E38="YP Contract",if(O$1=$H38,500000,if(O$1=($H38+1),1000000,if(O$1=($H38+2),1500000,"")))))))) | P38: =if($E38="","",if($E38="Dropped",if(and(P$1<=$I38,P$1>=$H38),if(Year($D38)=P$1,$F38*0.8,if((year($D38)+1)=P$1,$F38*0.6,$F38*0.4)) ,""),if($E38="Minors",0,if($E38="FA Contract",if(and(P$1<=$I38,P$1>=$H38),$F38,""),if($E38="YP Contract",if(P$1=$H38,500000,if(P$1=($H38+1),1000000,if(P$1=($H38+2),1500000,""))))))))
A39: Tyler Fitzgerald | B39: Brenden Freedman | C39: 45721 | E39: FA Contract | F39: 500000 | G39: 1 | H39: 2025 | I39: =if(H39="","",if(or($E39="FA Contract",$E39="Dropped"),$H39+$G39-1,if($E39="YP Contract",$H39+2,if(and($E39="Minors",$G39<>"YP"),$H39+$G39-1,if(and($E39="Minors",$G39="YP"),$H39+2,""))))) -> 2025 | J39: 33100000 | K39: =if($E39="","",if($E39="Dropped",if(and(K$1<=$I39,K$1>=$H39),if(Year($D39)=K$1,$F39*0.8,if((year($D39)+1)=K$1,$F39*0.6,$F39*0.4)) ,""),if($E39="Minors",0,if($E39="FA Contract",if(and(K$1<=$I39,K$1>=$H39),$F39,""),if($E39="YP Contract",if(K$1=$H39,500000,if(K$1=($H39+1),1000000,if(K$1=($H39+2),1500000,"")))))))) -> 500000 | L39: =if($E39="","",if($E39="Dropped",if(and(L$1<=$I39,L$1>=$H39),if(Year($D39)=L$1,$F39*0.8,if((year($D39)+1)=L$1,$F39*0.6,$F39*0.4)) ,""),if($E39="Minors",0,if($E39="FA Contract",if(and(L$1<=$I39,L$1>=$H39),$F39,""),if($E39="YP Contract",if(L$1=$H39,500000,if(L$1=($H39+1),1000000,if(L$1=($H39+2),1500000,"")))))))) | M39: =if($E39="","",if($E39="Dropped",if(and(M$1<=$I39,M$1>=$H39),if(Year($D39)=M$1,$F39*0.8,if((year($D39)+1)=M$1,$F39*0.6,$F39*0.4)) ,""),if($E39="Minors",0,if($E39="FA Contract",if(and(M$1<=$I39,M$1>=$H39),$F39,""),if($E39="YP Contract",if(M$1=$H39,500000,if(M$1=($H39+1),1000000,if(M$1=($H39+2),1500000,"")))))))) | N39: =if($E39="","",if($E39="Dropped",if(and(N$1<=$I39,N$1>=$H39),if(Year($D39)=N$1,$F39*0.8,if((year($D39)+1)=N$1,$F39*0.6,$F39*0.4)) ,""),if($E39="Minors",0,if($E39="FA Contract",if(and(N$1<=$I39,N$1>=$H39),$F39,""),if($E39="YP Contract",if(N$1=$H39,500000,if(N$1=($H39+1),1000000,if(N$1=($H39+2),1500000,"")))))))) | O39: =if($E39="","",if($E39="Dropped",if(and(O$1<=$I39,O$1>=$H39),if(Year($D39)=O$1,$F39*0.8,if((year($D39)+1)=O$1,$F39*0.6,$F39*0.4)) ,""),if($E39="Minors",0,if($E39="FA Contract",if(and(O$1<=$I39,O$1>=$H39),$F39,""),if($E39="YP Contract",if(O$1=$H39,500000,if(O$1=($H39+1),1000000,if(O$1=($H39+2),1500000,"")))))))) | P39: =if($E39="","",if($E39="Dropped",if(and(P$1<=$I39,P$1>=$H39),if(Year($D39)=P$1,$F39*0.8,if((year($D39)+1)=P$1,$F39*0.6,$F39*0.4)) ,""),if($E39="Minors",0,if($E39="FA Contract",if(and(P$1<=$I39,P$1>=$H39),$F39,""),if($E39="YP Contract",if(P$1=$H39,500000,if(P$1=($H39+1),1000000,if(P$1=($H39+2),1500000,""))))))))
A40: Anthony Solomento | B40: Brenden Freedman | C40: 45343 | E40: Minors | F40: YP | G40: YP | I40: =if(H40="","",if(or($E40="FA Contract",$E40="Dropped"),$H40+$G40-1,if($E40="YP Contract",$H40+2,if(and($E40="Minors",$G40<>"YP"),$H40+$G40-1,if(and($E40="Minors",$G40="YP"),$H40+2,""))))) | J40: 33100000 | K40: =if($E40="","",if($E40="Dropped",if(and(K$1<=$I40,K$1>=$H40),if(Year($D40)=K$1,$F40*0.8,if((year($D40)+1)=K$1,$F40*0.6,$F40*0.4)) ,""),if($E40="Minors",0,if($E40="FA Contract",if(and(K$1<=$I40,K$1>=$H40),$F40,""),if($E40="YP Contract",if(K$1=$H40,500000,if(K$1=($H40+1),1000000,if(K$1=($H40+2),1500000,"")))))))) -> 0 | L40: =if($E40="","",if($E40="Dropped",if(and(L$1<=$I40,L$1>=$H40),if(Year($D40)=L$1,$F40*0.8,if((year($D40)+1)=L$1,$F40*0.6,$F40*0.4)) ,""),if($E40="Minors",0,if($E40="FA Contract",if(and(L$1<=$I40,L$1>=$H40),$F40,""),if($E40="YP Contract",if(L$1=$H40,500000,if(L$1=($H40+1),1000000,if(L$1=($H40+2),1500000,"")))))))) -> 0 | M40: =if($E40="","",if($E40="Dropped",if(and(M$1<=$I40,M$1>=$H40),if(Year($D40)=M$1,$F40*0.8,if((year($D40)+1)=M$1,$F40*0.6,$F40*0.4)) ,""),if($E40="Minors",0,if($E40="FA Contract",if(and(M$1<=$I40,M$1>=$H40),$F40,""),if($E40="YP Contract",if(M$1=$H40,500000,if(M$1=($H40+1),1000000,if(M$1=($H40+2),1500000,"")))))))) -> 0 | N40: =if($E40="","",if($E40="Dropped",if(and(N$1<=$I40,N$1>=$H40),if(Year($D40)=N$1,$F40*0.8,if((year($D40)+1)=N$1,$F40*0.6,$F40*0.4)) ,""),if($E40="Minors",0,if($E40="FA Contract",if(and(N$1<=$I40,N$1>=$H40),$F40,""),if($E40="YP Contract",if(N$1=$H40,500000,if(N$1=($H40+1),1000000,if(N$1=($H40+2),1500000,"")))))))) -> 0 | O40: =if($E40="","",if($E40="Dropped",if(and(O$1<=$I40,O$1>=$H40),if(Year($D40)=O$1,$F40*0.8,if((year($D40)+1)=O$1,$F40*0.6,$F40*0.4)) ,""),if($E40="Minors",0,if($E40="FA Contract",if(and(O$1<=$I40,O$1>=$H40),$F40,""),if($E40="YP Contract",if(O$1=$H40,500000,if(O$1=($H40+1),1000000,if(O$1=($H40+2),1500000,"")))))))) -> 0 | P40: =if($E40="","",if($E40="Dropped",if(and(P$1<=$I40,P$1>=$H40),if(Year($D40)=P$1,$F40*0.8,if((year($D40)+1)=P$1,$F40*0.6,$F40*0.4)) ,""),if($E40="Minors",0,if($E40="FA Contract",if(and(P$1<=$I40,P$1>=$H40),$F40,""),if($E40="YP Contract",if(P$1=$H40,500000,if(P$1=($H40+1),1000000,if(P$1=($H40+2),1500000,"")))))))) -> 0
A41: Arjun Nimmala | B41: Brenden Freedman | C41: 45354 | E41: Minors | F41: YP | G41: YP | I41: =if(H41="","",if(or($E41="FA Contract",$E41="Dropped"),$H41+$G41-1,if($E41="YP Contract",$H41+2,if(and($E41="Minors",$G41<>"YP"),$H41+$G41-1,if(and($E41="Minors",$G41="YP"),$H41+2,""))))) | J41: 33100000 | K41: =if($E41="","",if($E41="Dropped",if(and(K$1<=$I41,K$1>=$H41),if(Year($D41)=K$1,$F41*0.8,if((year($D41)+1)=K$1,$F41*0.6,$F41*0.4)) ,""),if($E41="Minors",0,if($E41="FA Contract",if(and(K$1<=$I41,K$1>=$H41),$F41,""),if($E41="YP Contract",if(K$1=$H41,500000,if(K$1=($H41+1),1000000,if(K$1=($H41+2),1500000,"")))))))) -> 0 | L41: =if($E41="","",if($E41="Dropped",if(and(L$1<=$I41,L$1>=$H41),if(Year($D41)=L$1,$F41*0.8,if((year($D41)+1)=L$1,$F41*0.6,$F41*0.4)) ,""),if($E41="Minors",0,if($E41="FA Contract",if(and(L$1<=$I41,L$1>=$H41),$F41,""),if($E41="YP Contract",if(L$1=$H41,500000,if(L$1=($H41+1),1000000,if(L$1=($H41+2),1500000,"")))))))) -> 0 | M41: =if($E41="","",if($E41="Dropped",if(and(M$1<=$I41,M$1>=$H41),if(Year($D41)=M$1,$F41*0.8,if((year($D41)+1)=M$1,$F41*0.6,$F41*0.4)) ,""),if($E41="Minors",0,if($E41="FA Contract",if(and(M$1<=$I41,M$1>=$H41),$F41,""),if($E41="YP Contract",if(M$1=$H41,500000,if(M$1=($H41+1),1000000,if(M$1=($H41+2),1500000,"")))))))) -> 0 | N41: =if($E41="","",if($E41="Dropped",if(and(N$1<=$I41,N$1>=$H41),if(Year($D41)=N$1,$F41*0.8,if((year($D41)+1)=N$1,$F41*0.6,$F41*0.4)) ,""),if($E41="Minors",0,if($E41="FA Contract",if(and(N$1<=$I41,N$1>=$H41),$F41,""),if($E41="YP Contract",if(N$1=$H41,500000,if(N$1=($H41+1),1000000,if(N$1=($H41+2),1500000,"")))))))) -> 0 | O41: =if($E41="","",if($E41="Dropped",if(and(O$1<=$I41,O$1>=$H41),if(Year($D41)=O$1,$F41*0.8,if((year($D41)+1)=O$1,$F41*0.6,$F41*0.4)) ,""),if($E41="Minors",0,if($E41="FA Contract",if(and(O$1<=$I41,O$1>=$H41),$F41,""),if($E41="YP Contract",if(O$1=$H41,500000,if(O$1=($H41+1),1000000,if(O$1=($H41+2),1500000,"")))))))) -> 0 | P41: =if($E41="","",if($E41="Dropped",if(and(P$1<=$I41,P$1>=$H41),if(Year($D41)=P$1,$F41*0.8,if((year($D41)+1)=P$1,$F41*0.6,$F41*0.4)) ,""),if($E41="Minors",0,if($E41="FA Contract",if(and(P$1<=$I41,P$1>=$H41),$F41,""),if($E41="YP Contract",if(P$1=$H41,500000,if(P$1=($H41+1),1000000,if(P$1=($H41+2),1500000,"")))))))) -> 0
A42: Blake Mitchell | B42: Brenden Freedman | C42: 45346 | E42: Minors | F42: YP | G42: YP | I42: =if(H42="","",if(or($E42="FA Contract",$E42="Dropped"),$H42+$G42-1,if($E42="YP Contract",$H42+2,if(and($E42="Minors",$G42<>"YP"),$H42+$G42-1,if(and($E42="Minors",$G42="YP"),$H42+2,""))))) | J42: 33100000 | K42: =if($E42="","",if($E42="Dropped",if(and(K$1<=$I42,K$1>=$H42),if(Year($D42)=K$1,$F42*0.8,if((year($D42)+1)=K$1,$F42*0.6,$F42*0.4)) ,""),if($E42="Minors",0,if($E42="FA Contract",if(and(K$1<=$I42,K$1>=$H42),$F42,""),if($E42="YP Contract",if(K$1=$H42,500000,if(K$1=($H42+1),1000000,if(K$1=($H42+2),1500000,"")))))))) -> 0 | L42: =if($E42="","",if($E42="Dropped",if(and(L$1<=$I42,L$1>=$H42),if(Year($D42)=L$1,$F42*0.8,if((year($D42)+1)=L$1,$F42*0.6,$F42*0.4)) ,""),if($E42="Minors",0,if($E42="FA Contract",if(and(L$1<=$I42,L$1>=$H42),$F42,""),if($E42="YP Contract",if(L$1=$H42,500000,if(L$1=($H42+1),1000000,if(L$1=($H42+2),1500000,"")))))))) -> 0 | M42: =if($E42="","",if($E42="Dropped",if(and(M$1<=$I42,M$1>=$H42),if(Year($D42)=M$1,$F42*0.8,if((year($D42)+1)=M$1,$F42*0.6,$F42*0.4)) ,""),if($E42="Minors",0,if($E42="FA Contract",if(and(M$1<=$I42,M$1>=$H42),$F42,""),if($E42="YP Contract",if(M$1=$H42,500000,if(M$1=($H42+1),1000000,if(M$1=($H42+2),1500000,"")))))))) -> 0 | N42: =if($E42="","",if($E42="Dropped",if(and(N$1<=$I42,N$1>=$H42),if(Year($D42)=N$1,$F42*0.8,if((year($D42)+1)=N$1,$F42*0.6,$F42*0.4)) ,""),if($E42="Minors",0,if($E42="FA Contract",if(and(N$1<=$I42,N$1>=$H42),$F42,""),if($E42="YP Contract",if(N$1=$H42,500000,if(N$1=($H42+1),1000000,if(N$1=($H42+2),1500000,"")))))))) -> 0 | O42: =if($E42="","",if($E42="Dropped",if(and(O$1<=$I42,O$1>=$H42),if(Year($D42)=O$1,$F42*0.8,if((year($D42)+1)=O$1,$F42*0.6,$F42*0.4)) ,""),if($E42="Minors",0,if($E42="FA Contract",if(and(O$1<=$I42,O$1>=$H42),$F42,""),if($E42="YP Contract",if(O$1=$H42,500000,if(O$1=($H42+1),1000000,if(O$1=($H42+2),1500000,"")))))))) -> 0 | P42: =if($E42="","",if($E42="Dropped",if(and(P$1<=$I42,P$1>=$H42),if(Year($D42)=P$1,$F42*0.8,if((year($D42)+1)=P$1,$F42*0.6,$F42*0.4)) ,""),if($E42="Minors",0,if($E42="FA Contract",if(and(P$1<=$I42,P$1>=$H42),$F42,""),if($E42="YP Contract",if(P$1=$H42,500000,if(P$1=($H42+1),1000000,if(P$1=($H42+2),1500000,"")))))))) -> 0
A43: Brock Porter | B43: Brenden Freedman | C43: 45343 | E43: Minors | F43: YP | G43: YP | I43: =if(H43="","",if(or($E43="FA Contract",$E43="Dropped"),$H43+$G43-1,if($E43="YP Contract",$H43+2,if(and($E43="Minors",$G43<>"YP"),$H43+$G43-1,if(and($E43="Minors",$G43="YP"),$H43+2,""))))) | J43: 33100000 | K43: =if($E43="","",if($E43="Dropped",if(and(K$1<=$I43,K$1>=$H43),if(Year($D43)=K$1,$F43*0.8,if((year($D43)+1)=K$1,$F43*0.6,$F43*0.4)) ,""),if($E43="Minors",0,if($E43="FA Contract",if(and(K$1<=$I43,K$1>=$H43),$F43,""),if($E43="YP Contract",if(K$1=$H43,500000,if(K$1=($H43+1),1000000,if(K$1=($H43+2),1500000,"")))))))) -> 0 | L43: =if($E43="","",if($E43="Dropped",if(and(L$1<=$I43,L$1>=$H43),if(Year($D43)=L$1,$F43*0.8,if((year($D43)+1)=L$1,$F43*0.6,$F43*0.4)) ,""),if($E43="Minors",0,if($E43="FA Contract",if(and(L$1<=$I43,L$1>=$H43),$F43,""),if($E43="YP Contract",if(L$1=$H43,500000,if(L$1=($H43+1),1000000,if(L$1=($H43+2),1500000,"")))))))) -> 0 | M43: =if($E43="","",if($E43="Dropped",if(and(M$1<=$I43,M$1>=$H43),if(Year($D43)=M$1,$F43*0.8,if((year($D43)+1)=M$1,$F43*0.6,$F43*0.4)) ,""),if($E43="Minors",0,if($E43="FA Contract",if(and(M$1<=$I43,M$1>=$H43),$F43,""),if($E43="YP Contract",if(M$1=$H43,500000,if(M$1=($H43+1),1000000,if(M$1=($H43+2),1500000,"")))))))) -> 0 | N43: =if($E43="","",if($E43="Dropped",if(and(N$1<=$I43,N$1>=$H43),if(Year($D43)=N$1,$F43*0.8,if((year($D43)+1)=N$1,$F43*0.6,$F43*0.4)) ,""),if($E43="Minors",0,if($E43="FA Contract",if(and(N$1<=$I43,N$1>=$H43),$F43,""),if($E43="YP Contract",if(N$1=$H43,500000,if(N$1=($H43+1),1000000,if(N$1=($H43+2),1500000,"")))))))) -> 0 | O43: =if($E43="","",if($E43="Dropped",if(and(O$1<=$I43,O$1>=$H43),if(Year($D43)=O$1,$F43*0.8,if((year($D43)+1)=O$1,$F43*0.6,$F43*0.4)) ,""),if($E43="Minors",0,if($E43="FA Contract",if(and(O$1<=$I43,O$1>=$H43),$F43,""),if($E43="YP Contract",if(O$1=$H43,500000,if(O$1=($H43+1),1000000,if(O$1=($H43+2),1500000,"")))))))) -> 0 | P43: =if($E43="","",if($E43="Dropped",if(and(P$1<=$I43,P$1>=$H43),if(Year($D43)=P$1,$F43*0.8,if((year($D43)+1)=P$1,$F43*0.6,$F43*0.4)) ,""),if($E43="Minors",0,if($E43="FA Contract",if(and(P$1<=$I43,P$1>=$H43),$F43,""),if($E43="YP Contract",if(P$1=$H43,500000,if(P$1=($H43+1),1000000,if(P$1=($H43+2),1500000,"")))))))) -> 0
A44: Bryan De La Cruz | B44: Brenden Freedman | C44: 45356 | E44: Minors | F44: 1500000 | G44: 2 | H44: 2024 | I44: =if(H44="","",if(or($E44="FA Contract",$E44="Dropped"),$H44+$G44-1,if($E44="YP Contract",$H44+2,if(and($E44="Minors",$G44<>"YP"),$H44+$G44-1,if(and($E44="Minors",$G44="YP"),$H44+2,""))))) -> 2025 | J44: 33100000 | K44: =if($E44="","",if($E44="Dropped",if(and(K$1<=$I44,K$1>=$H44),if(Year($D44)=K$1,$F44*0.8,if((year($D44)+1)=K$1,$F44*0.6,$F44*0.4)) ,""),if($E44="Minors",0,if($E44="FA Contract",if(and(K$1<=$I44,K$1>=$H44),$F44,""),if($E44="YP Contract",if(K$1=$H44,500000,if(K$1=($H44+1),1000000,if(K$1=($H44+2),1500000,"")))))))) -> 0 | L44: =if($E44="","",if($E44="Dropped",if(and(L$1<=$I44,L$1>=$H44),if(Year($D44)=L$1,$F44*0.8,if((year($D44)+1)=L$1,$F44*0.6,$F44*0.4)) ,""),if($E44="Minors",0,if($E44="FA Contract",if(and(L$1<=$I44,L$1>=$H44),$F44,""),if($E44="YP Contract",if(L$1=$H44,500000,if(L$1=($H44+1),1000000,if(L$1=($H44+2),1500000,"")))))))) -> 0 | M44: =if($E44="","",if($E44="Dropped",if(and(M$1<=$I44,M$1>=$H44),if(Year($D44)=M$1,$F44*0.8,if((year($D44)+1)=M$1,$F44*0.6,$F44*0.4)) ,""),if($E44="Minors",0,if($E44="FA Contract",if(and(M$1<=$I44,M$1>=$H44),$F44,""),if($E44="YP Contract",if(M$1=$H44,500000,if(M$1=($H44+1),1000000,if(M$1=($H44+2),1500000,"")))))))) -> 0 | N44: =if($E44="","",if($E44="Dropped",if(and(N$1<=$I44,N$1>=$H44),if(Year($D44)=N$1,$F44*0.8,if((year($D44)+1)=N$1,$F44*0.6,$F44*0.4)) ,""),if($E44="Minors",0,if($E44="FA Contract",if(and(N$1<=$I44,N$1>=$H44),$F44,""),if($E44="YP Contract",if(N$1=$H44,500000,if(N$1=($H44+1),1000000,if(N$1=($H44+2),1500000,"")))))))) -> 0 | O44: =if($E44="","",if($E44="Dropped",if(and(O$1<=$I44,O$1>=$H44),if(Year($D44)=O$1,$F44*0.8,if((year($D44)+1)=O$1,$F44*0.6,$F44*0.4)) ,""),if($E44="Minors",0,if($E44="FA Contract",if(and(O$1<=$I44,O$1>=$H44),$F44,""),if($E44="YP Contract",if(O$1=$H44,500000,if(O$1=($H44+1),1000000,if(O$1=($H44+2),1500000,"")))))))) -> 0 | P44: =if($E44="","",if($E44="Dropped",if(and(P$1<=$I44,P$1>=$H44),if(Year($D44)=P$1,$F44*0.8,if((year($D44)+1)=P$1,$F44*0.6,$F44*0.4)) ,""),if($E44="Minors",0,if($E44="FA Contract",if(and(P$1<=$I44,P$1>=$H44),$F44,""),if($E44="YP Contract",if(P$1=$H44,500000,if(P$1=($H44+1),1000000,if(P$1=($H44+2),1500000,"")))))))) -> 0
A45: Druw Jones | B45: Brenden Freedman | C45: 45495 | E45: Minors | F45: YP | G45: YP | I45: =if(H45="","",if(or($E45="FA Contract",$E45="Dropped"),$H45+$G45-1,if($E45="YP Contract",$H45+2,if(and($E45="Minors",$G45<>"YP"),$H45+$G45-1,if(and($E45="Minors",$G45="YP"),$H45+2,""))))) | J45: 33100000 | K45: =if($E45="","",if($E45="Dropped",if(and(K$1<=$I45,K$1>=$H45),if(Year($D45)=K$1,$F45*0.8,if((year($D45)+1)=K$1,$F45*0.6,$F45*0.4)) ,""),if($E45="Minors",0,if($E45="FA Contract",if(and(K$1<=$I45,K$1>=$H45),$F45,""),if($E45="YP Contract",if(K$1=$H45,500000,if(K$1=($H45+1),1000000,if(K$1=($H45+2),1500000,"")))))))) -> 0 | L45: =if($E45="","",if($E45="Dropped",if(and(L$1<=$I45,L$1>=$H45),if(Year($D45)=L$1,$F45*0.8,if((year($D45)+1)=L$1,$F45*0.6,$F45*0.4)) ,""),if($E45="Minors",0,if($E45="FA Contract",if(and(L$1<=$I45,L$1>=$H45),$F45,""),if($E45="YP Contract",if(L$1=$H45,500000,if(L$1=($H45+1),1000000,if(L$1=($H45+2),1500000,"")))))))) -> 0 | M45: =if($E45="","",if($E45="Dropped",if(and(M$1<=$I45,M$1>=$H45),if(Year($D45)=M$1,$F45*0.8,if((year($D45)+1)=M$1,$F45*0.6,$F45*0.4)) ,""),if($E45="Minors",0,if($E45="FA Contract",if(and(M$1<=$I45,M$1>=$H45),$F45,""),if($E45="YP Contract",if(M$1=$H45,500000,if(M$1=($H45+1),1000000,if(M$1=($H45+2),1500000,"")))))))) -> 0 | N45: =if($E45="","",if($E45="Dropped",if(and(N$1<=$I45,N$1>=$H45),if(Year($D45)=N$1,$F45*0.8,if((year($D45)+1)=N$1,$F45*0.6,$F45*0.4)) ,""),if($E45="Minors",0,if($E45="FA Contract",if(and(N$1<=$I45,N$1>=$H45),$F45,""),if($E45="YP Contract",if(N$1=$H45,500000,if(N$1=($H45+1),1000000,if(N$1=($H45+2),1500000,"")))))))) -> 0 | O45: =if($E45="","",if($E45="Dropped",if(and(O$1<=$I45,O$1>=$H45),if(Year($D45)=O$1,$F45*0.8,if((year($D45)+1)=O$1,$F45*0.6,$F45*0.4)) ,""),if($E45="Minors",0,if($E45="FA Contract",if(and(O$1<=$I45,O$1>=$H45),$F45,""),if($E45="YP Contract",if(O$1=$H45,500000,if(O$1=($H45+1),1000000,if(O$1=($H45+2),1500000,"")))))))) -> 0 | P45: =if($E45="","",if($E45="Dropped",if(and(P$1<=$I45,P$1>=$H45),if(Year($D45)=P$1,$F45*0.8,if((year($D45)+1)=P$1,$F45*0.6,$F45*0.4)) ,""),if($E45="Minors",0,if($E45="FA Contract",if(and(P$1<=$I45,P$1>=$H45),$F45,""),if($E45="YP Contract",if(P$1=$H45,500000,if(P$1=($H45+1),1000000,if(P$1=($H45+2),1500000,"")))))))) -> 0
A46: Erik Swanson | B46: Brenden Freedman | C46: 45356 | E46: Minors | F46: 1500000 | G46: 2 | H46: 2024 | I46: =if(H46="","",if(or($E46="FA Contract",$E46="Dropped"),$H46+$G46-1,if($E46="YP Contract",$H46+2,if(and($E46="Minors",$G46<>"YP"),$H46+$G46-1,if(and($E46="Minors",$G46="YP"),$H46+2,""))))) -> 2025 | J46: 33100000 | K46: =if($E46="","",if($E46="Dropped",if(and(K$1<=$I46,K$1>=$H46),if(Year($D46)=K$1,$F46*0.8,if((year($D46)+1)=K$1,$F46*0.6,$F46*0.4)) ,""),if($E46="Minors",0,if($E46="FA Contract",if(and(K$1<=$I46,K$1>=$H46),$F46,""),if($E46="YP Contract",if(K$1=$H46,500000,if(K$1=($H46+1),1000000,if(K$1=($H46+2),1500000,"")))))))) -> 0 | L46: =if($E46="","",if($E46="Dropped",if(and(L$1<=$I46,L$1>=$H46),if(Year($D46)=L$1,$F46*0.8,if((year($D46)+1)=L$1,$F46*0.6,$F46*0.4)) ,""),if($E46="Minors",0,if($E46="FA Contract",if(and(L$1<=$I46,L$1>=$H46),$F46,""),if($E46="YP Contract",if(L$1=$H46,500000,if(L$1=($H46+1),1000000,if(L$1=($H46+2),1500000,"")))))))) -> 0 | M46: =if($E46="","",if($E46="Dropped",if(and(M$1<=$I46,M$1>=$H46),if(Year($D46)=M$1,$F46*0.8,if((year($D46)+1)=M$1,$F46*0.6,$F46*0.4)) ,""),if($E46="Minors",0,if($E46="FA Contract",if(and(M$1<=$I46,M$1>=$H46),$F46,""),if($E46="YP Contract",if(M$1=$H46,500000,if(M$1=($H46+1),1000000,if(M$1=($H46+2),1500000,"")))))))) -> 0 | N46: =if($E46="","",if($E46="Dropped",if(and(N$1<=$I46,N$1>=$H46),if(Year($D46)=N$1,$F46*0.8,if((year($D46)+1)=N$1,$F46*0.6,$F46*0.4)) ,""),if($E46="Minors",0,if($E46="FA Contract",if(and(N$1<=$I46,N$1>=$H46),$F46,""),if($E46="YP Contract",if(N$1=$H46,500000,if(N$1=($H46+1),1000000,if(N$1=($H46+2),1500000,"")))))))) -> 0 | O46: =if($E46="","",if($E46="Dropped",if(and(O$1<=$I46,O$1>=$H46),if(Year($D46)=O$1,$F46*0.8,if((year($D46)+1)=O$1,$F46*0.6,$F46*0.4)) ,""),if($E46="Minors",0,if($E46="FA Contract",if(and(O$1<=$I46,O$1>=$H46),$F46,""),if($E46="YP Contract",if(O$1=$H46,500000,if(O$1=($H46+1),1000000,if(O$1=($H46+2),1500000,"")))))))) -> 0 | P46: =if($E46="","",if($E46="Dropped",if(and(P$1<=$I46,P$1>=$H46),if(Year($D46)=P$1,$F46*0.8,if((year($D46)+1)=P$1,$F46*0.6,$F46*0.4)) ,""),if($E46="Minors",0,if($E46="FA Contract",if(and(P$1<=$I46,P$1>=$H46),$F46,""),if($E46="YP Contract",if(P$1=$H46,500000,if(P$1=($H46+1),1000000,if(P$1=($H46+2),1500000,"")))))))) -> 0
A47: Ernesto Martinez Jr | B47: Brenden Freedman | C47: 45767 | E47: Minors | F47: YP | G47: YP | I47: =if(H47="","",if(or($E47="FA Contract",$E47="Dropped"),$H47+$G47-1,if($E47="YP Contract",$H47+2,if(and($E47="Minors",$G47<>"YP"),$H47+$G47-1,if(and($E47="Minors",$G47="YP"),$H47+2,""))))) | J47: 33100000 | K47: =if($E47="","",if($E47="Dropped",if(and(K$1<=$I47,K$1>=$H47),if(Year($D47)=K$1,$F47*0.8,if((year($D47)+1)=K$1,$F47*0.6,$F47*0.4)) ,""),if($E47="Minors",0,if($E47="FA Contract",if(and(K$1<=$I47,K$1>=$H47),$F47,""),if($E47="YP Contract",if(K$1=$H47,500000,if(K$1=($H47+1),1000000,if(K$1=($H47+2),1500000,"")))))))) -> 0 | L47: =if($E47="","",if($E47="Dropped",if(and(L$1<=$I47,L$1>=$H47),if(Year($D47)=L$1,$F47*0.8,if((year($D47)+1)=L$1,$F47*0.6,$F47*0.4)) ,""),if($E47="Minors",0,if($E47="FA Contract",if(and(L$1<=$I47,L$1>=$H47),$F47,""),if($E47="YP Contract",if(L$1=$H47,500000,if(L$1=($H47+1),1000000,if(L$1=($H47+2),1500000,"")))))))) -> 0 | M47: =if($E47="","",if($E47="Dropped",if(and(M$1<=$I47,M$1>=$H47),if(Year($D47)=M$1,$F47*0.8,if((year($D47)+1)=M$1,$F47*0.6,$F47*0.4)) ,""),if($E47="Minors",0,if($E47="FA Contract",if(and(M$1<=$I47,M$1>=$H47),$F47,""),if($E47="YP Contract",if(M$1=$H47,500000,if(M$1=($H47+1),1000000,if(M$1=($H47+2),1500000,"")))))))) -> 0 | N47: =if($E47="","",if($E47="Dropped",if(and(N$1<=$I47,N$1>=$H47),if(Year($D47)=N$1,$F47*0.8,if((year($D47)+1)=N$1,$F47*0.6,$F47*0.4)) ,""),if($E47="Minors",0,if($E47="FA Contract",if(and(N$1<=$I47,N$1>=$H47),$F47,""),if($E47="YP Contract",if(N$1=$H47,500000,if(N$1=($H47+1),1000000,if(N$1=($H47+2),1500000,"")))))))) -> 0 | O47: =if($E47="","",if($E47="Dropped",if(and(O$1<=$I47,O$1>=$H47),if(Year($D47)=O$1,$F47*0.8,if((year($D47)+1)=O$1,$F47*0.6,$F47*0.4)) ,""),if($E47="Minors",0,if($E47="FA Contract",if(and(O$1<=$I47,O$1>=$H47),$F47,""),if($E47="YP Contract",if(O$1=$H47,500000,if(O$1=($H47+1),1000000,if(O$1=($H47+2),1500000,"")))))))) -> 0 | P47: =if($E47="","",if($E47="Dropped",if(and(P$1<=$I47,P$1>=$H47),if(Year($D47)=P$1,$F47*0.8,if((year($D47)+1)=P$1,$F47*0.6,$F47*0.4)) ,""),if($E47="Minors",0,if($E47="FA Contract",if(and(P$1<=$I47,P$1>=$H47),$F47,""),if($E47="YP Contract",if(P$1=$H47,500000,if(P$1=($H47+1),1000000,if(P$1=($H47+2),1500000,"")))))))) -> 0
A48: Josue Briceno | B48: Brenden Freedman | C48: 45350 | E48: Minors | F48: YP | G48: YP | I48: =if(H48="","",if(or($E48="FA Contract",$E48="Dropped"),$H48+$G48-1,if($E48="YP Contract",$H48+2,if(and($E48="Minors",$G48<>"YP"),$H48+$G48-1,if(and($E48="Minors",$G48="YP"),$H48+2,""))))) | J48: 33100000 | K48: =if($E48="","",if($E48="Dropped",if(and(K$1<=$I48,K$1>=$H48),if(Year($D48)=K$1,$F48*0.8,if((year($D48)+1)=K$1,$F48*0.6,$F48*0.4)) ,""),if($E48="Minors",0,if($E48="FA Contract",if(and(K$1<=$I48,K$1>=$H48),$F48,""),if($E48="YP Contract",if(K$1=$H48,500000,if(K$1=($H48+1),1000000,if(K$1=($H48+2),1500000,"")))))))) -> 0 | L48: =if($E48="","",if($E48="Dropped",if(and(L$1<=$I48,L$1>=$H48),if(Year($D48)=L$1,$F48*0.8,if((year($D48)+1)=L$1,$F48*0.6,$F48*0.4)) ,""),if($E48="Minors",0,if($E48="FA Contract",if(and(L$1<=$I48,L$1>=$H48),$F48,""),if($E48="YP Contract",if(L$1=$H48,500000,if(L$1=($H48+1),1000000,if(L$1=($H48+2),1500000,"")))))))) -> 0 | M48: =if($E48="","",if($E48="Dropped",if(and(M$1<=$I48,M$1>=$H48),if(Year($D48)=M$1,$F48*0.8,if((year($D48)+1)=M$1,$F48*0.6,$F48*0.4)) ,""),if($E48="Minors",0,if($E48="FA Contract",if(and(M$1<=$I48,M$1>=$H48),$F48,""),if($E48="YP Contract",if(M$1=$H48,500000,if(M$1=($H48+1),1000000,if(M$1=($H48+2),1500000,"")))))))) -> 0 | N48: =if($E48="","",if($E48="Dropped",if(and(N$1<=$I48,N$1>=$H48),if(Year($D48)=N$1,$F48*0.8,if((year($D48)+1)=N$1,$F48*0.6,$F48*0.4)) ,""),if($E48="Minors",0,if($E48="FA Contract",if(and(N$1<=$I48,N$1>=$H48),$F48,""),if($E48="YP Contract",if(N$1=$H48,500000,if(N$1=($H48+1),1000000,if(N$1=($H48+2),1500000,"")))))))) -> 0 | O48: =if($E48="","",if($E48="Dropped",if(and(O$1<=$I48,O$1>=$H48),if(Year($D48)=O$1,$F48*0.8,if((year($D48)+1)=O$1,$F48*0.6,$F48*0.4)) ,""),if($E48="Minors",0,if($E48="FA Contract",if(and(O$1<=$I48,O$1>=$H48),$F48,""),if($E48="YP Contract",if(O$1=$H48,500000,if(O$1=($H48+1),1000000,if(O$1=($H48+2),1500000,"")))))))) -> 0 | P48: =if($E48="","",if($E48="Dropped",if(and(P$1<=$I48,P$1>=$H48),if(Year($D48)=P$1,$F48*0.8,if((year($D48)+1)=P$1,$F48*0.6,$F48*0.4)) ,""),if($E48="Minors",0,if($E48="FA Contract",if(and(P$1<=$I48,P$1>=$H48),$F48,""),if($E48="YP Contract",if(P$1=$H48,500000,if(P$1=($H48+1),1000000,if(P$1=($H48+2),1500000,"")))))))) -> 0
A49: Max Clark | B49: Brenden Freedman | C49: 45343 | E49: Minors | F49: YP | G49: YP | I49: =if(H49="","",if(or($E49="FA Contract",$E49="Dropped"),$H49+$G49-1,if($E49="YP Contract",$H49+2,if(and($E49="Minors",$G49<>"YP"),$H49+$G49-1,if(and($E49="Minors",$G49="YP"),$H49+2,""))))) | J49: 33100000 | K49: =if($E49="","",if($E49="Dropped",if(and(K$1<=$I49,K$1>=$H49),if(Year($D49)=K$1,$F49*0.8,if((year($D49)+1)=K$1,$F49*0.6,$F49*0.4)) ,""),if($E49="Minors",0,if($E49="FA Contract",if(and(K$1<=$I49,K$1>=$H49),$F49,""),if($E49="YP Contract",if(K$1=$H49,500000,if(K$1=($H49+1),1000000,if(K$1=($H49+2),1500000,"")))))))) -> 0 | L49: =if($E49="","",if($E49="Dropped",if(and(L$1<=$I49,L$1>=$H49),if(Year($D49)=L$1,$F49*0.8,if((year($D49)+1)=L$1,$F49*0.6,$F49*0.4)) ,""),if($E49="Minors",0,if($E49="FA Contract",if(and(L$1<=$I49,L$1>=$H49),$F49,""),if($E49="YP Contract",if(L$1=$H49,500000,if(L$1=($H49+1),1000000,if(L$1=($H49+2),1500000,"")))))))) -> 0 | M49: =if($E49="","",if($E49="Dropped",if(and(M$1<=$I49,M$1>=$H49),if(Year($D49)=M$1,$F49*0.8,if((year($D49)+1)=M$1,$F49*0.6,$F49*0.4)) ,""),if($E49="Minors",0,if($E49="FA Contract",if(and(M$1<=$I49,M$1>=$H49),$F49,""),if($E49="YP Contract",if(M$1=$H49,500000,if(M$1=($H49+1),1000000,if(M$1=($H49+2),1500000,"")))))))) -> 0 | N49: =if($E49="","",if($E49="Dropped",if(and(N$1<=$I49,N$1>=$H49),if(Year($D49)=N$1,$F49*0.8,if((year($D49)+1)=N$1,$F49*0.6,$F49*0.4)) ,""),if($E49="Minors",0,if($E49="FA Contract",if(and(N$1<=$I49,N$1>=$H49),$F49,""),if($E49="YP Contract",if(N$1=$H49,500000,if(N$1=($H49+1),1000000,if(N$1=($H49+2),1500000,"")))))))) -> 0 | O49: =if($E49="","",if($E49="Dropped",if(and(O$1<=$I49,O$1>=$H49),if(Year($D49)=O$1,$F49*0.8,if((year($D49)+1)=O$1,$F49*0.6,$F49*0.4)) ,""),if($E49="Minors",0,if($E49="FA Contract",if(and(O$1<=$I49,O$1>=$H49),$F49,""),if($E49="YP Contract",if(O$1=$H49,500000,if(O$1=($H49+1),1000000,if(O$1=($H49+2),1500000,"")))))))) -> 0 | P49: =if($E49="","",if($E49="Dropped",if(and(P$1<=$I49,P$1>=$H49),if(Year($D49)=P$1,$F49*0.8,if((year($D49)+1)=P$1,$F49*0.6,$F49*0.4)) ,""),if($E49="Minors",0,if($E49="FA Contract",if(and(P$1<=$I49,P$1>=$H49),$F49,""),if($E49="YP Contract",if(P$1=$H49,500000,if(P$1=($H49+1),1000000,if(P$1=($H49+2),1500000,"")))))))) -> 0
A50: Ricky Tiedemann | B50: Brenden Freedman | C50: 45343 | E50: Minors | F50: YP | G50: YP | I50: =if(H50="","",if(or($E50="FA Contract",$E50="Dropped"),$H50+$G50-1,if($E50="YP Contract",$H50+2,if(and($E50="Minors",$G50<>"YP"),$H50+$G50-1,if(and($E50="Minors",$G50="YP"),$H50+2,""))))) | J50: 33100000 | K50: =if($E50="","",if($E50="Dropped",if(and(K$1<=$I50,K$1>=$H50),if(Year($D50)=K$1,$F50*0.8,if((year($D50)+1)=K$1,$F50*0.6,$F50*0.4)) ,""),if($E50="Minors",0,if($E50="FA Contract",if(and(K$1<=$I50,K$1>=$H50),$F50,""),if($E50="YP Contract",if(K$1=$H50,500000,if(K$1=($H50+1),1000000,if(K$1=($H50+2),1500000,"")))))))) -> 0 | L50: =if($E50="","",if($E50="Dropped",if(and(L$1<=$I50,L$1>=$H50),if(Year($D50)=L$1,$F50*0.8,if((year($D50)+1)=L$1,$F50*0.6,$F50*0.4)) ,""),if($E50="Minors",0,if($E50="FA Contract",if(and(L$1<=$I50,L$1>=$H50),$F50,""),if($E50="YP Contract",if(L$1=$H50,500000,if(L$1=($H50+1),1000000,if(L$1=($H50+2),1500000,"")))))))) -> 0 | M50: =if($E50="","",if($E50="Dropped",if(and(M$1<=$I50,M$1>=$H50),if(Year($D50)=M$1,$F50*0.8,if((year($D50)+1)=M$1,$F50*0.6,$F50*0.4)) ,""),if($E50="Minors",0,if($E50="FA Contract",if(and(M$1<=$I50,M$1>=$H50),$F50,""),if($E50="YP Contract",if(M$1=$H50,500000,if(M$1=($H50+1),1000000,if(M$1=($H50+2),1500000,"")))))))) -> 0 | N50: =if($E50="","",if($E50="Dropped",if(and(N$1<=$I50,N$1>=$H50),if(Year($D50)=N$1,$F50*0.8,if((year($D50)+1)=N$1,$F50*0.6,$F50*0.4)) ,""),if($E50="Minors",0,if($E50="FA Contract",if(and(N$1<=$I50,N$1>=$H50),$F50,""),if($E50="YP Contract",if(N$1=$H50,500000,if(N$1=($H50+1),1000000,if(N$1=($H50+2),1500000,"")))))))) -> 0 | O50: =if($E50="","",if($E50="Dropped",if(and(O$1<=$I50,O$1>=$H50),if(Year($D50)=O$1,$F50*0.8,if((year($D50)+1)=O$1,$F50*0.6,$F50*0.4)) ,""),if($E50="Minors",0,if($E50="FA Contract",if(and(O$1<=$I50,O$1>=$H50),$F50,""),if($E50="YP Contract",if(O$1=$H50,500000,if(O$1=($H50+1),1000000,if(O$1=($H50+2),1500000,"")))))))) -> 0 | P50: =if($E50="","",if($E50="Dropped",if(and(P$1<=$I50,P$1>=$H50),if(Year($D50)=P$1,$F50*0.8,if((year($D50)+1)=P$1,$F50*0.6,$F50*0.4)) ,""),if($E50="Minors",0,if($E50="FA Contract",if(and(P$1<=$I50,P$1>=$H50),$F50,""),if($E50="YP Contract",if(P$1=$H50,500000,if(P$1=($H50+1),1000000,if(P$1=($H50+2),1500000,"")))))))) -> 0
A51: Thomas White | B51: Brenden Freedman | C51: 45358 | E51: Minors | F51: YP | G51: YP | I51: =if(H51="","",if(or($E51="FA Contract",$E51="Dropped"),$H51+$G51-1,if($E51="YP Contract",$H51+2,if(and($E51="Minors",$G51<>"YP"),$H51+$G51-1,if(and($E51="Minors",$G51="YP"),$H51+2,""))))) | J51: 33100000 | K51: =if($E51="","",if($E51="Dropped",if(and(K$1<=$I51,K$1>=$H51),if(Year($D51)=K$1,$F51*0.8,if((year($D51)+1)=K$1,$F51*0.6,$F51*0.4)) ,""),if($E51="Minors",0,if($E51="FA Contract",if(and(K$1<=$I51,K$1>=$H51),$F51,""),if($E51="YP Contract",if(K$1=$H51,500000,if(K$1=($H51+1),1000000,if(K$1=($H51+2),1500000,"")))))))) -> 0 | L51: =if($E51="","",if($E51="Dropped",if(and(L$1<=$I51,L$1>=$H51),if(Year($D51)=L$1,$F51*0.8,if((year($D51)+1)=L$1,$F51*0.6,$F51*0.4)) ,""),if($E51="Minors",0,if($E51="FA Contract",if(and(L$1<=$I51,L$1>=$H51),$F51,""),if($E51="YP Contract",if(L$1=$H51,500000,if(L$1=($H51+1),1000000,if(L$1=($H51+2),1500000,"")))))))) -> 0 | M51: =if($E51="","",if($E51="Dropped",if(and(M$1<=$I51,M$1>=$H51),if(Year($D51)=M$1,$F51*0.8,if((year($D51)+1)=M$1,$F51*0.6,$F51*0.4)) ,""),if($E51="Minors",0,if($E51="FA Contract",if(and(M$1<=$I51,M$1>=$H51),$F51,""),if($E51="YP Contract",if(M$1=$H51,500000,if(M$1=($H51+1),1000000,if(M$1=($H51+2),1500000,"")))))))) -> 0 | N51: =if($E51="","",if($E51="Dropped",if(and(N$1<=$I51,N$1>=$H51),if(Year($D51)=N$1,$F51*0.8,if((year($D51)+1)=N$1,$F51*0.6,$F51*0.4)) ,""),if($E51="Minors",0,if($E51="FA Contract",if(and(N$1<=$I51,N$1>=$H51),$F51,""),if($E51="YP Contract",if(N$1=$H51,500000,if(N$1=($H51+1),1000000,if(N$1=($H51+2),1500000,"")))))))) -> 0 | O51: =if($E51="","",if($E51="Dropped",if(and(O$1<=$I51,O$1>=$H51),if(Year($D51)=O$1,$F51*0.8,if((year($D51)+1)=O$1,$F51*0.6,$F51*0.4)) ,""),if($E51="Minors",0,if($E51="FA Contract",if(and(O$1<=$I51,O$1>=$H51),$F51,""),if($E51="YP Contract",if(O$1=$H51,500000,if(O$1=($H51+1),1000000,if(O$1=($H51+2),1500000,"")))))))) -> 0 | P51: =if($E51="","",if($E51="Dropped",if(and(P$1<=$I51,P$1>=$H51),if(Year($D51)=P$1,$F51*0.8,if((year($D51)+1)=P$1,$F51*0.6,$F51*0.4)) ,""),if($E51="Minors",0,if($E51="FA Contract",if(and(P$1<=$I51,P$1>=$H51),$F51,""),if($E51="YP Contract",if(P$1=$H51,500000,if(P$1=($H51+1),1000000,if(P$1=($H51+2),1500000,"")))))))) -> 0
A52: Tink Hence | B52: Brenden Freedman | C52: 45343 | E52: Minors | F52: YP | G52: YP | I52: =if(H52="","",if(or($E52="FA Contract",$E52="Dropped"),$H52+$G52-1,if($E52="YP Contract",$H52+2,if(and($E52="Minors",$G52<>"YP"),$H52+$G52-1,if(and($E52="Minors",$G52="YP"),$H52+2,""))))) | J52: 33100000 | K52: =if($E52="","",if($E52="Dropped",if(and(K$1<=$I52,K$1>=$H52),if(Year($D52)=K$1,$F52*0.8,if((year($D52)+1)=K$1,$F52*0.6,$F52*0.4)) ,""),if($E52="Minors",0,if($E52="FA Contract",if(and(K$1<=$I52,K$1>=$H52),$F52,""),if($E52="YP Contract",if(K$1=$H52,500000,if(K$1=($H52+1),1000000,if(K$1=($H52+2),1500000,"")))))))) -> 0 | L52: =if($E52="","",if($E52="Dropped",if(and(L$1<=$I52,L$1>=$H52),if(Year($D52)=L$1,$F52*0.8,if((year($D52)+1)=L$1,$F52*0.6,$F52*0.4)) ,""),if($E52="Minors",0,if($E52="FA Contract",if(and(L$1<=$I52,L$1>=$H52),$F52,""),if($E52="YP Contract",if(L$1=$H52,500000,if(L$1=($H52+1),1000000,if(L$1=($H52+2),1500000,"")))))))) -> 0 | M52: =if($E52="","",if($E52="Dropped",if(and(M$1<=$I52,M$1>=$H52),if(Year($D52)=M$1,$F52*0.8,if((year($D52)+1)=M$1,$F52*0.6,$F52*0.4)) ,""),if($E52="Minors",0,if($E52="FA Contract",if(and(M$1<=$I52,M$1>=$H52),$F52,""),if($E52="YP Contract",if(M$1=$H52,500000,if(M$1=($H52+1),1000000,if(M$1=($H52+2),1500000,"")))))))) -> 0 | N52: =if($E52="","",if($E52="Dropped",if(and(N$1<=$I52,N$1>=$H52),if(Year($D52)=N$1,$F52*0.8,if((year($D52)+1)=N$1,$F52*0.6,$F52*0.4)) ,""),if($E52="Minors",0,if($E52="FA Contract",if(and(N$1<=$I52,N$1>=$H52),$F52,""),if($E52="YP Contract",if(N$1=$H52,500000,if(N$1=($H52+1),1000000,if(N$1=($H52+2),1500000,"")))))))) -> 0 | O52: =if($E52="","",if($E52="Dropped",if(and(O$1<=$I52,O$1>=$H52),if(Year($D52)=O$1,$F52*0.8,if((year($D52)+1)=O$1,$F52*0.6,$F52*0.4)) ,""),if($E52="Minors",0,if($E52="FA Contract",if(and(O$1<=$I52,O$1>=$H52),$F52,""),if($E52="YP Contract",if(O$1=$H52,500000,if(O$1=($H52+1),1000000,if(O$1=($H52+2),1500000,"")))))))) -> 0 | P52: =if($E52="","",if($E52="Dropped",if(and(P$1<=$I52,P$1>=$H52),if(Year($D52)=P$1,$F52*0.8,if((year($D52)+1)=P$1,$F52*0.6,$F52*0.4)) ,""),if($E52="Minors",0,if($E52="FA Contract",if(and(P$1<=$I52,P$1>=$H52),$F52,""),if($E52="YP Contract",if(P$1=$H52,500000,if(P$1=($H52+1),1000000,if(P$1=($H52+2),1500000,"")))))))) -> 0
A53: Tommy Troy | B53: Brenden Freedman | C53: 45883 | E53: Minors | F53: YP | G53: YP | I53: =if(H53="","",if(or($E53="FA Contract",$E53="Dropped"),$H53+$G53-1,if($E53="YP Contract",$H53+2,if(and($E53="Minors",$G53<>"YP"),$H53+$G53-1,if(and($E53="Minors",$G53="YP"),$H53+2,""))))) | J53: 33100000 | K53: =if($E53="","",if($E53="Dropped",if(and(K$1<=$I53,K$1>=$H53),if(Year($D53)=K$1,$F53*0.8,if((year($D53)+1)=K$1,$F53*0.6,$F53*0.4)) ,""),if($E53="Minors",0,if($E53="FA Contract",if(and(K$1<=$I53,K$1>=$H53),$F53,""),if($E53="YP Contract",if(K$1=$H53,500000,if(K$1=($H53+1),1000000,if(K$1=($H53+2),1500000,"")))))))) -> 0 | L53: =if($E53="","",if($E53="Dropped",if(and(L$1<=$I53,L$1>=$H53),if(Year($D53)=L$1,$F53*0.8,if((year($D53)+1)=L$1,$F53*0.6,$F53*0.4)) ,""),if($E53="Minors",0,if($E53="FA Contract",if(and(L$1<=$I53,L$1>=$H53),$F53,""),if($E53="YP Contract",if(L$1=$H53,500000,if(L$1=($H53+1),1000000,if(L$1=($H53+2),1500000,"")))))))) -> 0 | M53: =if($E53="","",if($E53="Dropped",if(and(M$1<=$I53,M$1>=$H53),if(Year($D53)=M$1,$F53*0.8,if((year($D53)+1)=M$1,$F53*0.6,$F53*0.4)) ,""),if($E53="Minors",0,if($E53="FA Contract",if(and(M$1<=$I53,M$1>=$H53),$F53,""),if($E53="YP Contract",if(M$1=$H53,500000,if(M$1=($H53+1),1000000,if(M$1=($H53+2),1500000,"")))))))) -> 0 | N53: =if($E53="","",if($E53="Dropped",if(and(N$1<=$I53,N$1>=$H53),if(Year($D53)=N$1,$F53*0.8,if((year($D53)+1)=N$1,$F53*0.6,$F53*0.4)) ,""),if($E53="Minors",0,if($E53="FA Contract",if(and(N$1<=$I53,N$1>=$H53),$F53,""),if($E53="YP Contract",if(N$1=$H53,500000,if(N$1=($H53+1),1000000,if(N$1=($H53+2),1500000,"")))))))) -> 0 | O53: =if($E53="","",if($E53="Dropped",if(and(O$1<=$I53,O$1>=$H53),if(Year($D53)=O$1,$F53*0.8,if((year($D53)+1)=O$1,$F53*0.6,$F53*0.4)) ,""),if($E53="Minors",0,if($E53="FA Contract",if(and(O$1<=$I53,O$1>=$H53),$F53,""),if($E53="YP Contract",if(O$1=$H53,500000,if(O$1=($H53+1),1000000,if(O$1=($H53+2),1500000,"")))))))) -> 0 | P53: =if($E53="","",if($E53="Dropped",if(and(P$1<=$I53,P$1>=$H53),if(Year($D53)=P$1,$F53*0.8,if((year($D53)+1)=P$1,$F53*0.6,$F53*0.4)) ,""),if($E53="Minors",0,if($E53="FA Contract",if(and(P$1<=$I53,P$1>=$H53),$F53,""),if($E53="YP Contract",if(P$1=$H53,500000,if(P$1=($H53+1),1000000,if(P$1=($H53+2),1500000,"")))))))) -> 0
A54: Trey Yesavage | B54: Brenden Freedman | C54: 45689 | E54: Minors | F54: YP | G54: YP | I54: =if(H54="","",if(or($E54="FA Contract",$E54="Dropped"),$H54+$G54-1,if($E54="YP Contract",$H54+2,if(and($E54="Minors",$G54<>"YP"),$H54+$G54-1,if(and($E54="Minors",$G54="YP"),$H54+2,""))))) | J54: 33100000 | K54: =if($E54="","",if($E54="Dropped",if(and(K$1<=$I54,K$1>=$H54),if(Year($D54)=K$1,$F54*0.8,if((year($D54)+1)=K$1,$F54*0.6,$F54*0.4)) ,""),if($E54="Minors",0,if($E54="FA Contract",if(and(K$1<=$I54,K$1>=$H54),$F54,""),if($E54="YP Contract",if(K$1=$H54,500000,if(K$1=($H54+1),1000000,if(K$1=($H54+2),1500000,"")))))))) -> 0 | L54: =if($E54="","",if($E54="Dropped",if(and(L$1<=$I54,L$1>=$H54),if(Year($D54)=L$1,$F54*0.8,if((year($D54)+1)=L$1,$F54*0.6,$F54*0.4)) ,""),if($E54="Minors",0,if($E54="FA Contract",if(and(L$1<=$I54,L$1>=$H54),$F54,""),if($E54="YP Contract",if(L$1=$H54,500000,if(L$1=($H54+1),1000000,if(L$1=($H54+2),1500000,"")))))))) -> 0 | M54: =if($E54="","",if($E54="Dropped",if(and(M$1<=$I54,M$1>=$H54),if(Year($D54)=M$1,$F54*0.8,if((year($D54)+1)=M$1,$F54*0.6,$F54*0.4)) ,""),if($E54="Minors",0,if($E54="FA Contract",if(and(M$1<=$I54,M$1>=$H54),$F54,""),if($E54="YP Contract",if(M$1=$H54,500000,if(M$1=($H54+1),1000000,if(M$1=($H54+2),1500000,"")))))))) -> 0 | N54: =if($E54="","",if($E54="Dropped",if(and(N$1<=$I54,N$1>=$H54),if(Year($D54)=N$1,$F54*0.8,if((year($D54)+1)=N$1,$F54*0.6,$F54*0.4)) ,""),if($E54="Minors",0,if($E54="FA Contract",if(and(N$1<=$I54,N$1>=$H54),$F54,""),if($E54="YP Contract",if(N$1=$H54,500000,if(N$1=($H54+1),1000000,if(N$1=($H54+2),1500000,"")))))))) -> 0 | O54: =if($E54="","",if($E54="Dropped",if(and(O$1<=$I54,O$1>=$H54),if(Year($D54)=O$1,$F54*0.8,if((year($D54)+1)=O$1,$F54*0.6,$F54*0.4)) ,""),if($E54="Minors",0,if($E54="FA Contract",if(and(O$1<=$I54,O$1>=$H54),$F54,""),if($E54="YP Contract",if(O$1=$H54,500000,if(O$1=($H54+1),1000000,if(O$1=($H54+2),1500000,"")))))))) -> 0 | P54: =if($E54="","",if($E54="Dropped",if(and(P$1<=$I54,P$1>=$H54),if(Year($D54)=P$1,$F54*0.8,if((year($D54)+1)=P$1,$F54*0.6,$F54*0.4)) ,""),if($E54="Minors",0,if($E54="FA Contract",if(and(P$1<=$I54,P$1>=$H54),$F54,""),if($E54="YP Contract",if(P$1=$H54,500000,if(P$1=($H54+1),1000000,if(P$1=($H54+2),1500000,"")))))))) -> 0
A55: Yordan Alvarez | B55: Brian Frederick | C55: 45318 | E55: FA Contract | F55: 32400000 | G55: 5 | H55: 2024 | I55: =if(H55="","",if(or($E55="FA Contract",$E55="Dropped"),$H55+$G55-1,if($E55="YP Contract",$H55+2,if(and($E55="Minors",$G55<>"YP"),$H55+$G55-1,if(and($E55="Minors",$G55="YP"),$H55+2,""))))) -> 2028 | J55: 33100000 | K55: =if($E55="","",if($E55="Dropped",if(and(K$1<=$I55,K$1>=$H55),if(Year($D55)=K$1,$F55*0.8,if((year($D55)+1)=K$1,$F55*0.6,$F55*0.4)) ,""),if($E55="Minors",0,if($E55="FA Contract",if(and(K$1<=$I55,K$1>=$H55),$F55,""),if($E55="YP Contract",if(K$1=$H55,500000,if(K$1=($H55+1),1000000,if(K$1=($H55+2),1500000,"")))))))) -> 32400000 | L55: =if($E55="","",if($E55="Dropped",if(and(L$1<=$I55,L$1>=$H55),if(Year($D55)=L$1,$F55*0.8,if((year($D55)+1)=L$1,$F55*0.6,$F55*0.4)) ,""),if($E55="Minors",0,if($E55="FA Contract",if(and(L$1<=$I55,L$1>=$H55),$F55,""),if($E55="YP Contract",if(L$1=$H55,500000,if(L$1=($H55+1),1000000,if(L$1=($H55+2),1500000,"")))))))) -> 32400000 | M55: =if($E55="","",if($E55="Dropped",if(and(M$1<=$I55,M$1>=$H55),if(Year($D55)=M$1,$F55*0.8,if((year($D55)+1)=M$1,$F55*0.6,$F55*0.4)) ,""),if($E55="Minors",0,if($E55="FA Contract",if(and(M$1<=$I55,M$1>=$H55),$F55,""),if($E55="YP Contract",if(M$1=$H55,500000,if(M$1=($H55+1),1000000,if(M$1=($H55+2),1500000,"")))))))) -> 32400000 | N55: =if($E55="","",if($E55="Dropped",if(and(N$1<=$I55,N$1>=$H55),if(Year($D55)=N$1,$F55*0.8,if((year($D55)+1)=N$1,$F55*0.6,$F55*0.4)) ,""),if($E55="Minors",0,if($E55="FA Contract",if(and(N$1<=$I55,N$1>=$H55),$F55,""),if($E55="YP Contract",if(N$1=$H55,500000,if(N$1=($H55+1),1000000,if(N$1=($H55+2),1500000,"")))))))) -> 32400000 | O55: =if($E55="","",if($E55="Dropped",if(and(O$1<=$I55,O$1>=$H55),if(Year($D55)=O$1,$F55*0.8,if((year($D55)+1)=O$1,$F55*0.6,$F55*0.4)) ,""),if($E55="Minors",0,if($E55="FA Contract",if(and(O$1<=$I55,O$1>=$H55),$F55,""),if($E55="YP Contract",if(O$1=$H55,500000,if(O$1=($H55+1),1000000,if(O$1=($H55+2),1500000,"")))))))) | P55: =if($E55="","",if($E55="Dropped",if(and(P$1<=$I55,P$1>=$H55),if(Year($D55)=P$1,$F55*0.8,if((year($D55)+1)=P$1,$F55*0.6,$F55*0.4)) ,""),if($E55="Minors",0,if($E55="FA Contract",if(and(P$1<=$I55,P$1>=$H55),$F55,""),if($E55="YP Contract",if(P$1=$H55,500000,if(P$1=($H55+1),1000000,if(P$1=($H55+2),1500000,""))))))))
A56: Mookie Betts | B56: Brian Frederick | C56: 45318 | E56: FA Contract | F56: 30000000 | G56: 3 | H56: 2024 | I56: =if(H56="","",if(or($E56="FA Contract",$E56="Dropped"),$H56+$G56-1,if($E56="YP Contract",$H56+2,if(and($E56="Minors",$G56<>"YP"),$H56+$G56-1,if(and($E56="Minors",$G56="YP"),$H56+2,""))))) -> 2026 | J56: 33100000 | K56: =if($E56="","",if($E56="Dropped",if(and(K$1<=$I56,K$1>=$H56),if(Year($D56)=K$1,$F56*0.8,if((year($D56)+1)=K$1,$F56*0.6,$F56*0.4)) ,""),if($E56="Minors",0,if($E56="FA Contract",if(and(K$1<=$I56,K$1>=$H56),$F56,""),if($E56="YP Contract",if(K$1=$H56,500000,if(K$1=($H56+1),1000000,if(K$1=($H56+2),1500000,"")))))))) -> 30000000 | L56: =if($E56="","",if($E56="Dropped",if(and(L$1<=$I56,L$1>=$H56),if(Year($D56)=L$1,$F56*0.8,if((year($D56)+1)=L$1,$F56*0.6,$F56*0.4)) ,""),if($E56="Minors",0,if($E56="FA Contract",if(and(L$1<=$I56,L$1>=$H56),$F56,""),if($E56="YP Contract",if(L$1=$H56,500000,if(L$1=($H56+1),1000000,if(L$1=($H56+2),1500000,"")))))))) -> 30000000 | M56: =if($E56="","",if($E56="Dropped",if(and(M$1<=$I56,M$1>=$H56),if(Year($D56)=M$1,$F56*0.8,if((year($D56)+1)=M$1,$F56*0.6,$F56*0.4)) ,""),if($E56="Minors",0,if($E56="FA Contract",if(and(M$1<=$I56,M$1>=$H56),$F56,""),if($E56="YP Contract",if(M$1=$H56,500000,if(M$1=($H56+1),1000000,if(M$1=($H56+2),1500000,"")))))))) | N56: =if($E56="","",if($E56="Dropped",if(and(N$1<=$I56,N$1>=$H56),if(Year($D56)=N$1,$F56*0.8,if((year($D56)+1)=N$1,$F56*0.6,$F56*0.4)) ,""),if($E56="Minors",0,if($E56="FA Contract",if(and(N$1<=$I56,N$1>=$H56),$F56,""),if($E56="YP Contract",if(N$1=$H56,500000,if(N$1=($H56+1),1000000,if(N$1=($H56+2),1500000,"")))))))) | O56: =if($E56="","",if($E56="Dropped",if(and(O$1<=$I56,O$1>=$H56),if(Year($D56)=O$1,$F56*0.8,if((year($D56)+1)=O$1,$F56*0.6,$F56*0.4)) ,""),if($E56="Minors",0,if($E56="FA Contract",if(and(O$1<=$I56,O$1>=$H56),$F56,""),if($E56="YP Contract",if(O$1=$H56,500000,if(O$1=($H56+1),1000000,if(O$1=($H56+2),1500000,"")))))))) | P56: =if($E56="","",if($E56="Dropped",if(and(P$1<=$I56,P$1>=$H56),if(Year($D56)=P$1,$F56*0.8,if((year($D56)+1)=P$1,$F56*0.6,$F56*0.4)) ,""),if($E56="Minors",0,if($E56="FA Contract",if(and(P$1<=$I56,P$1>=$H56),$F56,""),if($E56="YP Contract",if(P$1=$H56,500000,if(P$1=($H56+1),1000000,if(P$1=($H56+2),1500000,""))))))))
A57: Logan Webb | B57: Brian Frederick | C57: 45687 | E57: FA Contract | F57: 12000000 | G57: 4 | H57: 2025 | I57: =if(H57="","",if(or($E57="FA Contract",$E57="Dropped"),$H57+$G57-1,if($E57="YP Contract",$H57+2,if(and($E57="Minors",$G57<>"YP"),$H57+$G57-1,if(and($E57="Minors",$G57="YP"),$H57+2,""))))) -> 2028 | J57: 33100000 | K57: =if($E57="","",if($E57="Dropped",if(and(K$1<=$I57,K$1>=$H57),if(Year($D57)=K$1,$F57*0.8,if((year($D57)+1)=K$1,$F57*0.6,$F57*0.4)) ,""),if($E57="Minors",0,if($E57="FA Contract",if(and(K$1<=$I57,K$1>=$H57),$F57,""),if($E57="YP Contract",if(K$1=$H57,500000,if(K$1=($H57+1),1000000,if(K$1=($H57+2),1500000,"")))))))) -> 12000000 | L57: =if($E57="","",if($E57="Dropped",if(and(L$1<=$I57,L$1>=$H57),if(Year($D57)=L$1,$F57*0.8,if((year($D57)+1)=L$1,$F57*0.6,$F57*0.4)) ,""),if($E57="Minors",0,if($E57="FA Contract",if(and(L$1<=$I57,L$1>=$H57),$F57,""),if($E57="YP Contract",if(L$1=$H57,500000,if(L$1=($H57+1),1000000,if(L$1=($H57+2),1500000,"")))))))) -> 12000000 | M57: =if($E57="","",if($E57="Dropped",if(and(M$1<=$I57,M$1>=$H57),if(Year($D57)=M$1,$F57*0.8,if((year($D57)+1)=M$1,$F57*0.6,$F57*0.4)) ,""),if($E57="Minors",0,if($E57="FA Contract",if(and(M$1<=$I57,M$1>=$H57),$F57,""),if($E57="YP Contract",if(M$1=$H57,500000,if(M$1=($H57+1),1000000,if(M$1=($H57+2),1500000,"")))))))) -> 12000000 | N57: =if($E57="","",if($E57="Dropped",if(and(N$1<=$I57,N$1>=$H57),if(Year($D57)=N$1,$F57*0.8,if((year($D57)+1)=N$1,$F57*0.6,$F57*0.4)) ,""),if($E57="Minors",0,if($E57="FA Contract",if(and(N$1<=$I57,N$1>=$H57),$F57,""),if($E57="YP Contract",if(N$1=$H57,500000,if(N$1=($H57+1),1000000,if(N$1=($H57+2),1500000,"")))))))) -> 12000000 | O57: =if($E57="","",if($E57="Dropped",if(and(O$1<=$I57,O$1>=$H57),if(Year($D57)=O$1,$F57*0.8,if((year($D57)+1)=O$1,$F57*0.6,$F57*0.4)) ,""),if($E57="Minors",0,if($E57="FA Contract",if(and(O$1<=$I57,O$1>=$H57),$F57,""),if($E57="YP Contract",if(O$1=$H57,500000,if(O$1=($H57+1),1000000,if(O$1=($H57+2),1500000,"")))))))) | P57: =if($E57="","",if($E57="Dropped",if(and(P$1<=$I57,P$1>=$H57),if(Year($D57)=P$1,$F57*0.8,if((year($D57)+1)=P$1,$F57*0.6,$F57*0.4)) ,""),if($E57="Minors",0,if($E57="FA Contract",if(and(P$1<=$I57,P$1>=$H57),$F57,""),if($E57="YP Contract",if(P$1=$H57,500000,if(P$1=($H57+1),1000000,if(P$1=($H57+2),1500000,""))))))))
A58: Amed Rosario | B58: Brian Frederick | C58: 45356 | E58: FA Contract | F58: 5000000 | G58: 2 | H58: 2024 | I58: =if(H58="","",if(or($E58="FA Contract",$E58="Dropped"),$H58+$G58-1,if($E58="YP Contract",$H58+2,if(and($E58="Minors",$G58<>"YP"),$H58+$G58-1,if(and($E58="Minors",$G58="YP"),$H58+2,""))))) -> 2025 | J58: 33100000 | K58: =if($E58="","",if($E58="Dropped",if(and(K$1<=$I58,K$1>=$H58),if(Year($D58)=K$1,$F58*0.8,if((year($D58)+1)=K$1,$F58*0.6,$F58*0.4)) ,""),if($E58="Minors",0,if($E58="FA Contract",if(and(K$1<=$I58,K$1>=$H58),$F58,""),if($E58="YP Contract",if(K$1=$H58,500000,if(K$1=($H58+1),1000000,if(K$1=($H58+2),1500000,"")))))))) -> 5000000 | L58: =if($E58="","",if($E58="Dropped",if(and(L$1<=$I58,L$1>=$H58),if(Year($D58)=L$1,$F58*0.8,if((year($D58)+1)=L$1,$F58*0.6,$F58*0.4)) ,""),if($E58="Minors",0,if($E58="FA Contract",if(and(L$1<=$I58,L$1>=$H58),$F58,""),if($E58="YP Contract",if(L$1=$H58,500000,if(L$1=($H58+1),1000000,if(L$1=($H58+2),1500000,"")))))))) | M58: =if($E58="","",if($E58="Dropped",if(and(M$1<=$I58,M$1>=$H58),if(Year($D58)=M$1,$F58*0.8,if((year($D58)+1)=M$1,$F58*0.6,$F58*0.4)) ,""),if($E58="Minors",0,if($E58="FA Contract",if(and(M$1<=$I58,M$1>=$H58),$F58,""),if($E58="YP Contract",if(M$1=$H58,500000,if(M$1=($H58+1),1000000,if(M$1=($H58+2),1500000,"")))))))) | N58: =if($E58="","",if($E58="Dropped",if(and(N$1<=$I58,N$1>=$H58),if(Year($D58)=N$1,$F58*0.8,if((year($D58)+1)=N$1,$F58*0.6,$F58*0.4)) ,""),if($E58="Minors",0,if($E58="FA Contract",if(and(N$1<=$I58,N$1>=$H58),$F58,""),if($E58="YP Contract",if(N$1=$H58,500000,if(N$1=($H58+1),1000000,if(N$1=($H58+2),1500000,"")))))))) | O58: =if($E58="","",if($E58="Dropped",if(and(O$1<=$I58,O$1>=$H58),if(Year($D58)=O$1,$F58*0.8,if((year($D58)+1)=O$1,$F58*0.6,$F58*0.4)) ,""),if($E58="Minors",0,if($E58="FA Contract",if(and(O$1<=$I58,O$1>=$H58),$F58,""),if($E58="YP Contract",if(O$1=$H58,500000,if(O$1=($H58+1),1000000,if(O$1=($H58+2),1500000,"")))))))) | P58: =if($E58="","",if($E58="Dropped",if(and(P$1<=$I58,P$1>=$H58),if(Year($D58)=P$1,$F58*0.8,if((year($D58)+1)=P$1,$F58*0.6,$F58*0.4)) ,""),if($E58="Minors",0,if($E58="FA Contract",if(and(P$1<=$I58,P$1>=$H58),$F58,""),if($E58="YP Contract",if(P$1=$H58,500000,if(P$1=($H58+1),1000000,if(P$1=($H58+2),1500000,""))))))))
A59: Chris Bassitt | B59: Brian Frederick | C59: 45721 | E59: FA Contract | F59: 5000000 | G59: 2 | H59: 2025 | I59: =if(H59="","",if(or($E59="FA Contract",$E59="Dropped"),$H59+$G59-1,if($E59="YP Contract",$H59+2,if(and($E59="Minors",$G59<>"YP"),$H59+$G59-1,if(and($E59="Minors",$G59="YP"),$H59+2,""))))) -> 2026 | J59: 33100000 | K59: =if($E59="","",if($E59="Dropped",if(and(K$1<=$I59,K$1>=$H59),if(Year($D59)=K$1,$F59*0.8,if((year($D59)+1)=K$1,$F59*0.6,$F59*0.4)) ,""),if($E59="Minors",0,if($E59="FA Contract",if(and(K$1<=$I59,K$1>=$H59),$F59,""),if($E59="YP Contract",if(K$1=$H59,500000,if(K$1=($H59+1),1000000,if(K$1=($H59+2),1500000,"")))))))) -> 5000000 | L59: =if($E59="","",if($E59="Dropped",if(and(L$1<=$I59,L$1>=$H59),if(Year($D59)=L$1,$F59*0.8,if((year($D59)+1)=L$1,$F59*0.6,$F59*0.4)) ,""),if($E59="Minors",0,if($E59="FA Contract",if(and(L$1<=$I59,L$1>=$H59),$F59,""),if($E59="YP Contract",if(L$1=$H59,500000,if(L$1=($H59+1),1000000,if(L$1=($H59+2),1500000,"")))))))) -> 5000000 | M59: =if($E59="","",if($E59="Dropped",if(and(M$1<=$I59,M$1>=$H59),if(Year($D59)=M$1,$F59*0.8,if((year($D59)+1)=M$1,$F59*0.6,$F59*0.4)) ,""),if($E59="Minors",0,if($E59="FA Contract",if(and(M$1<=$I59,M$1>=$H59),$F59,""),if($E59="YP Contract",if(M$1=$H59,500000,if(M$1=($H59+1),1000000,if(M$1=($H59+2),1500000,"")))))))) | N59: =if($E59="","",if($E59="Dropped",if(and(N$1<=$I59,N$1>=$H59),if(Year($D59)=N$1,$F59*0.8,if((year($D59)+1)=N$1,$F59*0.6,$F59*0.4)) ,""),if($E59="Minors",0,if($E59="FA Contract",if(and(N$1<=$I59,N$1>=$H59),$F59,""),if($E59="YP Contract",if(N$1=$H59,500000,if(N$1=($H59+1),1000000,if(N$1=($H59+2),1500000,"")))))))) | O59: =if($E59="","",if($E59="Dropped",if(and(O$1<=$I59,O$1>=$H59),if(Year($D59)=O$1,$F59*0.8,if((year($D59)+1)=O$1,$F59*0.6,$F59*0.4)) ,""),if($E59="Minors",0,if($E59="FA Contract",if(and(O$1<=$I59,O$1>=$H59),$F59,""),if($E59="YP Contract",if(O$1=$H59,500000,if(O$1=($H59+1),1000000,if(O$1=($H59+2),1500000,"")))))))) | P59: =if($E59="","",if($E59="Dropped",if(and(P$1<=$I59,P$1>=$H59),if(Year($D59)=P$1,$F59*0.8,if((year($D59)+1)=P$1,$F59*0.6,$F59*0.4)) ,""),if($E59="Minors",0,if($E59="FA Contract",if(and(P$1<=$I59,P$1>=$H59),$F59,""),if($E59="YP Contract",if(P$1=$H59,500000,if(P$1=($H59+1),1000000,if(P$1=($H59+2),1500000,""))))))))
A60: Jeremy Pena | B60: Brian Frederick | C60: 45721 | E60: FA Contract | F60: 5000000 | G60: 2 | H60: 2025 | I60: =if(H60="","",if(or($E60="FA Contract",$E60="Dropped"),$H60+$G60-1,if($E60="YP Contract",$H60+2,if(and($E60="Minors",$G60<>"YP"),$H60+$G60-1,if(and($E60="Minors",$G60="YP"),$H60+2,""))))) -> 2026 | J60: 33100000 | K60: =if($E60="","",if($E60="Dropped",if(and(K$1<=$I60,K$1>=$H60),if(Year($D60)=K$1,$F60*0.8,if((year($D60)+1)=K$1,$F60*0.6,$F60*0.4)) ,""),if($E60="Minors",0,if($E60="FA Contract",if(and(K$1<=$I60,K$1>=$H60),$F60,""),if($E60="YP Contract",if(K$1=$H60,500000,if(K$1=($H60+1),1000000,if(K$1=($H60+2),1500000,"")))))))) -> 5000000 | L60: =if($E60="","",if($E60="Dropped",if(and(L$1<=$I60,L$1>=$H60),if(Year($D60)=L$1,$F60*0.8,if((year($D60)+1)=L$1,$F60*0.6,$F60*0.4)) ,""),if($E60="Minors",0,if($E60="FA Contract",if(and(L$1<=$I60,L$1>=$H60),$F60,""),if($E60="YP Contract",if(L$1=$H60,500000,if(L$1=($H60+1),1000000,if(L$1=($H60+2),1500000,"")))))))) -> 5000000 | M60: =if($E60="","",if($E60="Dropped",if(and(M$1<=$I60,M$1>=$H60),if(Year($D60)=M$1,$F60*0.8,if((year($D60)+1)=M$1,$F60*0.6,$F60*0.4)) ,""),if($E60="Minors",0,if($E60="FA Contract",if(and(M$1<=$I60,M$1>=$H60),$F60,""),if($E60="YP Contract",if(M$1=$H60,500000,if(M$1=($H60+1),1000000,if(M$1=($H60+2),1500000,"")))))))) | N60: =if($E60="","",if($E60="Dropped",if(and(N$1<=$I60,N$1>=$H60),if(Year($D60)=N$1,$F60*0.8,if((year($D60)+1)=N$1,$F60*0.6,$F60*0.4)) ,""),if($E60="Minors",0,if($E60="FA Contract",if(and(N$1<=$I60,N$1>=$H60),$F60,""),if($E60="YP Contract",if(N$1=$H60,500000,if(N$1=($H60+1),1000000,if(N$1=($H60+2),1500000,"")))))))) | O60: =if($E60="","",if($E60="Dropped",if(and(O$1<=$I60,O$1>=$H60),if(Year($D60)=O$1,$F60*0.8,if((year($D60)+1)=O$1,$F60*0.6,$F60*0.4)) ,""),if($E60="Minors",0,if($E60="FA Contract",if(and(O$1<=$I60,O$1>=$H60),$F60,""),if($E60="YP Contract",if(O$1=$H60,500000,if(O$1=($H60+1),1000000,if(O$1=($H60+2),1500000,"")))))))) | P60: =if($E60="","",if($E60="Dropped",if(and(P$1<=$I60,P$1>=$H60),if(Year($D60)=P$1,$F60*0.8,if((year($D60)+1)=P$1,$F60*0.6,$F60*0.4)) ,""),if($E60="Minors",0,if($E60="FA Contract",if(and(P$1<=$I60,P$1>=$H60),$F60,""),if($E60="YP Contract",if(P$1=$H60,500000,if(P$1=($H60+1),1000000,if(P$1=($H60+2),1500000,""))))))))
A61: Jorge Soler | B61: Brian Frederick | C61: 45356 | E61: FA Contract | F61: 5000000 | G61: 2 | H61: 2024 | I61: =if(H61="","",if(or($E61="FA Contract",$E61="Dropped"),$H61+$G61-1,if($E61="YP Contract",$H61+2,if(and($E61="Minors",$G61<>"YP"),$H61+$G61-1,if(and($E61="Minors",$G61="YP"),$H61+2,""))))) -> 2025 | J61: 33100000 | K61: =if($E61="","",if($E61="Dropped",if(and(K$1<=$I61,K$1>=$H61),if(Year($D61)=K$1,$F61*0.8,if((year($D61)+1)=K$1,$F61*0.6,$F61*0.4)) ,""),if($E61="Minors",0,if($E61="FA Contract",if(and(K$1<=$I61,K$1>=$H61),$F61,""),if($E61="YP Contract",if(K$1=$H61,500000,if(K$1=($H61+1),1000000,if(K$1=($H61+2),1500000,"")))))))) -> 5000000 | L61: =if($E61="","",if($E61="Dropped",if(and(L$1<=$I61,L$1>=$H61),if(Year($D61)=L$1,$F61*0.8,if((year($D61)+1)=L$1,$F61*0.6,$F61*0.4)) ,""),if($E61="Minors",0,if($E61="FA Contract",if(and(L$1<=$I61,L$1>=$H61),$F61,""),if($E61="YP Contract",if(L$1=$H61,500000,if(L$1=($H61+1),1000000,if(L$1=($H61+2),1500000,"")))))))) | M61: =if($E61="","",if($E61="Dropped",if(and(M$1<=$I61,M$1>=$H61),if(Year($D61)=M$1,$F61*0.8,if((year($D61)+1)=M$1,$F61*0.6,$F61*0.4)) ,""),if($E61="Minors",0,if($E61="FA Contract",if(and(M$1<=$I61,M$1>=$H61),$F61,""),if($E61="YP Contract",if(M$1=$H61,500000,if(M$1=($H61+1),1000000,if(M$1=($H61+2),1500000,"")))))))) | N61: =if($E61="","",if($E61="Dropped",if(and(N$1<=$I61,N$1>=$H61),if(Year($D61)=N$1,$F61*0.8,if((year($D61)+1)=N$1,$F61*0.6,$F61*0.4)) ,""),if($E61="Minors",0,if($E61="FA Contract",if(and(N$1<=$I61,N$1>=$H61),$F61,""),if($E61="YP Contract",if(N$1=$H61,500000,if(N$1=($H61+1),1000000,if(N$1=($H61+2),1500000,"")))))))) | O61: =if($E61="","",if($E61="Dropped",if(and(O$1<=$I61,O$1>=$H61),if(Year($D61)=O$1,$F61*0.8,if((year($D61)+1)=O$1,$F61*0.6,$F61*0.4)) ,""),if($E61="Minors",0,if($E61="FA Contract",if(and(O$1<=$I61,O$1>=$H61),$F61,""),if($E61="YP Contract",if(O$1=$H61,500000,if(O$1=($H61+1),1000000,if(O$1=($H61+2),1500000,"")))))))) | P61: =if($E61="","",if($E61="Dropped",if(and(P$1<=$I61,P$1>=$H61),if(Year($D61)=P$1,$F61*0.8,if((year($D61)+1)=P$1,$F61*0.6,$F61*0.4)) ,""),if($E61="Minors",0,if($E61="FA Contract",if(and(P$1<=$I61,P$1>=$H61),$F61,""),if($E61="YP Contract",if(P$1=$H61,500000,if(P$1=($H61+1),1000000,if(P$1=($H61+2),1500000,""))))))))
A62: Lance Lynn | B62: Brian Frederick | C62: 45356 | E62: FA Contract | F62: 5000000 | G62: 2 | H62: 2024 | I62: =if(H62="","",if(or($E62="FA Contract",$E62="Dropped"),$H62+$G62-1,if($E62="YP Contract",$H62+2,if(and($E62="Minors",$G62<>"YP"),$H62+$G62-1,if(and($E62="Minors",$G62="YP"),$H62+2,""))))) -> 2025 | J62: 33100000 | K62: =if($E62="","",if($E62="Dropped",if(and(K$1<=$I62,K$1>=$H62),if(Year($D62)=K$1,$F62*0.8,if((year($D62)+1)=K$1,$F62*0.6,$F62*0.4)) ,""),if($E62="Minors",0,if($E62="FA Contract",if(and(K$1<=$I62,K$1>=$H62),$F62,""),if($E62="YP Contract",if(K$1=$H62,500000,if(K$1=($H62+1),1000000,if(K$1=($H62+2),1500000,"")))))))) -> 5000000 | L62: =if($E62="","",if($E62="Dropped",if(and(L$1<=$I62,L$1>=$H62),if(Year($D62)=L$1,$F62*0.8,if((year($D62)+1)=L$1,$F62*0.6,$F62*0.4)) ,""),if($E62="Minors",0,if($E62="FA Contract",if(and(L$1<=$I62,L$1>=$H62),$F62,""),if($E62="YP Contract",if(L$1=$H62,500000,if(L$1=($H62+1),1000000,if(L$1=($H62+2),1500000,"")))))))) | M62: =if($E62="","",if($E62="Dropped",if(and(M$1<=$I62,M$1>=$H62),if(Year($D62)=M$1,$F62*0.8,if((year($D62)+1)=M$1,$F62*0.6,$F62*0.4)) ,""),if($E62="Minors",0,if($E62="FA Contract",if(and(M$1<=$I62,M$1>=$H62),$F62,""),if($E62="YP Contract",if(M$1=$H62,500000,if(M$1=($H62+1),1000000,if(M$1=($H62+2),1500000,"")))))))) | N62: =if($E62="","",if($E62="Dropped",if(and(N$1<=$I62,N$1>=$H62),if(Year($D62)=N$1,$F62*0.8,if((year($D62)+1)=N$1,$F62*0.6,$F62*0.4)) ,""),if($E62="Minors",0,if($E62="FA Contract",if(and(N$1<=$I62,N$1>=$H62),$F62,""),if($E62="YP Contract",if(N$1=$H62,500000,if(N$1=($H62+1),1000000,if(N$1=($H62+2),1500000,"")))))))) | O62: =if($E62="","",if($E62="Dropped",if(and(O$1<=$I62,O$1>=$H62),if(Year($D62)=O$1,$F62*0.8,if((year($D62)+1)=O$1,$F62*0.6,$F62*0.4)) ,""),if($E62="Minors",0,if($E62="FA Contract",if(and(O$1<=$I62,O$1>=$H62),$F62,""),if($E62="YP Contract",if(O$1=$H62,500000,if(O$1=($H62+1),1000000,if(O$1=($H62+2),1500000,"")))))))) | P62: =if($E62="","",if($E62="Dropped",if(and(P$1<=$I62,P$1>=$H62),if(Year($D62)=P$1,$F62*0.8,if((year($D62)+1)=P$1,$F62*0.6,$F62*0.4)) ,""),if($E62="Minors",0,if($E62="FA Contract",if(and(P$1<=$I62,P$1>=$H62),$F62,""),if($E62="YP Contract",if(P$1=$H62,500000,if(P$1=($H62+1),1000000,if(P$1=($H62+2),1500000,""))))))))
A63: Max Muincy | B63: Brian Frederick | C63: 45356 | E63: FA Contract | F63: 5000000 | G63: 2 | H63: 2024 | I63: =if(H63="","",if(or($E63="FA Contract",$E63="Dropped"),$H63+$G63-1,if($E63="YP Contract",$H63+2,if(and($E63="Minors",$G63<>"YP"),$H63+$G63-1,if(and($E63="Minors",$G63="YP"),$H63+2,""))))) -> 2025 | J63: 33100000 | K63: =if($E63="","",if($E63="Dropped",if(and(K$1<=$I63,K$1>=$H63),if(Year($D63)=K$1,$F63*0.8,if((year($D63)+1)=K$1,$F63*0.6,$F63*0.4)) ,""),if($E63="Minors",0,if($E63="FA Contract",if(and(K$1<=$I63,K$1>=$H63),$F63,""),if($E63="YP Contract",if(K$1=$H63,500000,if(K$1=($H63+1),1000000,if(K$1=($H63+2),1500000,"")))))))) -> 5000000 | L63: =if($E63="","",if($E63="Dropped",if(and(L$1<=$I63,L$1>=$H63),if(Year($D63)=L$1,$F63*0.8,if((year($D63)+1)=L$1,$F63*0.6,$F63*0.4)) ,""),if($E63="Minors",0,if($E63="FA Contract",if(and(L$1<=$I63,L$1>=$H63),$F63,""),if($E63="YP Contract",if(L$1=$H63,500000,if(L$1=($H63+1),1000000,if(L$1=($H63+2),1500000,"")))))))) | M63: =if($E63="","",if($E63="Dropped",if(and(M$1<=$I63,M$1>=$H63),if(Year($D63)=M$1,$F63*0.8,if((year($D63)+1)=M$1,$F63*0.6,$F63*0.4)) ,""),if($E63="Minors",0,if($E63="FA Contract",if(and(M$1<=$I63,M$1>=$H63),$F63,""),if($E63="YP Contract",if(M$1=$H63,500000,if(M$1=($H63+1),1000000,if(M$1=($H63+2),1500000,"")))))))) | N63: =if($E63="","",if($E63="Dropped",if(and(N$1<=$I63,N$1>=$H63),if(Year($D63)=N$1,$F63*0.8,if((year($D63)+1)=N$1,$F63*0.6,$F63*0.4)) ,""),if($E63="Minors",0,if($E63="FA Contract",if(and(N$1<=$I63,N$1>=$H63),$F63,""),if($E63="YP Contract",if(N$1=$H63,500000,if(N$1=($H63+1),1000000,if(N$1=($H63+2),1500000,"")))))))) | O63: =if($E63="","",if($E63="Dropped",if(and(O$1<=$I63,O$1>=$H63),if(Year($D63)=O$1,$F63*0.8,if((year($D63)+1)=O$1,$F63*0.6,$F63*0.4)) ,""),if($E63="Minors",0,if($E63="FA Contract",if(and(O$1<=$I63,O$1>=$H63),$F63,""),if($E63="YP Contract",if(O$1=$H63,500000,if(O$1=($H63+1),1000000,if(O$1=($H63+2),1500000,"")))))))) | P63: =if($E63="","",if($E63="Dropped",if(and(P$1<=$I63,P$1>=$H63),if(Year($D63)=P$1,$F63*0.8,if((year($D63)+1)=P$1,$F63*0.6,$F63*0.4)) ,""),if($E63="Minors",0,if($E63="FA Contract",if(and(P$1<=$I63,P$1>=$H63),$F63,""),if($E63="YP Contract",if(P$1=$H63,500000,if(P$1=($H63+1),1000000,if(P$1=($H63+2),1500000,""))))))))
A64: Mitch Keller | B64: Brian Frederick | C64: 45356 | E64: FA Contract | F64: 5000000 | G64: 2 | H64: 2024 | I64: =if(H64="","",if(or($E64="FA Contract",$E64="Dropped"),$H64+$G64-1,if($E64="YP Contract",$H64+2,if(and($E64="Minors",$G64<>"YP"),$H64+$G64-1,if(and($E64="Minors",$G64="YP"),$H64+2,""))))) -> 2025 | J64: 33100000 | K64: =if($E64="","",if($E64="Dropped",if(and(K$1<=$I64,K$1>=$H64),if(Year($D64)=K$1,$F64*0.8,if((year($D64)+1)=K$1,$F64*0.6,$F64*0.4)) ,""),if($E64="Minors",0,if($E64="FA Contract",if(and(K$1<=$I64,K$1>=$H64),$F64,""),if($E64="YP Contract",if(K$1=$H64,500000,if(K$1=($H64+1),1000000,if(K$1=($H64+2),1500000,"")))))))) -> 5000000 | L64: =if($E64="","",if($E64="Dropped",if(and(L$1<=$I64,L$1>=$H64),if(Year($D64)=L$1,$F64*0.8,if((year($D64)+1)=L$1,$F64*0.6,$F64*0.4)) ,""),if($E64="Minors",0,if($E64="FA Contract",if(and(L$1<=$I64,L$1>=$H64),$F64,""),if($E64="YP Contract",if(L$1=$H64,500000,if(L$1=($H64+1),1000000,if(L$1=($H64+2),1500000,"")))))))) | M64: =if($E64="","",if($E64="Dropped",if(and(M$1<=$I64,M$1>=$H64),if(Year($D64)=M$1,$F64*0.8,if((year($D64)+1)=M$1,$F64*0.6,$F64*0.4)) ,""),if($E64="Minors",0,if($E64="FA Contract",if(and(M$1<=$I64,M$1>=$H64),$F64,""),if($E64="YP Contract",if(M$1=$H64,500000,if(M$1=($H64+1),1000000,if(M$1=($H64+2),1500000,"")))))))) | N64: =if($E64="","",if($E64="Dropped",if(and(N$1<=$I64,N$1>=$H64),if(Year($D64)=N$1,$F64*0.8,if((year($D64)+1)=N$1,$F64*0.6,$F64*0.4)) ,""),if($E64="Minors",0,if($E64="FA Contract",if(and(N$1<=$I64,N$1>=$H64),$F64,""),if($E64="YP Contract",if(N$1=$H64,500000,if(N$1=($H64+1),1000000,if(N$1=($H64+2),1500000,"")))))))) | O64: =if($E64="","",if($E64="Dropped",if(and(O$1<=$I64,O$1>=$H64),if(Year($D64)=O$1,$F64*0.8,if((year($D64)+1)=O$1,$F64*0.6,$F64*0.4)) ,""),if($E64="Minors",0,if($E64="FA Contract",if(and(O$1<=$I64,O$1>=$H64),$F64,""),if($E64="YP Contract",if(O$1=$H64,500000,if(O$1=($H64+1),1000000,if(O$1=($H64+2),1500000,"")))))))) | P64: =if($E64="","",if($E64="Dropped",if(and(P$1<=$I64,P$1>=$H64),if(Year($D64)=P$1,$F64*0.8,if((year($D64)+1)=P$1,$F64*0.6,$F64*0.4)) ,""),if($E64="Minors",0,if($E64="FA Contract",if(and(P$1<=$I64,P$1>=$H64),$F64,""),if($E64="YP Contract",if(P$1=$H64,500000,if(P$1=($H64+1),1000000,if(P$1=($H64+2),1500000,""))))))))
A65: William Contreras | B65: Brian Frederick | C65: 45356 | E65: FA Contract | F65: 5000000 | G65: 2 | H65: 2024 | I65: =if(H65="","",if(or($E65="FA Contract",$E65="Dropped"),$H65+$G65-1,if($E65="YP Contract",$H65+2,if(and($E65="Minors",$G65<>"YP"),$H65+$G65-1,if(and($E65="Minors",$G65="YP"),$H65+2,""))))) -> 2025 | J65: 33100000 | K65: =if($E65="","",if($E65="Dropped",if(and(K$1<=$I65,K$1>=$H65),if(Year($D65)=K$1,$F65*0.8,if((year($D65)+1)=K$1,$F65*0.6,$F65*0.4)) ,""),if($E65="Minors",0,if($E65="FA Contract",if(and(K$1<=$I65,K$1>=$H65),$F65,""),if($E65="YP Contract",if(K$1=$H65,500000,if(K$1=($H65+1),1000000,if(K$1=($H65+2),1500000,"")))))))) -> 5000000 | L65: =if($E65="","",if($E65="Dropped",if(and(L$1<=$I65,L$1>=$H65),if(Year($D65)=L$1,$F65*0.8,if((year($D65)+1)=L$1,$F65*0.6,$F65*0.4)) ,""),if($E65="Minors",0,if($E65="FA Contract",if(and(L$1<=$I65,L$1>=$H65),$F65,""),if($E65="YP Contract",if(L$1=$H65,500000,if(L$1=($H65+1),1000000,if(L$1=($H65+2),1500000,"")))))))) | M65: =if($E65="","",if($E65="Dropped",if(and(M$1<=$I65,M$1>=$H65),if(Year($D65)=M$1,$F65*0.8,if((year($D65)+1)=M$1,$F65*0.6,$F65*0.4)) ,""),if($E65="Minors",0,if($E65="FA Contract",if(and(M$1<=$I65,M$1>=$H65),$F65,""),if($E65="YP Contract",if(M$1=$H65,500000,if(M$1=($H65+1),1000000,if(M$1=($H65+2),1500000,"")))))))) | N65: =if($E65="","",if($E65="Dropped",if(and(N$1<=$I65,N$1>=$H65),if(Year($D65)=N$1,$F65*0.8,if((year($D65)+1)=N$1,$F65*0.6,$F65*0.4)) ,""),if($E65="Minors",0,if($E65="FA Contract",if(and(N$1<=$I65,N$1>=$H65),$F65,""),if($E65="YP Contract",if(N$1=$H65,500000,if(N$1=($H65+1),1000000,if(N$1=($H65+2),1500000,"")))))))) | O65: =if($E65="","",if($E65="Dropped",if(and(O$1<=$I65,O$1>=$H65),if(Year($D65)=O$1,$F65*0.8,if((year($D65)+1)=O$1,$F65*0.6,$F65*0.4)) ,""),if($E65="Minors",0,if($E65="FA Contract",if(and(O$1<=$I65,O$1>=$H65),$F65,""),if($E65="YP Contract",if(O$1=$H65,500000,if(O$1=($H65+1),1000000,if(O$1=($H65+2),1500000,"")))))))) | P65: =if($E65="","",if($E65="Dropped",if(and(P$1<=$I65,P$1>=$H65),if(Year($D65)=P$1,$F65*0.8,if((year($D65)+1)=P$1,$F65*0.6,$F65*0.4)) ,""),if($E65="Minors",0,if($E65="FA Contract",if(and(P$1<=$I65,P$1>=$H65),$F65,""),if($E65="YP Contract",if(P$1=$H65,500000,if(P$1=($H65+1),1000000,if(P$1=($H65+2),1500000,""))))))))
A66: J.P. Crawford | B66: Brian Frederick | C66: 45356 | E66: FA Contract | F66: 4000000 | G66: 2 | H66: 2024 | I66: =if(H66="","",if(or($E66="FA Contract",$E66="Dropped"),$H66+$G66-1,if($E66="YP Contract",$H66+2,if(and($E66="Minors",$G66<>"YP"),$H66+$G66-1,if(and($E66="Minors",$G66="YP"),$H66+2,""))))) -> 2025 | J66: 33100000 | K66: =if($E66="","",if($E66="Dropped",if(and(K$1<=$I66,K$1>=$H66),if(Year($D66)=K$1,$F66*0.8,if((year($D66)+1)=K$1,$F66*0.6,$F66*0.4)) ,""),if($E66="Minors",0,if($E66="FA Contract",if(and(K$1<=$I66,K$1>=$H66),$F66,""),if($E66="YP Contract",if(K$1=$H66,500000,if(K$1=($H66+1),1000000,if(K$1=($H66+2),1500000,"")))))))) -> 4000000 | L66: =if($E66="","",if($E66="Dropped",if(and(L$1<=$I66,L$1>=$H66),if(Year($D66)=L$1,$F66*0.8,if((year($D66)+1)=L$1,$F66*0.6,$F66*0.4)) ,""),if($E66="Minors",0,if($E66="FA Contract",if(and(L$1<=$I66,L$1>=$H66),$F66,""),if($E66="YP Contract",if(L$1=$H66,500000,if(L$1=($H66+1),1000000,if(L$1=($H66+2),1500000,"")))))))) | M66: =if($E66="","",if($E66="Dropped",if(and(M$1<=$I66,M$1>=$H66),if(Year($D66)=M$1,$F66*0.8,if((year($D66)+1)=M$1,$F66*0.6,$F66*0.4)) ,""),if($E66="Minors",0,if($E66="FA Contract",if(and(M$1<=$I66,M$1>=$H66),$F66,""),if($E66="YP Contract",if(M$1=$H66,500000,if(M$1=($H66+1),1000000,if(M$1=($H66+2),1500000,"")))))))) | N66: =if($E66="","",if($E66="Dropped",if(and(N$1<=$I66,N$1>=$H66),if(Year($D66)=N$1,$F66*0.8,if((year($D66)+1)=N$1,$F66*0.6,$F66*0.4)) ,""),if($E66="Minors",0,if($E66="FA Contract",if(and(N$1<=$I66,N$1>=$H66),$F66,""),if($E66="YP Contract",if(N$1=$H66,500000,if(N$1=($H66+1),1000000,if(N$1=($H66+2),1500000,"")))))))) | O66: =if($E66="","",if($E66="Dropped",if(and(O$1<=$I66,O$1>=$H66),if(Year($D66)=O$1,$F66*0.8,if((year($D66)+1)=O$1,$F66*0.6,$F66*0.4)) ,""),if($E66="Minors",0,if($E66="FA Contract",if(and(O$1<=$I66,O$1>=$H66),$F66,""),if($E66="YP Contract",if(O$1=$H66,500000,if(O$1=($H66+1),1000000,if(O$1=($H66+2),1500000,"")))))))) | P66: =if($E66="","",if($E66="Dropped",if(and(P$1<=$I66,P$1>=$H66),if(Year($D66)=P$1,$F66*0.8,if((year($D66)+1)=P$1,$F66*0.6,$F66*0.4)) ,""),if($E66="Minors",0,if($E66="FA Contract",if(and(P$1<=$I66,P$1>=$H66),$F66,""),if($E66="YP Contract",if(P$1=$H66,500000,if(P$1=($H66+1),1000000,if(P$1=($H66+2),1500000,""))))))))
... A73: Christian Yelich | B73: Brian Frederick | C73: 45721 | E73: FA Contract | F73: 2800000 | G73: 2 | H73: 2025 | I73: =if(H73="","",if(or($E73="FA Contract",$E73="Dropped"),$H73+$G73-1,if($E73="YP Contract",$H73+2,if(and($E73="Minors",$G73<>"YP"),$H73+$G73-1,if(and($E73="Minors",$G73="YP"),$H73+2,""))))) -> 2026 | J73: 33100000 | K73: =if($E73="","",if($E73="Dropped",if(and(K$1<=$I73,K$1>=$H73),if(Year($D73)=K$1,$F73*0.8,if((year($D73)+1)=K$1,$F73*0.6,$F73*0.4)) ,""),if($E73="Minors",0,if($E73="FA Contract",if(and(K$1<=$I73,K$1>=$H73),$F73,""),if($E73="YP Contract",if(K$1=$H73,500000,if(K$1=($H73+1),1000000,if(K$1=($H73+2),1500000,"")))))))) -> 2800000 | L73: =if($E73="","",if($E73="Dropped",if(and(L$1<=$I73,L$1>=$H73),if(Year($D73)=L$1,$F73*0.8,if((year($D73)+1)=L$1,$F73*0.6,$F73*0.4)) ,""),if($E73="Minors",0,if($E73="FA Contract",if(and(L$1<=$I73,L$1>=$H73),$F73,""),if($E73="YP Contract",if(L$1=$H73,500000,if(L$1=($H73+1),1000000,if(L$1=($H73+2),1500000,"")))))))) -> 2800000 | M73: =if($E73="","",if($E73="Dropped",if(and(M$1<=$I73,M$1>=$H73),if(Year($D73)=M$1,$F73*0.8,if((year($D73)+1)=M$1,$F73*0.6,$F73*0.4)) ,""),if($E73="Minors",0,if($E73="FA Contract",if(and(M$1<=$I73,M$1>=$H73),$F73,""),if($E73="YP Contract",if(M$1=$H73,500000,if(M$1=($H73+1),1000000,if(M$1=($H73+2),1500000,"")))))))) | N73: =if($E73="","",if($E73="Dropped",if(and(N$1<=$I73,N$1>=$H73),if(Year($D73)=N$1,$F73*0.8,if((year($D73)+1)=N$1,$F73*0.6,$F73*0.4)) ,""),if($E73="Minors",0,if($E73="FA Contract",if(and(N$1<=$I73,N$1>=$H73),$F73,""),if($E73="YP Contract",if(N$1=$H73,500000,if(N$1=($H73+1),1000000,if(N$1=($H73+2),1500000,"")))))))) | O73: =if($E73="","",if($E73="Dropped",if(and(O$1<=$I73,O$1>=$H73),if(Year($D73)=O$1,$F73*0.8,if((year($D73)+1)=O$1,$F73*0.6,$F73*0.4)) ,""),if($E73="Minors",0,if($E73="FA Contract",if(and(O$1<=$I73,O$1>=$H73),$F73,""),if($E73="YP Contract",if(O$1=$H73,500000,if(O$1=($H73+1),1000000,if(O$1=($H73+2),1500000,"")))))))) | P73: =if($E73="","",if($E73="Dropped",if(and(P$1<=$I73,P$1>=$H73),if(Year($D73)=P$1,$F73*0.8,if((year($D73)+1)=P$1,$F73*0.6,$F73*0.4)) ,""),if($E73="Minors",0,if($E73="FA Contract",if(and(P$1<=$I73,P$1>=$H73),$F73,""),if($E73="YP Contract",if(P$1=$H73,500000,if(P$1=($H73+1),1000000,if(P$1=($H73+2),1500000,""))))))))
A74: Brett Baty | B74: Brian Frederick | C74: 45343 | E74: YP Contract | F74: YP | G74: YP | H74: 2023 | I74: =if(H74="","",if(or($E74="FA Contract",$E74="Dropped"),$H74+$G74-1,if($E74="YP Contract",$H74+2,if(and($E74="Minors",$G74<>"YP"),$H74+$G74-1,if(and($E74="Minors",$G74="YP"),$H74+2,""))))) -> 2025 | J74: 33100000 | K74: =if($E74="","",if($E74="Dropped",if(and(K$1<=$I74,K$1>=$H74),if(Year($D74)=K$1,$F74*0.8,if((year($D74)+1)=K$1,$F74*0.6,$F74*0.4)) ,""),if($E74="Minors",0,if($E74="FA Contract",if(and(K$1<=$I74,K$1>=$H74),$F74,""),if($E74="YP Contract",if(K$1=$H74,500000,if(K$1=($H74+1),1000000,if(K$1=($H74+2),1500000,"")))))))) -> 1500000 | L74: =if($E74="","",if($E74="Dropped",if(and(L$1<=$I74,L$1>=$H74),if(Year($D74)=L$1,$F74*0.8,if((year($D74)+1)=L$1,$F74*0.6,$F74*0.4)) ,""),if($E74="Minors",0,if($E74="FA Contract",if(and(L$1<=$I74,L$1>=$H74),$F74,""),if($E74="YP Contract",if(L$1=$H74,500000,if(L$1=($H74+1),1000000,if(L$1=($H74+2),1500000,"")))))))) | M74: =if($E74="","",if($E74="Dropped",if(and(M$1<=$I74,M$1>=$H74),if(Year($D74)=M$1,$F74*0.8,if((year($D74)+1)=M$1,$F74*0.6,$F74*0.4)) ,""),if($E74="Minors",0,if($E74="FA Contract",if(and(M$1<=$I74,M$1>=$H74),$F74,""),if($E74="YP Contract",if(M$1=$H74,500000,if(M$1=($H74+1),1000000,if(M$1=($H74+2),1500000,"")))))))) | N74: =if($E74="","",if($E74="Dropped",if(and(N$1<=$I74,N$1>=$H74),if(Year($D74)=N$1,$F74*0.8,if((year($D74)+1)=N$1,$F74*0.6,$F74*0.4)) ,""),if($E74="Minors",0,if($E74="FA Contract",if(and(N$1<=$I74,N$1>=$H74),$F74,""),if($E74="YP Contract",if(N$1=$H74,500000,if(N$1=($H74+1),1000000,if(N$1=($H74+2),1500000,"")))))))) | O74: =if($E74="","",if($E74="Dropped",if(and(O$1<=$I74,O$1>=$H74),if(Year($D74)=O$1,$F74*0.8,if((year($D74)+1)=O$1,$F74*0.6,$F74*0.4)) ,""),if($E74="Minors",0,if($E74="FA Contract",if(and(O$1<=$I74,O$1>=$H74),$F74,""),if($E74="YP Contract",if(O$1=$H74,500000,if(O$1=($H74+1),1000000,if(O$1=($H74+2),1500000,"")))))))) | P74: =if($E74="","",if($E74="Dropped",if(and(P$1<=$I74,P$1>=$H74),if(Year($D74)=P$1,$F74*0.8,if((year($D74)+1)=P$1,$F74*0.6,$F74*0.4)) ,""),if($E74="Minors",0,if($E74="FA Contract",if(and(P$1<=$I74,P$1>=$H74),$F74,""),if($E74="YP Contract",if(P$1=$H74,500000,if(P$1=($H74+1),1000000,if(P$1=($H74+2),1500000,""))))))))
A75: Logan Allen | B75: Brian Frederick | C75: 45343 | E75: YP Contract | F75: YP | G75: YP | H75: 2023 | I75: =if(H75="","",if(or($E75="FA Contract",$E75="Dropped"),$H75+$G75-1,if($E75="YP Contract",$H75+2,if(and($E75="Minors",$G75<>"YP"),$H75+$G75-1,if(and($E75="Minors",$G75="YP"),$H75+2,""))))) -> 2025 | J75: 33100000 | K75: =if($E75="","",if($E75="Dropped",if(and(K$1<=$I75,K$1>=$H75),if(Year($D75)=K$1,$F75*0.8,if((year($D75)+1)=K$1,$F75*0.6,$F75*0.4)) ,""),if($E75="Minors",0,if($E75="FA Contract",if(and(K$1<=$I75,K$1>=$H75),$F75,""),if($E75="YP Contract",if(K$1=$H75,500000,if(K$1=($H75+1),1000000,if(K$1=($H75+2),1500000,"")))))))) -> 1500000 | L75: =if($E75="","",if($E75="Dropped",if(and(L$1<=$I75,L$1>=$H75),if(Year($D75)=L$1,$F75*0.8,if((year($D75)+1)=L$1,$F75*0.6,$F75*0.4)) ,""),if($E75="Minors",0,if($E75="FA Contract",if(and(L$1<=$I75,L$1>=$H75),$F75,""),if($E75="YP Contract",if(L$1=$H75,500000,if(L$1=($H75+1),1000000,if(L$1=($H75+2),1500000,"")))))))) | M75: =if($E75="","",if($E75="Dropped",if(and(M$1<=$I75,M$1>=$H75),if(Year($D75)=M$1,$F75*0.8,if((year($D75)+1)=M$1,$F75*0.6,$F75*0.4)) ,""),if($E75="Minors",0,if($E75="FA Contract",if(and(M$1<=$I75,M$1>=$H75),$F75,""),if($E75="YP Contract",if(M$1=$H75,500000,if(M$1=($H75+1),1000000,if(M$1=($H75+2),1500000,"")))))))) | N75: =if($E75="","",if($E75="Dropped",if(and(N$1<=$I75,N$1>=$H75),if(Year($D75)=N$1,$F75*0.8,if((year($D75)+1)=N$1,$F75*0.6,$F75*0.4)) ,""),if($E75="Minors",0,if($E75="FA Contract",if(and(N$1<=$I75,N$1>=$H75),$F75,""),if($E75="YP Contract",if(N$1=$H75,500000,if(N$1=($H75+1),1000000,if(N$1=($H75+2),1500000,"")))))))) | O75: =if($E75="","",if($E75="Dropped",if(and(O$1<=$I75,O$1>=$H75),if(Year($D75)=O$1,$F75*0.8,if((year($D75)+1)=O$1,$F75*0.6,$F75*0.4)) ,""),if($E75="Minors",0,if($E75="FA Contract",if(and(O$1<=$I75,O$1>=$H75),$F75,""),if($E75="YP Contract",if(O$1=$H75,500000,if(O$1=($H75+1),1000000,if(O$1=($H75+2),1500000,"")))))))) | P75: =if($E75="","",if($E75="Dropped",if(and(P$1<=$I75,P$1>=$H75),if(Year($D75)=P$1,$F75*0.8,if((year($D75)+1)=P$1,$F75*0.6,$F75*0.4)) ,""),if($E75="Minors",0,if($E75="FA Contract",if(and(P$1<=$I75,P$1>=$H75),$F75,""),if($E75="YP Contract",if(P$1=$H75,500000,if(P$1=($H75+1),1000000,if(P$1=($H75+2),1500000,""))))))))
A76: Mark Vientos | B76: Brian Frederick | C76: 45343 | E76: YP Contract | F76: YP | G76: YP | H76: 2023 | I76: =if(H76="","",if(or($E76="FA Contract",$E76="Dropped"),$H76+$G76-1,if($E76="YP Contract",$H76+2,if(and($E76="Minors",$G76<>"YP"),$H76+$G76-1,if(and($E76="Minors",$G76="YP"),$H76+2,""))))) -> 2025 | J76: 33100000 | K76: =if($E76="","",if($E76="Dropped",if(and(K$1<=$I76,K$1>=$H76),if(Year($D76)=K$1,$F76*0.8,if((year($D76)+1)=K$1,$F76*0.6,$F76*0.4)) ,""),if($E76="Minors",0,if($E76="FA Contract",if(and(K$1<=$I76,K$1>=$H76),$F76,""),if($E76="YP Contract",if(K$1=$H76,500000,if(K$1=($H76+1),1000000,if(K$1=($H76+2),1500000,"")))))))) -> 1500000 | L76: =if($E76="","",if($E76="Dropped",if(and(L$1<=$I76,L$1>=$H76),if(Year($D76)=L$1,$F76*0.8,if((year($D76)+1)=L$1,$F76*0.6,$F76*0.4)) ,""),if($E76="Minors",0,if($E76="FA Contract",if(and(L$1<=$I76,L$1>=$H76),$F76,""),if($E76="YP Contract",if(L$1=$H76,500000,if(L$1=($H76+1),1000000,if(L$1=($H76+2),1500000,"")))))))) | M76: =if($E76="","",if($E76="Dropped",if(and(M$1<=$I76,M$1>=$H76),if(Year($D76)=M$1,$F76*0.8,if((year($D76)+1)=M$1,$F76*0.6,$F76*0.4)) ,""),if($E76="Minors",0,if($E76="FA Contract",if(and(M$1<=$I76,M$1>=$H76),$F76,""),if($E76="YP Contract",if(M$1=$H76,500000,if(M$1=($H76+1),1000000,if(M$1=($H76+2),1500000,"")))))))) | N76: =if($E76="","",if($E76="Dropped",if(and(N$1<=$I76,N$1>=$H76),if(Year($D76)=N$1,$F76*0.8,if((year($D76)+1)=N$1,$F76*0.6,$F76*0.4)) ,""),if($E76="Minors",0,if($E76="FA Contract",if(and(N$1<=$I76,N$1>=$H76),$F76,""),if($E76="YP Contract",if(N$1=$H76,500000,if(N$1=($H76+1),1000000,if(N$1=($H76+2),1500000,"")))))))) | O76: =if($E76="","",if($E76="Dropped",if(and(O$1<=$I76,O$1>=$H76),if(Year($D76)=O$1,$F76*0.8,if((year($D76)+1)=O$1,$F76*0.6,$F76*0.4)) ,""),if($E76="Minors",0,if($E76="FA Contract",if(and(O$1<=$I76,O$1>=$H76),$F76,""),if($E76="YP Contract",if(O$1=$H76,500000,if(O$1=($H76+1),1000000,if(O$1=($H76+2),1500000,"")))))))) | P76: =if($E76="","",if($E76="Dropped",if(and(P$1<=$I76,P$1>=$H76),if(Year($D76)=P$1,$F76*0.8,if((year($D76)+1)=P$1,$F76*0.6,$F76*0.4)) ,""),if($E76="Minors",0,if($E76="FA Contract",if(and(P$1<=$I76,P$1>=$H76),$F76,""),if($E76="YP Contract",if(P$1=$H76,500000,if(P$1=($H76+1),1000000,if(P$1=($H76+2),1500000,""))))))))
A77: Ryan Walker | B77: Brian Frederick | C77: 45343 | E77: YP Contract | F77: YP | G77: YP | H77: 2023 | I77: =if(H77="","",if(or($E77="FA Contract",$E77="Dropped"),$H77+$G77-1,if($E77="YP Contract",$H77+2,if(and($E77="Minors",$G77<>"YP"),$H77+$G77-1,if(and($E77="Minors",$G77="YP"),$H77+2,""))))) -> 2025 | J77: 33100000 | K77: =if($E77="","",if($E77="Dropped",if(and(K$1<=$I77,K$1>=$H77),if(Year($D77)=K$1,$F77*0.8,if((year($D77)+1)=K$1,$F77*0.6,$F77*0.4)) ,""),if($E77="Minors",0,if($E77="FA Contract",if(and(K$1<=$I77,K$1>=$H77),$F77,""),if($E77="YP Contract",if(K$1=$H77,500000,if(K$1=($H77+1),1000000,if(K$1=($H77+2),1500000,"")))))))) -> 1500000 | L77: =if($E77="","",if($E77="Dropped",if(and(L$1<=$I77,L$1>=$H77),if(Year($D77)=L$1,$F77*0.8,if((year($D77)+1)=L$1,$F77*0.6,$F77*0.4)) ,""),if($E77="Minors",0,if($E77="FA Contract",if(and(L$1<=$I77,L$1>=$H77),$F77,""),if($E77="YP Contract",if(L$1=$H77,500000,if(L$1=($H77+1),1000000,if(L$1=($H77+2),1500000,"")))))))) | M77: =if($E77="","",if($E77="Dropped",if(and(M$1<=$I77,M$1>=$H77),if(Year($D77)=M$1,$F77*0.8,if((year($D77)+1)=M$1,$F77*0.6,$F77*0.4)) ,""),if($E77="Minors",0,if($E77="FA Contract",if(and(M$1<=$I77,M$1>=$H77),$F77,""),if($E77="YP Contract",if(M$1=$H77,500000,if(M$1=($H77+1),1000000,if(M$1=($H77+2),1500000,"")))))))) | N77: =if($E77="","",if($E77="Dropped",if(and(N$1<=$I77,N$1>=$H77),if(Year($D77)=N$1,$F77*0.8,if((year($D77)+1)=N$1,$F77*0.6,$F77*0.4)) ,""),if($E77="Minors",0,if($E77="FA Contract",if(and(N$1<=$I77,N$1>=$H77),$F77,""),if($E77="YP Contract",if(N$1=$H77,500000,if(N$1=($H77+1),1000000,if(N$1=($H77+2),1500000,"")))))))) | O77: =if($E77="","",if($E77="Dropped",if(and(O$1<=$I77,O$1>=$H77),if(Year($D77)=O$1,$F77*0.8,if((year($D77)+1)=O$1,$F77*0.6,$F77*0.4)) ,""),if($E77="Minors",0,if($E77="FA Contract",if(and(O$1<=$I77,O$1>=$H77),$F77,""),if($E77="YP Contract",if(O$1=$H77,500000,if(O$1=($H77+1),1000000,if(O$1=($H77+2),1500000,"")))))))) | P77: =if($E77="","",if($E77="Dropped",if(and(P$1<=$I77,P$1>=$H77),if(Year($D77)=P$1,$F77*0.8,if((year($D77)+1)=P$1,$F77*0.6,$F77*0.4)) ,""),if($E77="Minors",0,if($E77="FA Contract",if(and(P$1<=$I77,P$1>=$H77),$F77,""),if($E77="YP Contract",if(P$1=$H77,500000,if(P$1=($H77+1),1000000,if(P$1=($H77+2),1500000,""))))))))
A78: Tyler Holton | B78: Brian Frederick | C78: 45343 | E78: YP Contract | F78: YP | G78: YP | H78: 2023 | I78: =if(H78="","",if(or($E78="FA Contract",$E78="Dropped"),$H78+$G78-1,if($E78="YP Contract",$H78+2,if(and($E78="Minors",$G78<>"YP"),$H78+$G78-1,if(and($E78="Minors",$G78="YP"),$H78+2,""))))) -> 2025 | J78: 33100000 | K78: =if($E78="","",if($E78="Dropped",if(and(K$1<=$I78,K$1>=$H78),if(Year($D78)=K$1,$F78*0.8,if((year($D78)+1)=K$1,$F78*0.6,$F78*0.4)) ,""),if($E78="Minors",0,if($E78="FA Contract",if(and(K$1<=$I78,K$1>=$H78),$F78,""),if($E78="YP Contract",if(K$1=$H78,500000,if(K$1=($H78+1),1000000,if(K$1=($H78+2),1500000,"")))))))) -> 1500000 | L78: =if($E78="","",if($E78="Dropped",if(and(L$1<=$I78,L$1>=$H78),if(Year($D78)=L$1,$F78*0.8,if((year($D78)+1)=L$1,$F78*0.6,$F78*0.4)) ,""),if($E78="Minors",0,if($E78="FA Contract",if(and(L$1<=$I78,L$1>=$H78),$F78,""),if($E78="YP Contract",if(L$1=$H78,500000,if(L$1=($H78+1),1000000,if(L$1=($H78+2),1500000,"")))))))) | M78: =if($E78="","",if($E78="Dropped",if(and(M$1<=$I78,M$1>=$H78),if(Year($D78)=M$1,$F78*0.8,if((year($D78)+1)=M$1,$F78*0.6,$F78*0.4)) ,""),if($E78="Minors",0,if($E78="FA Contract",if(and(M$1<=$I78,M$1>=$H78),$F78,""),if($E78="YP Contract",if(M$1=$H78,500000,if(M$1=($H78+1),1000000,if(M$1=($H78+2),1500000,"")))))))) | N78: =if($E78="","",if($E78="Dropped",if(and(N$1<=$I78,N$1>=$H78),if(Year($D78)=N$1,$F78*0.8,if((year($D78)+1)=N$1,$F78*0.6,$F78*0.4)) ,""),if($E78="Minors",0,if($E78="FA Contract",if(and(N$1<=$I78,N$1>=$H78),$F78,""),if($E78="YP Contract",if(N$1=$H78,500000,if(N$1=($H78+1),1000000,if(N$1=($H78+2),1500000,"")))))))) | O78: =if($E78="","",if($E78="Dropped",if(and(O$1<=$I78,O$1>=$H78),if(Year($D78)=O$1,$F78*0.8,if((year($D78)+1)=O$1,$F78*0.6,$F78*0.4)) ,""),if($E78="Minors",0,if($E78="FA Contract",if(and(O$1<=$I78,O$1>=$H78),$F78,""),if($E78="YP Contract",if(O$1=$H78,500000,if(O$1=($H78+1),1000000,if(O$1=($H78+2),1500000,"")))))))) | P78: =if($E78="","",if($E78="Dropped",if(and(P$1<=$I78,P$1>=$H78),if(Year($D78)=P$1,$F78*0.8,if((year($D78)+1)=P$1,$F78*0.6,$F78*0.4)) ,""),if($E78="Minors",0,if($E78="FA Contract",if(and(P$1<=$I78,P$1>=$H78),$F78,""),if($E78="YP Contract",if(P$1=$H78,500000,if(P$1=($H78+1),1000000,if(P$1=($H78+2),1500000,""))))))))
A79: Nathan Eovaldi | B79: Brian Frederick | C79: 45721 | E79: FA Contract | F79: 1100000 | G79: 1 | H79: 2025 | I79: =if(H79="","",if(or($E79="FA Contract",$E79="Dropped"),$H79+$G79-1,if($E79="YP Contract",$H79+2,if(and($E79="Minors",$G79<>"YP"),$H79+$G79-1,if(and($E79="Minors",$G79="YP"),$H79+2,""))))) -> 2025 | J79: 33100000 | K79: =if($E79="","",if($E79="Dropped",if(and(K$1<=$I79,K$1>=$H79),if(Year($D79)=K$1,$F79*0.8,if((year($D79)+1)=K$1,$F79*0.6,$F79*0.4)) ,""),if($E79="Minors",0,if($E79="FA Contract",if(and(K$1<=$I79,K$1>=$H79),$F79,""),if($E79="YP Contract",if(K$1=$H79,500000,if(K$1=($H79+1),1000000,if(K$1=($H79+2),1500000,"")))))))) -> 1100000 | L79: =if($E79="","",if($E79="Dropped",if(and(L$1<=$I79,L$1>=$H79),if(Year($D79)=L$1,$F79*0.8,if((year($D79)+1)=L$1,$F79*0.6,$F79*0.4)) ,""),if($E79="Minors",0,if($E79="FA Contract",if(and(L$1<=$I79,L$1>=$H79),$F79,""),if($E79="YP Contract",if(L$1=$H79,500000,if(L$1=($H79+1),1000000,if(L$1=($H79+2),1500000,"")))))))) | M79: =if($E79="","",if($E79="Dropped",if(and(M$1<=$I79,M$1>=$H79),if(Year($D79)=M$1,$F79*0.8,if((year($D79)+1)=M$1,$F79*0.6,$F79*0.4)) ,""),if($E79="Minors",0,if($E79="FA Contract",if(and(M$1<=$I79,M$1>=$H79),$F79,""),if($E79="YP Contract",if(M$1=$H79,500000,if(M$1=($H79+1),1000000,if(M$1=($H79+2),1500000,"")))))))) | N79: =if($E79="","",if($E79="Dropped",if(and(N$1<=$I79,N$1>=$H79),if(Year($D79)=N$1,$F79*0.8,if((year($D79)+1)=N$1,$F79*0.6,$F79*0.4)) ,""),if($E79="Minors",0,if($E79="FA Contract",if(and(N$1<=$I79,N$1>=$H79),$F79,""),if($E79="YP Contract",if(N$1=$H79,500000,if(N$1=($H79+1),1000000,if(N$1=($H79+2),1500000,"")))))))) | O79: =if($E79="","",if($E79="Dropped",if(and(O$1<=$I79,O$1>=$H79),if(Year($D79)=O$1,$F79*0.8,if((year($D79)+1)=O$1,$F79*0.6,$F79*0.4)) ,""),if($E79="Minors",0,if($E79="FA Contract",if(and(O$1<=$I79,O$1>=$H79),$F79,""),if($E79="YP Contract",if(O$1=$H79,500000,if(O$1=($H79+1),1000000,if(O$1=($H79+2),1500000,"")))))))) | P79: =if($E79="","",if($E79="Dropped",if(and(P$1<=$I79,P$1>=$H79),if(Year($D79)=P$1,$F79*0.8,if((year($D79)+1)=P$1,$F79*0.6,$F79*0.4)) ,""),if($E79="Minors",0,if($E79="FA Contract",if(and(P$1<=$I79,P$1>=$H79),$F79,""),if($E79="YP Contract",if(P$1=$H79,500000,if(P$1=($H79+1),1000000,if(P$1=($H79+2),1500000,""))))))))
A80: Chris Martin | B80: Brian Frederick | C80: 45823 | E80: FA Contract | F80: 1000000 | G80: 1 | H80: 2025 | I80: =if(H80="","",if(or($E80="FA Contract",$E80="Dropped"),$H80+$G80-1,if($E80="YP Contract",$H80+2,if(and($E80="Minors",$G80<>"YP"),$H80+$G80-1,if(and($E80="Minors",$G80="YP"),$H80+2,""))))) -> 2025 | J80: 33100000 | K80: =if($E80="","",if($E80="Dropped",if(and(K$1<=$I80,K$1>=$H80),if(Year($D80)=K$1,$F80*0.8,if((year($D80)+1)=K$1,$F80*0.6,$F80*0.4)) ,""),if($E80="Minors",0,if($E80="FA Contract",if(and(K$1<=$I80,K$1>=$H80),$F80,""),if($E80="YP Contract",if(K$1=$H80,500000,if(K$1=($H80+1),1000000,if(K$1=($H80+2),1500000,"")))))))) -> 1000000 | L80: =if($E80="","",if($E80="Dropped",if(and(L$1<=$I80,L$1>=$H80),if(Year($D80)=L$1,$F80*0.8,if((year($D80)+1)=L$1,$F80*0.6,$F80*0.4)) ,""),if($E80="Minors",0,if($E80="FA Contract",if(and(L$1<=$I80,L$1>=$H80),$F80,""),if($E80="YP Contract",if(L$1=$H80,500000,if(L$1=($H80+1),1000000,if(L$1=($H80+2),1500000,"")))))))) | M80: =if($E80="","",if($E80="Dropped",if(and(M$1<=$I80,M$1>=$H80),if(Year($D80)=M$1,$F80*0.8,if((year($D80)+1)=M$1,$F80*0.6,$F80*0.4)) ,""),if($E80="Minors",0,if($E80="FA Contract",if(and(M$1<=$I80,M$1>=$H80),$F80,""),if($E80="YP Contract",if(M$1=$H80,500000,if(M$1=($H80+1),1000000,if(M$1=($H80+2),1500000,"")))))))) | N80: =if($E80="","",if($E80="Dropped",if(and(N$1<=$I80,N$1>=$H80),if(Year($D80)=N$1,$F80*0.8,if((year($D80)+1)=N$1,$F80*0.6,$F80*0.4)) ,""),if($E80="Minors",0,if($E80="FA Contract",if(and(N$1<=$I80,N$1>=$H80),$F80,""),if($E80="YP Contract",if(N$1=$H80,500000,if(N$1=($H80+1),1000000,if(N$1=($H80+2),1500000,"")))))))) | O80: =if($E80="","",if($E80="Dropped",if(and(O$1<=$I80,O$1>=$H80),if(Year($D80)=O$1,$F80*0.8,if((year($D80)+1)=O$1,$F80*0.6,$F80*0.4)) ,""),if($E80="Minors",0,if($E80="FA Contract",if(and(O$1<=$I80,O$1>=$H80),$F80,""),if($E80="YP Contract",if(O$1=$H80,500000,if(O$1=($H80+1),1000000,if(O$1=($H80+2),1500000,"")))))))) | P80: =if($E80="","",if($E80="Dropped",if(and(P$1<=$I80,P$1>=$H80),if(Year($D80)=P$1,$F80*0.8,if((year($D80)+1)=P$1,$F80*0.6,$F80*0.4)) ,""),if($E80="Minors",0,if($E80="FA Contract",if(and(P$1<=$I80,P$1>=$H80),$F80,""),if($E80="YP Contract",if(P$1=$H80,500000,if(P$1=($H80+1),1000000,if(P$1=($H80+2),1500000,""))))))))
A81: Colt Keith | B81: Brian Frederick | C81: 45343 | E81: YP Contract | F81: YP | G81: YP | H81: 2024 | I81: =if(H81="","",if(or($E81="FA Contract",$E81="Dropped"),$H81+$G81-1,if($E81="YP Contract",$H81+2,if(and($E81="Minors",$G81<>"YP"),$H81+$G81-1,if(and($E81="Minors",$G81="YP"),$H81+2,""))))) -> 2026 | J81: 33100000 | K81: =if($E81="","",if($E81="Dropped",if(and(K$1<=$I81,K$1>=$H81),if(Year($D81)=K$1,$F81*0.8,if((year($D81)+1)=K$1,$F81*0.6,$F81*0.4)) ,""),if($E81="Minors",0,if($E81="FA Contract",if(and(K$1<=$I81,K$1>=$H81),$F81,""),if($E81="YP Contract",if(K$1=$H81,500000,if(K$1=($H81+1),1000000,if(K$1=($H81+2),1500000,"")))))))) -> 1000000 | L81: =if($E81="","",if($E81="Dropped",if(and(L$1<=$I81,L$1>=$H81),if(Year($D81)=L$1,$F81*0.8,if((year($D81)+1)=L$1,$F81*0.6,$F81*0.4)) ,""),if($E81="Minors",0,if($E81="FA Contract",if(and(L$1<=$I81,L$1>=$H81),$F81,""),if($E81="YP Contract",if(L$1=$H81,500000,if(L$1=($H81+1),1000000,if(L$1=($H81+2),1500000,"")))))))) -> 1500000 | M81: =if($E81="","",if($E81="Dropped",if(and(M$1<=$I81,M$1>=$H81),if(Year($D81)=M$1,$F81*0.8,if((year($D81)+1)=M$1,$F81*0.6,$F81*0.4)) ,""),if($E81="Minors",0,if($E81="FA Contract",if(and(M$1<=$I81,M$1>=$H81),$F81,""),if($E81="YP Contract",if(M$1=$H81,500000,if(M$1=($H81+1),1000000,if(M$1=($H81+2),1500000,"")))))))) | N81: =if($E81="","",if($E81="Dropped",if(and(N$1<=$I81,N$1>=$H81),if(Year($D81)=N$1,$F81*0.8,if((year($D81)+1)=N$1,$F81*0.6,$F81*0.4)) ,""),if($E81="Minors",0,if($E81="FA Contract",if(and(N$1<=$I81,N$1>=$H81),$F81,""),if($E81="YP Contract",if(N$1=$H81,500000,if(N$1=($H81+1),1000000,if(N$1=($H81+2),1500000,"")))))))) | O81: =if($E81="","",if($E81="Dropped",if(and(O$1<=$I81,O$1>=$H81),if(Year($D81)=O$1,$F81*0.8,if((year($D81)+1)=O$1,$F81*0.6,$F81*0.4)) ,""),if($E81="Minors",0,if($E81="FA Contract",if(and(O$1<=$I81,O$1>=$H81),$F81,""),if($E81="YP Contract",if(O$1=$H81,500000,if(O$1=($H81+1),1000000,if(O$1=($H81+2),1500000,"")))))))) | P81: =if($E81="","",if($E81="Dropped",if(and(P$1<=$I81,P$1>=$H81),if(Year($D81)=P$1,$F81*0.8,if((year($D81)+1)=P$1,$F81*0.6,$F81*0.4)) ,""),if($E81="Minors",0,if($E81="FA Contract",if(and(P$1<=$I81,P$1>=$H81),$F81,""),if($E81="YP Contract",if(P$1=$H81,500000,if(P$1=($H81+1),1000000,if(P$1=($H81+2),1500000,""))))))))
A82: Colton Cowser | B82: Brian Frederick | C82: 45343 | E82: YP Contract | F82: YP | G82: YP | H82: 2024 | I82: =if(H82="","",if(or($E82="FA Contract",$E82="Dropped"),$H82+$G82-1,if($E82="YP Contract",$H82+2,if(and($E82="Minors",$G82<>"YP"),$H82+$G82-1,if(and($E82="Minors",$G82="YP"),$H82+2,""))))) -> 2026 | J82: 33100000 | K82: =if($E82="","",if($E82="Dropped",if(and(K$1<=$I82,K$1>=$H82),if(Year($D82)=K$1,$F82*0.8,if((year($D82)+1)=K$1,$F82*0.6,$F82*0.4)) ,""),if($E82="Minors",0,if($E82="FA Contract",if(and(K$1<=$I82,K$1>=$H82),$F82,""),if($E82="YP Contract",if(K$1=$H82,500000,if(K$1=($H82+1),1000000,if(K$1=($H82+2),1500000,"")))))))) -> 1000000 | L82: =if($E82="","",if($E82="Dropped",if(and(L$1<=$I82,L$1>=$H82),if(Year($D82)=L$1,$F82*0.8,if((year($D82)+1)=L$1,$F82*0.6,$F82*0.4)) ,""),if($E82="Minors",0,if($E82="FA Contract",if(and(L$1<=$I82,L$1>=$H82),$F82,""),if($E82="YP Contract",if(L$1=$H82,500000,if(L$1=($H82+1),1000000,if(L$1=($H82+2),1500000,"")))))))) -> 1500000 | M82: =if($E82="","",if($E82="Dropped",if(and(M$1<=$I82,M$1>=$H82),if(Year($D82)=M$1,$F82*0.8,if((year($D82)+1)=M$1,$F82*0.6,$F82*0.4)) ,""),if($E82="Minors",0,if($E82="FA Contract",if(and(M$1<=$I82,M$1>=$H82),$F82,""),if($E82="YP Contract",if(M$1=$H82,500000,if(M$1=($H82+1),1000000,if(M$1=($H82+2),1500000,"")))))))) | N82: =if($E82="","",if($E82="Dropped",if(and(N$1<=$I82,N$1>=$H82),if(Year($D82)=N$1,$F82*0.8,if((year($D82)+1)=N$1,$F82*0.6,$F82*0.4)) ,""),if($E82="Minors",0,if($E82="FA Contract",if(and(N$1<=$I82,N$1>=$H82),$F82,""),if($E82="YP Contract",if(N$1=$H82,500000,if(N$1=($H82+1),1000000,if(N$1=($H82+2),1500000,"")))))))) | O82: =if($E82="","",if($E82="Dropped",if(and(O$1<=$I82,O$1>=$H82),if(Year($D82)=O$1,$F82*0.8,if((year($D82)+1)=O$1,$F82*0.6,$F82*0.4)) ,""),if($E82="Minors",0,if($E82="FA Contract",if(and(O$1<=$I82,O$1>=$H82),$F82,""),if($E82="YP Contract",if(O$1=$H82,500000,if(O$1=($H82+1),1000000,if(O$1=($H82+2),1500000,"")))))))) | P82: =if($E82="","",if($E82="Dropped",if(and(P$1<=$I82,P$1>=$H82),if(Year($D82)=P$1,$F82*0.8,if((year($D82)+1)=P$1,$F82*0.6,$F82*0.4)) ,""),if($E82="Minors",0,if($E82="FA Contract",if(and(P$1<=$I82,P$1>=$H82),$F82,""),if($E82="YP Contract",if(P$1=$H82,500000,if(P$1=($H82+1),1000000,if(P$1=($H82+2),1500000,""))))))))
A83: D.L. Hall | B83: Brian Frederick | C83: 45343 | E83: YP Contract | F83: YP | G83: YP | H83: 2024 | I83: =if(H83="","",if(or($E83="FA Contract",$E83="Dropped"),$H83+$G83-1,if($E83="YP Contract",$H83+2,if(and($E83="Minors",$G83<>"YP"),$H83+$G83-1,if(and($E83="Minors",$G83="YP"),$H83+2,""))))) -> 2026 | J83: 33100000 | K83: =if($E83="","",if($E83="Dropped",if(and(K$1<=$I83,K$1>=$H83),if(Year($D83)=K$1,$F83*0.8,if((year($D83)+1)=K$1,$F83*0.6,$F83*0.4)) ,""),if($E83="Minors",0,if($E83="FA Contract",if(and(K$1<=$I83,K$1>=$H83),$F83,""),if($E83="YP Contract",if(K$1=$H83,500000,if(K$1=($H83+1),1000000,if(K$1=($H83+2),1500000,"")))))))) -> 1000000 | L83: =if($E83="","",if($E83="Dropped",if(and(L$1<=$I83,L$1>=$H83),if(Year($D83)=L$1,$F83*0.8,if((year($D83)+1)=L$1,$F83*0.6,$F83*0.4)) ,""),if($E83="Minors",0,if($E83="FA Contract",if(and(L$1<=$I83,L$1>=$H83),$F83,""),if($E83="YP Contract",if(L$1=$H83,500000,if(L$1=($H83+1),1000000,if(L$1=($H83+2),1500000,"")))))))) -> 1500000 | M83: =if($E83="","",if($E83="Dropped",if(and(M$1<=$I83,M$1>=$H83),if(Year($D83)=M$1,$F83*0.8,if((year($D83)+1)=M$1,$F83*0.6,$F83*0.4)) ,""),if($E83="Minors",0,if($E83="FA Contract",if(and(M$1<=$I83,M$1>=$H83),$F83,""),if($E83="YP Contract",if(M$1=$H83,500000,if(M$1=($H83+1),1000000,if(M$1=($H83+2),1500000,"")))))))) | N83: =if($E83="","",if($E83="Dropped",if(and(N$1<=$I83,N$1>=$H83),if(Year($D83)=N$1,$F83*0.8,if((year($D83)+1)=N$1,$F83*0.6,$F83*0.4)) ,""),if($E83="Minors",0,if($E83="FA Contract",if(and(N$1<=$I83,N$1>=$H83),$F83,""),if($E83="YP Contract",if(N$1=$H83,500000,if(N$1=($H83+1),1000000,if(N$1=($H83+2),1500000,"")))))))) | O83: =if($E83="","",if($E83="Dropped",if(and(O$1<=$I83,O$1>=$H83),if(Year($D83)=O$1,$F83*0.8,if((year($D83)+1)=O$1,$F83*0.6,$F83*0.4)) ,""),if($E83="Minors",0,if($E83="FA Contract",if(and(O$1<=$I83,O$1>=$H83),$F83,""),if($E83="YP Contract",if(O$1=$H83,500000,if(O$1=($H83+1),1000000,if(O$1=($H83+2),1500000,"")))))))) | P83: =if($E83="","",if($E83="Dropped",if(and(P$1<=$I83,P$1>=$H83),if(Year($D83)=P$1,$F83*0.8,if((year($D83)+1)=P$1,$F83*0.6,$F83*0.4)) ,""),if($E83="Minors",0,if($E83="FA Contract",if(and(P$1<=$I83,P$1>=$H83),$F83,""),if($E83="YP Contract",if(P$1=$H83,500000,if(P$1=($H83+1),1000000,if(P$1=($H83+2),1500000,""))))))))
A84: Joey Ortiz | B84: Brian Frederick | C84: 45343 | E84: YP Contract | F84: YP | G84: YP | H84: 2024 | I84: =if(H84="","",if(or($E84="FA Contract",$E84="Dropped"),$H84+$G84-1,if($E84="YP Contract",$H84+2,if(and($E84="Minors",$G84<>"YP"),$H84+$G84-1,if(and($E84="Minors",$G84="YP"),$H84+2,""))))) -> 2026 | J84: 33100000 | K84: =if($E84="","",if($E84="Dropped",if(and(K$1<=$I84,K$1>=$H84),if(Year($D84)=K$1,$F84*0.8,if((year($D84)+1)=K$1,$F84*0.6,$F84*0.4)) ,""),if($E84="Minors",0,if($E84="FA Contract",if(and(K$1<=$I84,K$1>=$H84),$F84,""),if($E84="YP Contract",if(K$1=$H84,500000,if(K$1=($H84+1),1000000,if(K$1=($H84+2),1500000,"")))))))) -> 1000000 | L84: =if($E84="","",if($E84="Dropped",if(and(L$1<=$I84,L$1>=$H84),if(Year($D84)=L$1,$F84*0.8,if((year($D84)+1)=L$1,$F84*0.6,$F84*0.4)) ,""),if($E84="Minors",0,if($E84="FA Contract",if(and(L$1<=$I84,L$1>=$H84),$F84,""),if($E84="YP Contract",if(L$1=$H84,500000,if(L$1=($H84+1),1000000,if(L$1=($H84+2),1500000,"")))))))) -> 1500000 | M84: =if($E84="","",if($E84="Dropped",if(and(M$1<=$I84,M$1>=$H84),if(Year($D84)=M$1,$F84*0.8,if((year($D84)+1)=M$1,$F84*0.6,$F84*0.4)) ,""),if($E84="Minors",0,if($E84="FA Contract",if(and(M$1<=$I84,M$1>=$H84),$F84,""),if($E84="YP Contract",if(M$1=$H84,500000,if(M$1=($H84+1),1000000,if(M$1=($H84+2),1500000,"")))))))) | N84: =if($E84="","",if($E84="Dropped",if(and(N$1<=$I84,N$1>=$H84),if(Year($D84)=N$1,$F84*0.8,if((year($D84)+1)=N$1,$F84*0.6,$F84*0.4)) ,""),if($E84="Minors",0,if($E84="FA Contract",if(and(N$1<=$I84,N$1>=$H84),$F84,""),if($E84="YP Contract",if(N$1=$H84,500000,if(N$1=($H84+1),1000000,if(N$1=($H84+2),1500000,"")))))))) | O84: =if($E84="","",if($E84="Dropped",if(and(O$1<=$I84,O$1>=$H84),if(Year($D84)=O$1,$F84*0.8,if((year($D84)+1)=O$1,$F84*0.6,$F84*0.4)) ,""),if($E84="Minors",0,if($E84="FA Contract",if(and(O$1<=$I84,O$1>=$H84),$F84,""),if($E84="YP Contract",if(O$1=$H84,500000,if(O$1=($H84+1),1000000,if(O$1=($H84+2),1500000,"")))))))) | P84: =if($E84="","",if($E84="Dropped",if(and(P$1<=$I84,P$1>=$H84),if(Year($D84)=P$1,$F84*0.8,if((year($D84)+1)=P$1,$F84*0.6,$F84*0.4)) ,""),if($E84="Minors",0,if($E84="FA Contract",if(and(P$1<=$I84,P$1>=$H84),$F84,""),if($E84="YP Contract",if(P$1=$H84,500000,if(P$1=($H84+1),1000000,if(P$1=($H84+2),1500000,""))))))))
A85: Ronny Mauricio | B85: Brian Frederick | C85: 45343 | E85: YP Contract | F85: YP | G85: YP | H85: 2024 | I85: =if(H85="","",if(or($E85="FA Contract",$E85="Dropped"),$H85+$G85-1,if($E85="YP Contract",$H85+2,if(and($E85="Minors",$G85<>"YP"),$H85+$G85-1,if(and($E85="Minors",$G85="YP"),$H85+2,""))))) -> 2026 | J85: 33100000 | K85: =if($E85="","",if($E85="Dropped",if(and(K$1<=$I85,K$1>=$H85),if(Year($D85)=K$1,$F85*0.8,if((year($D85)+1)=K$1,$F85*0.6,$F85*0.4)) ,""),if($E85="Minors",0,if($E85="FA Contract",if(and(K$1<=$I85,K$1>=$H85),$F85,""),if($E85="YP Contract",if(K$1=$H85,500000,if(K$1=($H85+1),1000000,if(K$1=($H85+2),1500000,"")))))))) -> 1000000 | L85: =if($E85="","",if($E85="Dropped",if(and(L$1<=$I85,L$1>=$H85),if(Year($D85)=L$1,$F85*0.8,if((year($D85)+1)=L$1,$F85*0.6,$F85*0.4)) ,""),if($E85="Minors",0,if($E85="FA Contract",if(and(L$1<=$I85,L$1>=$H85),$F85,""),if($E85="YP Contract",if(L$1=$H85,500000,if(L$1=($H85+1),1000000,if(L$1=($H85+2),1500000,"")))))))) -> 1500000 | M85: =if($E85="","",if($E85="Dropped",if(and(M$1<=$I85,M$1>=$H85),if(Year($D85)=M$1,$F85*0.8,if((year($D85)+1)=M$1,$F85*0.6,$F85*0.4)) ,""),if($E85="Minors",0,if($E85="FA Contract",if(and(M$1<=$I85,M$1>=$H85),$F85,""),if($E85="YP Contract",if(M$1=$H85,500000,if(M$1=($H85+1),1000000,if(M$1=($H85+2),1500000,"")))))))) | N85: =if($E85="","",if($E85="Dropped",if(and(N$1<=$I85,N$1>=$H85),if(Year($D85)=N$1,$F85*0.8,if((year($D85)+1)=N$1,$F85*0.6,$F85*0.4)) ,""),if($E85="Minors",0,if($E85="FA Contract",if(and(N$1<=$I85,N$1>=$H85),$F85,""),if($E85="YP Contract",if(N$1=$H85,500000,if(N$1=($H85+1),1000000,if(N$1=($H85+2),1500000,"")))))))) | O85: =if($E85="","",if($E85="Dropped",if(and(O$1<=$I85,O$1>=$H85),if(Year($D85)=O$1,$F85*0.8,if((year($D85)+1)=O$1,$F85*0.6,$F85*0.4)) ,""),if($E85="Minors",0,if($E85="FA Contract",if(and(O$1<=$I85,O$1>=$H85),$F85,""),if($E85="YP Contract",if(O$1=$H85,500000,if(O$1=($H85+1),1000000,if(O$1=($H85+2),1500000,"")))))))) | P85: =if($E85="","",if($E85="Dropped",if(and(P$1<=$I85,P$1>=$H85),if(Year($D85)=P$1,$F85*0.8,if((year($D85)+1)=P$1,$F85*0.6,$F85*0.4)) ,""),if($E85="Minors",0,if($E85="FA Contract",if(and(P$1<=$I85,P$1>=$H85),$F85,""),if($E85="YP Contract",if(P$1=$H85,500000,if(P$1=($H85+1),1000000,if(P$1=($H85+2),1500000,""))))))))
A86: Carson Willaims | B86: Brian Frederick | C86: 45343 | E86: YP Contract | F86: YP | G86: YP | H86: 2025 | I86: =if(H86="","",if(or($E86="FA Contract",$E86="Dropped"),$H86+$G86-1,if($E86="YP Contract",$H86+2,if(and($E86="Minors",$G86<>"YP"),$H86+$G86-1,if(and($E86="Minors",$G86="YP"),$H86+2,""))))) -> 2027 | J86: 33100000 | K86: =if($E86="","",if($E86="Dropped",if(and(K$1<=$I86,K$1>=$H86),if(Year($D86)=K$1,$F86*0.8,if((year($D86)+1)=K$1,$F86*0.6,$F86*0.4)) ,""),if($E86="Minors",0,if($E86="FA Contract",if(and(K$1<=$I86,K$1>=$H86),$F86,""),if($E86="YP Contract",if(K$1=$H86,500000,if(K$1=($H86+1),1000000,if(K$1=($H86+2),1500000,"")))))))) -> 500000 | L86: =if($E86="","",if($E86="Dropped",if(and(L$1<=$I86,L$1>=$H86),if(Year($D86)=L$1,$F86*0.8,if((year($D86)+1)=L$1,$F86*0.6,$F86*0.4)) ,""),if($E86="Minors",0,if($E86="FA Contract",if(and(L$1<=$I86,L$1>=$H86),$F86,""),if($E86="YP Contract",if(L$1=$H86,500000,if(L$1=($H86+1),1000000,if(L$1=($H86+2),1500000,"")))))))) -> 1000000 | M86: =if($E86="","",if($E86="Dropped",if(and(M$1<=$I86,M$1>=$H86),if(Year($D86)=M$1,$F86*0.8,if((year($D86)+1)=M$1,$F86*0.6,$F86*0.4)) ,""),if($E86="Minors",0,if($E86="FA Contract",if(and(M$1<=$I86,M$1>=$H86),$F86,""),if($E86="YP Contract",if(M$1=$H86,500000,if(M$1=($H86+1),1000000,if(M$1=($H86+2),1500000,"")))))))) -> 1500000 | N86: =if($E86="","",if($E86="Dropped",if(and(N$1<=$I86,N$1>=$H86),if(Year($D86)=N$1,$F86*0.8,if((year($D86)+1)=N$1,$F86*0.6,$F86*0.4)) ,""),if($E86="Minors",0,if($E86="FA Contract",if(and(N$1<=$I86,N$1>=$H86),$F86,""),if($E86="YP Contract",if(N$1=$H86,500000,if(N$1=($H86+1),1000000,if(N$1=($H86+2),1500000,"")))))))) | O86: =if($E86="","",if($E86="Dropped",if(and(O$1<=$I86,O$1>=$H86),if(Year($D86)=O$1,$F86*0.8,if((year($D86)+1)=O$1,$F86*0.6,$F86*0.4)) ,""),if($E86="Minors",0,if($E86="FA Contract",if(and(O$1<=$I86,O$1>=$H86),$F86,""),if($E86="YP Contract",if(O$1=$H86,500000,if(O$1=($H86+1),1000000,if(O$1=($H86+2),1500000,"")))))))) | P86: =if($E86="","",if($E86="Dropped",if(and(P$1<=$I86,P$1>=$H86),if(Year($D86)=P$1,$F86*0.8,if((year($D86)+1)=P$1,$F86*0.6,$F86*0.4)) ,""),if($E86="Minors",0,if($E86="FA Contract",if(and(P$1<=$I86,P$1>=$H86),$F86,""),if($E86="YP Contract",if(P$1=$H86,500000,if(P$1=($H86+1),1000000,if(P$1=($H86+2),1500000,""))))))))
A87: Coby Mayo | B87: Brian Frederick | C87: 45343 | E87: YP Contract | F87: YP | G87: YP | H87: 2025 | I87: =if(H87="","",if(or($E87="FA Contract",$E87="Dropped"),$H87+$G87-1,if($E87="YP Contract",$H87+2,if(and($E87="Minors",$G87<>"YP"),$H87+$G87-1,if(and($E87="Minors",$G87="YP"),$H87+2,""))))) -> 2027 | J87: 33100000 | K87: =if($E87="","",if($E87="Dropped",if(and(K$1<=$I87,K$1>=$H87),if(Year($D87)=K$1,$F87*0.8,if((year($D87)+1)=K$1,$F87*0.6,$F87*0.4)) ,""),if($E87="Minors",0,if($E87="FA Contract",if(and(K$1<=$I87,K$1>=$H87),$F87,""),if($E87="YP Contract",if(K$1=$H87,500000,if(K$1=($H87+1),1000000,if(K$1=($H87+2),1500000,"")))))))) -> 500000 | L87: =if($E87="","",if($E87="Dropped",if(and(L$1<=$I87,L$1>=$H87),if(Year($D87)=L$1,$F87*0.8,if((year($D87)+1)=L$1,$F87*0.6,$F87*0.4)) ,""),if($E87="Minors",0,if($E87="FA Contract",if(and(L$1<=$I87,L$1>=$H87),$F87,""),if($E87="YP Contract",if(L$1=$H87,500000,if(L$1=($H87+1),1000000,if(L$1=($H87+2),1500000,"")))))))) -> 1000000 | M87: =if($E87="","",if($E87="Dropped",if(and(M$1<=$I87,M$1>=$H87),if(Year($D87)=M$1,$F87*0.8,if((year($D87)+1)=M$1,$F87*0.6,$F87*0.4)) ,""),if($E87="Minors",0,if($E87="FA Contract",if(and(M$1<=$I87,M$1>=$H87),$F87,""),if($E87="YP Contract",if(M$1=$H87,500000,if(M$1=($H87+1),1000000,if(M$1=($H87+2),1500000,"")))))))) -> 1500000 | N87: =if($E87="","",if($E87="Dropped",if(and(N$1<=$I87,N$1>=$H87),if(Year($D87)=N$1,$F87*0.8,if((year($D87)+1)=N$1,$F87*0.6,$F87*0.4)) ,""),if($E87="Minors",0,if($E87="FA Contract",if(and(N$1<=$I87,N$1>=$H87),$F87,""),if($E87="YP Contract",if(N$1=$H87,500000,if(N$1=($H87+1),1000000,if(N$1=($H87+2),1500000,"")))))))) | O87: =if($E87="","",if($E87="Dropped",if(and(O$1<=$I87,O$1>=$H87),if(Year($D87)=O$1,$F87*0.8,if((year($D87)+1)=O$1,$F87*0.6,$F87*0.4)) ,""),if($E87="Minors",0,if($E87="FA Contract",if(and(O$1<=$I87,O$1>=$H87),$F87,""),if($E87="YP Contract",if(O$1=$H87,500000,if(O$1=($H87+1),1000000,if(O$1=($H87+2),1500000,"")))))))) | P87: =if($E87="","",if($E87="Dropped",if(and(P$1<=$I87,P$1>=$H87),if(Year($D87)=P$1,$F87*0.8,if((year($D87)+1)=P$1,$F87*0.6,$F87*0.4)) ,""),if($E87="Minors",0,if($E87="FA Contract",if(and(P$1<=$I87,P$1>=$H87),$F87,""),if($E87="YP Contract",if(P$1=$H87,500000,if(P$1=($H87+1),1000000,if(P$1=($H87+2),1500000,""))))))))
A88: Jeff McNeil | B88: Brian Frederick | C88: 45721 | E88: FA Contract | F88: 500000 | G88: 1 | H88: 2025 | I88: =if(H88="","",if(or($E88="FA Contract",$E88="Dropped"),$H88+$G88-1,if($E88="YP Contract",$H88+2,if(and($E88="Minors",$G88<>"YP"),$H88+$G88-1,if(and($E88="Minors",$G88="YP"),$H88+2,""))))) -> 2025 | J88: 33100000 | K88: =if($E88="","",if($E88="Dropped",if(and(K$1<=$I88,K$1>=$H88),if(Year($D88)=K$1,$F88*0.8,if((year($D88)+1)=K$1,$F88*0.6,$F88*0.4)) ,""),if($E88="Minors",0,if($E88="FA Contract",if(and(K$1<=$I88,K$1>=$H88),$F88,""),if($E88="YP Contract",if(K$1=$H88,500000,if(K$1=($H88+1),1000000,if(K$1=($H88+2),1500000,"")))))))) -> 500000 | L88: =if($E88="","",if($E88="Dropped",if(and(L$1<=$I88,L$1>=$H88),if(Year($D88)=L$1,$F88*0.8,if((year($D88)+1)=L$1,$F88*0.6,$F88*0.4)) ,""),if($E88="Minors",0,if($E88="FA Contract",if(and(L$1<=$I88,L$1>=$H88),$F88,""),if($E88="YP Contract",if(L$1=$H88,500000,if(L$1=($H88+1),1000000,if(L$1=($H88+2),1500000,"")))))))) | M88: =if($E88="","",if($E88="Dropped",if(and(M$1<=$I88,M$1>=$H88),if(Year($D88)=M$1,$F88*0.8,if((year($D88)+1)=M$1,$F88*0.6,$F88*0.4)) ,""),if($E88="Minors",0,if($E88="FA Contract",if(and(M$1<=$I88,M$1>=$H88),$F88,""),if($E88="YP Contract",if(M$1=$H88,500000,if(M$1=($H88+1),1000000,if(M$1=($H88+2),1500000,"")))))))) | N88: =if($E88="","",if($E88="Dropped",if(and(N$1<=$I88,N$1>=$H88),if(Year($D88)=N$1,$F88*0.8,if((year($D88)+1)=N$1,$F88*0.6,$F88*0.4)) ,""),if($E88="Minors",0,if($E88="FA Contract",if(and(N$1<=$I88,N$1>=$H88),$F88,""),if($E88="YP Contract",if(N$1=$H88,500000,if(N$1=($H88+1),1000000,if(N$1=($H88+2),1500000,"")))))))) | O88: =if($E88="","",if($E88="Dropped",if(and(O$1<=$I88,O$1>=$H88),if(Year($D88)=O$1,$F88*0.8,if((year($D88)+1)=O$1,$F88*0.6,$F88*0.4)) ,""),if($E88="Minors",0,if($E88="FA Contract",if(and(O$1<=$I88,O$1>=$H88),$F88,""),if($E88="YP Contract",if(O$1=$H88,500000,if(O$1=($H88+1),1000000,if(O$1=($H88+2),1500000,"")))))))) | P88: =if($E88="","",if($E88="Dropped",if(and(P$1<=$I88,P$1>=$H88),if(Year($D88)=P$1,$F88*0.8,if((year($D88)+1)=P$1,$F88*0.6,$F88*0.4)) ,""),if($E88="Minors",0,if($E88="FA Contract",if(and(P$1<=$I88,P$1>=$H88),$F88,""),if($E88="YP Contract",if(P$1=$H88,500000,if(P$1=($H88+1),1000000,if(P$1=($H88+2),1500000,""))))))))
A89: Roman Anthony | B89: Brian Frederick | C89: 45343 | E89: YP Contract | F89: YP | G89: YP | H89: 2025 | I89: =if(H89="","",if(or($E89="FA Contract",$E89="Dropped"),$H89+$G89-1,if($E89="YP Contract",$H89+2,if(and($E89="Minors",$G89<>"YP"),$H89+$G89-1,if(and($E89="Minors",$G89="YP"),$H89+2,""))))) -> 2027 | J89: 33100000 | K89: =if($E89="","",if($E89="Dropped",if(and(K$1<=$I89,K$1>=$H89),if(Year($D89)=K$1,$F89*0.8,if((year($D89)+1)=K$1,$F89*0.6,$F89*0.4)) ,""),if($E89="Minors",0,if($E89="FA Contract",if(and(K$1<=$I89,K$1>=$H89),$F89,""),if($E89="YP Contract",if(K$1=$H89,500000,if(K$1=($H89+1),1000000,if(K$1=($H89+2),1500000,"")))))))) -> 500000 | L89: =if($E89="","",if($E89="Dropped",if(and(L$1<=$I89,L$1>=$H89),if(Year($D89)=L$1,$F89*0.8,if((year($D89)+1)=L$1,$F89*0.6,$F89*0.4)) ,""),if($E89="Minors",0,if($E89="FA Contract",if(and(L$1<=$I89,L$1>=$H89),$F89,""),if($E89="YP Contract",if(L$1=$H89,500000,if(L$1=($H89+1),1000000,if(L$1=($H89+2),1500000,"")))))))) -> 1000000 | M89: =if($E89="","",if($E89="Dropped",if(and(M$1<=$I89,M$1>=$H89),if(Year($D89)=M$1,$F89*0.8,if((year($D89)+1)=M$1,$F89*0.6,$F89*0.4)) ,""),if($E89="Minors",0,if($E89="FA Contract",if(and(M$1<=$I89,M$1>=$H89),$F89,""),if($E89="YP Contract",if(M$1=$H89,500000,if(M$1=($H89+1),1000000,if(M$1=($H89+2),1500000,"")))))))) -> 1500000 | N89: =if($E89="","",if($E89="Dropped",if(and(N$1<=$I89,N$1>=$H89),if(Year($D89)=N$1,$F89*0.8,if((year($D89)+1)=N$1,$F89*0.6,$F89*0.4)) ,""),if($E89="Minors",0,if($E89="FA Contract",if(and(N$1<=$I89,N$1>=$H89),$F89,""),if($E89="YP Contract",if(N$1=$H89,500000,if(N$1=($H89+1),1000000,if(N$1=($H89+2),1500000,"")))))))) | O89: =if($E89="","",if($E89="Dropped",if(and(O$1<=$I89,O$1>=$H89),if(Year($D89)=O$1,$F89*0.8,if((year($D89)+1)=O$1,$F89*0.6,$F89*0.4)) ,""),if($E89="Minors",0,if($E89="FA Contract",if(and(O$1<=$I89,O$1>=$H89),$F89,""),if($E89="YP Contract",if(O$1=$H89,500000,if(O$1=($H89+1),1000000,if(O$1=($H89+2),1500000,"")))))))) | P89: =if($E89="","",if($E89="Dropped",if(and(P$1<=$I89,P$1>=$H89),if(Year($D89)=P$1,$F89*0.8,if((year($D89)+1)=P$1,$F89*0.6,$F89*0.4)) ,""),if($E89="Minors",0,if($E89="FA Contract",if(and(P$1<=$I89,P$1>=$H89),$F89,""),if($E89="YP Contract",if(P$1=$H89,500000,if(P$1=($H89+1),1000000,if(P$1=($H89+2),1500000,""))))))))
A90: Wilmer Flores | B90: Brian Frederick | C90: 45760 | E90: FA Contract | F90: 500000 | G90: 1 | H90: 2025 | I90: =if(H90="","",if(or($E90="FA Contract",$E90="Dropped"),$H90+$G90-1,if($E90="YP Contract",$H90+2,if(and($E90="Minors",$G90<>"YP"),$H90+$G90-1,if(and($E90="Minors",$G90="YP"),$H90+2,""))))) -> 2025 | J90: 33100000 | K90: =if($E90="","",if($E90="Dropped",if(and(K$1<=$I90,K$1>=$H90),if(Year($D90)=K$1,$F90*0.8,if((year($D90)+1)=K$1,$F90*0.6,$F90*0.4)) ,""),if($E90="Minors",0,if($E90="FA Contract",if(and(K$1<=$I90,K$1>=$H90),$F90,""),if($E90="YP Contract",if(K$1=$H90,500000,if(K$1=($H90+1),1000000,if(K$1=($H90+2),1500000,"")))))))) -> 500000 | L90: =if($E90="","",if($E90="Dropped",if(and(L$1<=$I90,L$1>=$H90),if(Year($D90)=L$1,$F90*0.8,if((year($D90)+1)=L$1,$F90*0.6,$F90*0.4)) ,""),if($E90="Minors",0,if($E90="FA Contract",if(and(L$1<=$I90,L$1>=$H90),$F90,""),if($E90="YP Contract",if(L$1=$H90,500000,if(L$1=($H90+1),1000000,if(L$1=($H90+2),1500000,"")))))))) | M90: =if($E90="","",if($E90="Dropped",if(and(M$1<=$I90,M$1>=$H90),if(Year($D90)=M$1,$F90*0.8,if((year($D90)+1)=M$1,$F90*0.6,$F90*0.4)) ,""),if($E90="Minors",0,if($E90="FA Contract",if(and(M$1<=$I90,M$1>=$H90),$F90,""),if($E90="YP Contract",if(M$1=$H90,500000,if(M$1=($H90+1),1000000,if(M$1=($H90+2),1500000,"")))))))) | N90: =if($E90="","",if($E90="Dropped",if(and(N$1<=$I90,N$1>=$H90),if(Year($D90)=N$1,$F90*0.8,if((year($D90)+1)=N$1,$F90*0.6,$F90*0.4)) ,""),if($E90="Minors",0,if($E90="FA Contract",if(and(N$1<=$I90,N$1>=$H90),$F90,""),if($E90="YP Contract",if(N$1=$H90,500000,if(N$1=($H90+1),1000000,if(N$1=($H90+2),1500000,"")))))))) | O90: =if($E90="","",if($E90="Dropped",if(and(O$1<=$I90,O$1>=$H90),if(Year($D90)=O$1,$F90*0.8,if((year($D90)+1)=O$1,$F90*0.6,$F90*0.4)) ,""),if($E90="Minors",0,if($E90="FA Contract",if(and(O$1<=$I90,O$1>=$H90),$F90,""),if($E90="YP Contract",if(O$1=$H90,500000,if(O$1=($H90+1),1000000,if(O$1=($H90+2),1500000,"")))))))) | P90: =if($E90="","",if($E90="Dropped",if(and(P$1<=$I90,P$1>=$H90),if(Year($D90)=P$1,$F90*0.8,if((year($D90)+1)=P$1,$F90*0.6,$F90*0.4)) ,""),if($E90="Minors",0,if($E90="FA Contract",if(and(P$1<=$I90,P$1>=$H90),$F90,""),if($E90="YP Contract",if(P$1=$H90,500000,if(P$1=($H90+1),1000000,if(P$1=($H90+2),1500000,""))))))))
A91: Zack Littell | B91: Brian Frederick | C91: 45721 | E91: FA Contract | F91: 500000 | G91: 1 | H91: 2025 | I91: =if(H91="","",if(or($E91="FA Contract",$E91="Dropped"),$H91+$G91-1,if($E91="YP Contract",$H91+2,if(and($E91="Minors",$G91<>"YP"),$H91+$G91-1,if(and($E91="Minors",$G91="YP"),$H91+2,""))))) -> 2025 | J91: 33100000 | K91: =if($E91="","",if($E91="Dropped",if(and(K$1<=$I91,K$1>=$H91),if(Year($D91)=K$1,$F91*0.8,if((year($D91)+1)=K$1,$F91*0.6,$F91*0.4)) ,""),if($E91="Minors",0,if($E91="FA Contract",if(and(K$1<=$I91,K$1>=$H91),$F91,""),if($E91="YP Contract",if(K$1=$H91,500000,if(K$1=($H91+1),1000000,if(K$1=($H91+2),1500000,"")))))))) -> 500000 | L91: =if($E91="","",if($E91="Dropped",if(and(L$1<=$I91,L$1>=$H91),if(Year($D91)=L$1,$F91*0.8,if((year($D91)+1)=L$1,$F91*0.6,$F91*0.4)) ,""),if($E91="Minors",0,if($E91="FA Contract",if(and(L$1<=$I91,L$1>=$H91),$F91,""),if($E91="YP Contract",if(L$1=$H91,500000,if(L$1=($H91+1),1000000,if(L$1=($H91+2),1500000,"")))))))) | M91: =if($E91="","",if($E91="Dropped",if(and(M$1<=$I91,M$1>=$H91),if(Year($D91)=M$1,$F91*0.8,if((year($D91)+1)=M$1,$F91*0.6,$F91*0.4)) ,""),if($E91="Minors",0,if($E91="FA Contract",if(and(M$1<=$I91,M$1>=$H91),$F91,""),if($E91="YP Contract",if(M$1=$H91,500000,if(M$1=($H91+1),1000000,if(M$1=($H91+2),1500000,"")))))))) | N91: =if($E91="","",if($E91="Dropped",if(and(N$1<=$I91,N$1>=$H91),if(Year($D91)=N$1,$F91*0.8,if((year($D91)+1)=N$1,$F91*0.6,$F91*0.4)) ,""),if($E91="Minors",0,if($E91="FA Contract",if(and(N$1<=$I91,N$1>=$H91),$F91,""),if($E91="YP Contract",if(N$1=$H91,500000,if(N$1=($H91+1),1000000,if(N$1=($H91+2),1500000,"")))))))) | O91: =if($E91="","",if($E91="Dropped",if(and(O$1<=$I91,O$1>=$H91),if(Year($D91)=O$1,$F91*0.8,if((year($D91)+1)=O$1,$F91*0.6,$F91*0.4)) ,""),if($E91="Minors",0,if($E91="FA Contract",if(and(O$1<=$I91,O$1>=$H91),$F91,""),if($E91="YP Contract",if(O$1=$H91,500000,if(O$1=($H91+1),1000000,if(O$1=($H91+2),1500000,"")))))))) | P91: =if($E91="","",if($E91="Dropped",if(and(P$1<=$I91,P$1>=$H91),if(Year($D91)=P$1,$F91*0.8,if((year($D91)+1)=P$1,$F91*0.6,$F91*0.4)) ,""),if($E91="Minors",0,if($E91="FA Contract",if(and(P$1<=$I91,P$1>=$H91),$F91,""),if($E91="YP Contract",if(P$1=$H91,500000,if(P$1=($H91+1),1000000,if(P$1=($H91+2),1500000,""))))))))
A92: Dylan Lee | B92: Brian Frederick | C92: 45837 | E92: FA Contract | F92: 100000 | G92: 1 | H92: 2025 | I92: =if(H92="","",if(or($E92="FA Contract",$E92="Dropped"),$H92+$G92-1,if($E92="YP Contract",$H92+2,if(and($E92="Minors",$G92<>"YP"),$H92+$G92-1,if(and($E92="Minors",$G92="YP"),$H92+2,""))))) -> 2025 | J92: 33100000 | K92: =if($E92="","",if($E92="Dropped",if(and(K$1<=$I92,K$1>=$H92),if(Year($D92)=K$1,$F92*0.8,if((year($D92)+1)=K$1,$F92*0.6,$F92*0.4)) ,""),if($E92="Minors",0,if($E92="FA Contract",if(and(K$1<=$I92,K$1>=$H92),$F92,""),if($E92="YP Contract",if(K$1=$H92,500000,if(K$1=($H92+1),1000000,if(K$1=($H92+2),1500000,"")))))))) -> 100000 | L92: =if($E92="","",if($E92="Dropped",if(and(L$1<=$I92,L$1>=$H92),if(Year($D92)=L$1,$F92*0.8,if((year($D92)+1)=L$1,$F92*0.6,$F92*0.4)) ,""),if($E92="Minors",0,if($E92="FA Contract",if(and(L$1<=$I92,L$1>=$H92),$F92,""),if($E92="YP Contract",if(L$1=$H92,500000,if(L$1=($H92+1),1000000,if(L$1=($H92+2),1500000,"")))))))) | M92: =if($E92="","",if($E92="Dropped",if(and(M$1<=$I92,M$1>=$H92),if(Year($D92)=M$1,$F92*0.8,if((year($D92)+1)=M$1,$F92*0.6,$F92*0.4)) ,""),if($E92="Minors",0,if($E92="FA Contract",if(and(M$1<=$I92,M$1>=$H92),$F92,""),if($E92="YP Contract",if(M$1=$H92,500000,if(M$1=($H92+1),1000000,if(M$1=($H92+2),1500000,"")))))))) | N92: =if($E92="","",if($E92="Dropped",if(and(N$1<=$I92,N$1>=$H92),if(Year($D92)=N$1,$F92*0.8,if((year($D92)+1)=N$1,$F92*0.6,$F92*0.4)) ,""),if($E92="Minors",0,if($E92="FA Contract",if(and(N$1<=$I92,N$1>=$H92),$F92,""),if($E92="YP Contract",if(N$1=$H92,500000,if(N$1=($H92+1),1000000,if(N$1=($H92+2),1500000,"")))))))) | O92: =if($E92="","",if($E92="Dropped",if(and(O$1<=$I92,O$1>=$H92),if(Year($D92)=O$1,$F92*0.8,if((year($D92)+1)=O$1,$F92*0.6,$F92*0.4)) ,""),if($E92="Minors",0,if($E92="FA Contract",if(and(O$1<=$I92,O$1>=$H92),$F92,""),if($E92="YP Contract",if(O$1=$H92,500000,if(O$1=($H92+1),1000000,if(O$1=($H92+2),1500000,"")))))))) | P92: =if($E92="","",if($E92="Dropped",if(and(P$1<=$I92,P$1>=$H92),if(Year($D92)=P$1,$F92*0.8,if((year($D92)+1)=P$1,$F92*0.6,$F92*0.4)) ,""),if($E92="Minors",0,if($E92="FA Contract",if(and(P$1<=$I92,P$1>=$H92),$F92,""),if($E92="YP Contract",if(P$1=$H92,500000,if(P$1=($H92+1),1000000,if(P$1=($H92+2),1500000,""))))))))
A93: Trevor Story | B93: Brian Frederick | C93: 45863 | E93: FA Contract | F93: 100000 | G93: 1 | H93: 2025 | I93: =if(H93="","",if(or($E93="FA Contract",$E93="Dropped"),$H93+$G93-1,if($E93="YP Contract",$H93+2,if(and($E93="Minors",$G93<>"YP"),$H93+$G93-1,if(and($E93="Minors",$G93="YP"),$H93+2,""))))) -> 2025 | J93: 33100000 | K93: =if($E93="","",if($E93="Dropped",if(and(K$1<=$I93,K$1>=$H93),if(Year($D93)=K$1,$F93*0.8,if((year($D93)+1)=K$1,$F93*0.6,$F93*0.4)) ,""),if($E93="Minors",0,if($E93="FA Contract",if(and(K$1<=$I93,K$1>=$H93),$F93,""),if($E93="YP Contract",if(K$1=$H93,500000,if(K$1=($H93+1),1000000,if(K$1=($H93+2),1500000,"")))))))) -> 100000 | L93: =if($E93="","",if($E93="Dropped",if(and(L$1<=$I93,L$1>=$H93),if(Year($D93)=L$1,$F93*0.8,if((year($D93)+1)=L$1,$F93*0.6,$F93*0.4)) ,""),if($E93="Minors",0,if($E93="FA Contract",if(and(L$1<=$I93,L$1>=$H93),$F93,""),if($E93="YP Contract",if(L$1=$H93,500000,if(L$1=($H93+1),1000000,if(L$1=($H93+2),1500000,"")))))))) | M93: =if($E93="","",if($E93="Dropped",if(and(M$1<=$I93,M$1>=$H93),if(Year($D93)=M$1,$F93*0.8,if((year($D93)+1)=M$1,$F93*0.6,$F93*0.4)) ,""),if($E93="Minors",0,if($E93="FA Contract",if(and(M$1<=$I93,M$1>=$H93),$F93,""),if($E93="YP Contract",if(M$1=$H93,500000,if(M$1=($H93+1),1000000,if(M$1=($H93+2),1500000,"")))))))) | N93: =if($E93="","",if($E93="Dropped",if(and(N$1<=$I93,N$1>=$H93),if(Year($D93)=N$1,$F93*0.8,if((year($D93)+1)=N$1,$F93*0.6,$F93*0.4)) ,""),if($E93="Minors",0,if($E93="FA Contract",if(and(N$1<=$I93,N$1>=$H93),$F93,""),if($E93="YP Contract",if(N$1=$H93,500000,if(N$1=($H93+1),1000000,if(N$1=($H93+2),1500000,"")))))))) | O93: =if($E93="","",if($E93="Dropped",if(and(O$1<=$I93,O$1>=$H93),if(Year($D93)=O$1,$F93*0.8,if((year($D93)+1)=O$1,$F93*0.6,$F93*0.4)) ,""),if($E93="Minors",0,if($E93="FA Contract",if(and(O$1<=$I93,O$1>=$H93),$F93,""),if($E93="YP Contract",if(O$1=$H93,500000,if(O$1=($H93+1),1000000,if(O$1=($H93+2),1500000,"")))))))) | P93: =if($E93="","",if($E93="Dropped",if(and(P$1<=$I93,P$1>=$H93),if(Year($D93)=P$1,$F93*0.8,if((year($D93)+1)=P$1,$F93*0.6,$F93*0.4)) ,""),if($E93="Minors",0,if($E93="FA Contract",if(and(P$1<=$I93,P$1>=$H93),$F93,""),if($E93="YP Contract",if(P$1=$H93,500000,if(P$1=($H93+1),1000000,if(P$1=($H93+2),1500000,""))))))))
A94: Ben Hess | B94: Brian Frederick | C94: 45694 | E94: Minors | F94: YP | G94: YP | I94: =if(H94="","",if(or($E94="FA Contract",$E94="Dropped"),$H94+$G94-1,if($E94="YP Contract",$H94+2,if(and($E94="Minors",$G94<>"YP"),$H94+$G94-1,if(and($E94="Minors",$G94="YP"),$H94+2,""))))) | J94: 33100000 | K94: =if($E94="","",if($E94="Dropped",if(and(K$1<=$I94,K$1>=$H94),if(Year($D94)=K$1,$F94*0.8,if((year($D94)+1)=K$1,$F94*0.6,$F94*0.4)) ,""),if($E94="Minors",0,if($E94="FA Contract",if(and(K$1<=$I94,K$1>=$H94),$F94,""),if($E94="YP Contract",if(K$1=$H94,500000,if(K$1=($H94+1),1000000,if(K$1=($H94+2),1500000,"")))))))) -> 0 | L94: =if($E94="","",if($E94="Dropped",if(and(L$1<=$I94,L$1>=$H94),if(Year($D94)=L$1,$F94*0.8,if((year($D94)+1)=L$1,$F94*0.6,$F94*0.4)) ,""),if($E94="Minors",0,if($E94="FA Contract",if(and(L$1<=$I94,L$1>=$H94),$F94,""),if($E94="YP Contract",if(L$1=$H94,500000,if(L$1=($H94+1),1000000,if(L$1=($H94+2),1500000,"")))))))) -> 0 | M94: =if($E94="","",if($E94="Dropped",if(and(M$1<=$I94,M$1>=$H94),if(Year($D94)=M$1,$F94*0.8,if((year($D94)+1)=M$1,$F94*0.6,$F94*0.4)) ,""),if($E94="Minors",0,if($E94="FA Contract",if(and(M$1<=$I94,M$1>=$H94),$F94,""),if($E94="YP Contract",if(M$1=$H94,500000,if(M$1=($H94+1),1000000,if(M$1=($H94+2),1500000,"")))))))) -> 0 | N94: =if($E94="","",if($E94="Dropped",if(and(N$1<=$I94,N$1>=$H94),if(Year($D94)=N$1,$F94*0.8,if((year($D94)+1)=N$1,$F94*0.6,$F94*0.4)) ,""),if($E94="Minors",0,if($E94="FA Contract",if(and(N$1<=$I94,N$1>=$H94),$F94,""),if($E94="YP Contract",if(N$1=$H94,500000,if(N$1=($H94+1),1000000,if(N$1=($H94+2),1500000,"")))))))) -> 0 | O94: =if($E94="","",if($E94="Dropped",if(and(O$1<=$I94,O$1>=$H94),if(Year($D94)=O$1,$F94*0.8,if((year($D94)+1)=O$1,$F94*0.6,$F94*0.4)) ,""),if($E94="Minors",0,if($E94="FA Contract",if(and(O$1<=$I94,O$1>=$H94),$F94,""),if($E94="YP Contract",if(O$1=$H94,500000,if(O$1=($H94+1),1000000,if(O$1=($H94+2),1500000,"")))))))) -> 0 | P94: =if($E94="","",if($E94="Dropped",if(and(P$1<=$I94,P$1>=$H94),if(Year($D94)=P$1,$F94*0.8,if((year($D94)+1)=P$1,$F94*0.6,$F94*0.4)) ,""),if($E94="Minors",0,if($E94="FA Contract",if(and(P$1<=$I94,P$1>=$H94),$F94,""),if($E94="YP Contract",if(P$1=$H94,500000,if(P$1=($H94+1),1000000,if(P$1=($H94+2),1500000,"")))))))) -> 0
A95: Jett Williams | B95: Brian Frederick | C95: 45343 | E95: Minors | F95: YP | G95: YP | I95: =if(H95="","",if(or($E95="FA Contract",$E95="Dropped"),$H95+$G95-1,if($E95="YP Contract",$H95+2,if(and($E95="Minors",$G95<>"YP"),$H95+$G95-1,if(and($E95="Minors",$G95="YP"),$H95+2,""))))) | J95: 33100000 | K95: =if($E95="","",if($E95="Dropped",if(and(K$1<=$I95,K$1>=$H95),if(Year($D95)=K$1,$F95*0.8,if((year($D95)+1)=K$1,$F95*0.6,$F95*0.4)) ,""),if($E95="Minors",0,if($E95="FA Contract",if(and(K$1<=$I95,K$1>=$H95),$F95,""),if($E95="YP Contract",if(K$1=$H95,500000,if(K$1=($H95+1),1000000,if(K$1=($H95+2),1500000,"")))))))) -> 0 | L95: =if($E95="","",if($E95="Dropped",if(and(L$1<=$I95,L$1>=$H95),if(Year($D95)=L$1,$F95*0.8,if((year($D95)+1)=L$1,$F95*0.6,$F95*0.4)) ,""),if($E95="Minors",0,if($E95="FA Contract",if(and(L$1<=$I95,L$1>=$H95),$F95,""),if($E95="YP Contract",if(L$1=$H95,500000,if(L$1=($H95+1),1000000,if(L$1=($H95+2),1500000,"")))))))) -> 0 | M95: =if($E95="","",if($E95="Dropped",if(and(M$1<=$I95,M$1>=$H95),if(Year($D95)=M$1,$F95*0.8,if((year($D95)+1)=M$1,$F95*0.6,$F95*0.4)) ,""),if($E95="Minors",0,if($E95="FA Contract",if(and(M$1<=$I95,M$1>=$H95),$F95,""),if($E95="YP Contract",if(M$1=$H95,500000,if(M$1=($H95+1),1000000,if(M$1=($H95+2),1500000,"")))))))) -> 0 | N95: =if($E95="","",if($E95="Dropped",if(and(N$1<=$I95,N$1>=$H95),if(Year($D95)=N$1,$F95*0.8,if((year($D95)+1)=N$1,$F95*0.6,$F95*0.4)) ,""),if($E95="Minors",0,if($E95="FA Contract",if(and(N$1<=$I95,N$1>=$H95),$F95,""),if($E95="YP Contract",if(N$1=$H95,500000,if(N$1=($H95+1),1000000,if(N$1=($H95+2),1500000,"")))))))) -> 0 | O95: =if($E95="","",if($E95="Dropped",if(and(O$1<=$I95,O$1>=$H95),if(Year($D95)=O$1,$F95*0.8,if((year($D95)+1)=O$1,$F95*0.6,$F95*0.4)) ,""),if($E95="Minors",0,if($E95="FA Contract",if(and(O$1<=$I95,O$1>=$H95),$F95,""),if($E95="YP Contract",if(O$1=$H95,500000,if(O$1=($H95+1),1000000,if(O$1=($H95+2),1500000,"")))))))) -> 0 | P95: =if($E95="","",if($E95="Dropped",if(and(P$1<=$I95,P$1>=$H95),if(Year($D95)=P$1,$F95*0.8,if((year($D95)+1)=P$1,$F95*0.6,$F95*0.4)) ,""),if($E95="Minors",0,if($E95="FA Contract",if(and(P$1<=$I95,P$1>=$H95),$F95,""),if($E95="YP Contract",if(P$1=$H95,500000,if(P$1=($H95+1),1000000,if(P$1=($H95+2),1500000,"")))))))) -> 0
A96: Kameron Misner | B96: Brian Frederick | C96: 45774 | E96: Minors | F96: 5000000 | G96: 1 | H96: 2025 | I96: =if(H96="","",if(or($E96="FA Contract",$E96="Dropped"),$H96+$G96-1,if($E96="YP Contract",$H96+2,if(and($E96="Minors",$G96<>"YP"),$H96+$G96-1,if(and($E96="Minors",$G96="YP"),$H96+2,""))))) -> 2025 | J96: 33100000 | K96: =if($E96="","",if($E96="Dropped",if(and(K$1<=$I96,K$1>=$H96),if(Year($D96)=K$1,$F96*0.8,if((year($D96)+1)=K$1,$F96*0.6,$F96*0.4)) ,""),if($E96="Minors",0,if($E96="FA Contract",if(and(K$1<=$I96,K$1>=$H96),$F96,""),if($E96="YP Contract",if(K$1=$H96,500000,if(K$1=($H96+1),1000000,if(K$1=($H96+2),1500000,"")))))))) -> 0 | L96: =if($E96="","",if($E96="Dropped",if(and(L$1<=$I96,L$1>=$H96),if(Year($D96)=L$1,$F96*0.8,if((year($D96)+1)=L$1,$F96*0.6,$F96*0.4)) ,""),if($E96="Minors",0,if($E96="FA Contract",if(and(L$1<=$I96,L$1>=$H96),$F96,""),if($E96="YP Contract",if(L$1=$H96,500000,if(L$1=($H96+1),1000000,if(L$1=($H96+2),1500000,"")))))))) -> 0 | M96: =if($E96="","",if($E96="Dropped",if(and(M$1<=$I96,M$1>=$H96),if(Year($D96)=M$1,$F96*0.8,if((year($D96)+1)=M$1,$F96*0.6,$F96*0.4)) ,""),if($E96="Minors",0,if($E96="FA Contract",if(and(M$1<=$I96,M$1>=$H96),$F96,""),if($E96="YP Contract",if(M$1=$H96,500000,if(M$1=($H96+1),1000000,if(M$1=($H96+2),1500000,"")))))))) -> 0 | N96: =if($E96="","",if($E96="Dropped",if(and(N$1<=$I96,N$1>=$H96),if(Year($D96)=N$1,$F96*0.8,if((year($D96)+1)=N$1,$F96*0.6,$F96*0.4)) ,""),if($E96="Minors",0,if($E96="FA Contract",if(and(N$1<=$I96,N$1>=$H96),$F96,""),if($E96="YP Contract",if(N$1=$H96,500000,if(N$1=($H96+1),1000000,if(N$1=($H96+2),1500000,"")))))))) -> 0 | O96: =if($E96="","",if($E96="Dropped",if(and(O$1<=$I96,O$1>=$H96),if(Year($D96)=O$1,$F96*0.8,if((year($D96)+1)=O$1,$F96*0.6,$F96*0.4)) ,""),if($E96="Minors",0,if($E96="FA Contract",if(and(O$1<=$I96,O$1>=$H96),$F96,""),if($E96="YP Contract",if(O$1=$H96,500000,if(O$1=($H96+1),1000000,if(O$1=($H96+2),1500000,"")))))))) -> 0 | P96: =if($E96="","",if($E96="Dropped",if(and(P$1<=$I96,P$1>=$H96),if(Year($D96)=P$1,$F96*0.8,if((year($D96)+1)=P$1,$F96*0.6,$F96*0.4)) ,""),if($E96="Minors",0,if($E96="FA Contract",if(and(P$1<=$I96,P$1>=$H96),$F96,""),if($E96="YP Contract",if(P$1=$H96,500000,if(P$1=($H96+1),1000000,if(P$1=($H96+2),1500000,"")))))))) -> 0
A97: Kevin Parada | B97: Brian Frederick | C97: 45344 | E97: Minors | F97: YP | G97: YP | I97: =if(H97="","",if(or($E97="FA Contract",$E97="Dropped"),$H97+$G97-1,if($E97="YP Contract",$H97+2,if(and($E97="Minors",$G97<>"YP"),$H97+$G97-1,if(and($E97="Minors",$G97="YP"),$H97+2,""))))) | J97: 33100000 | K97: =if($E97="","",if($E97="Dropped",if(and(K$1<=$I97,K$1>=$H97),if(Year($D97)=K$1,$F97*0.8,if((year($D97)+1)=K$1,$F97*0.6,$F97*0.4)) ,""),if($E97="Minors",0,if($E97="FA Contract",if(and(K$1<=$I97,K$1>=$H97),$F97,""),if($E97="YP Contract",if(K$1=$H97,500000,if(K$1=($H97+1),1000000,if(K$1=($H97+2),1500000,"")))))))) -> 0 | L97: =if($E97="","",if($E97="Dropped",if(and(L$1<=$I97,L$1>=$H97),if(Year($D97)=L$1,$F97*0.8,if((year($D97)+1)=L$1,$F97*0.6,$F97*0.4)) ,""),if($E97="Minors",0,if($E97="FA Contract",if(and(L$1<=$I97,L$1>=$H97),$F97,""),if($E97="YP Contract",if(L$1=$H97,500000,if(L$1=($H97+1),1000000,if(L$1=($H97+2),1500000,"")))))))) -> 0 | M97: =if($E97="","",if($E97="Dropped",if(and(M$1<=$I97,M$1>=$H97),if(Year($D97)=M$1,$F97*0.8,if((year($D97)+1)=M$1,$F97*0.6,$F97*0.4)) ,""),if($E97="Minors",0,if($E97="FA Contract",if(and(M$1<=$I97,M$1>=$H97),$F97,""),if($E97="YP Contract",if(M$1=$H97,500000,if(M$1=($H97+1),1000000,if(M$1=($H97+2),1500000,"")))))))) -> 0 | N97: =if($E97="","",if($E97="Dropped",if(and(N$1<=$I97,N$1>=$H97),if(Year($D97)=N$1,$F97*0.8,if((year($D97)+1)=N$1,$F97*0.6,$F97*0.4)) ,""),if($E97="Minors",0,if($E97="FA Contract",if(and(N$1<=$I97,N$1>=$H97),$F97,""),if($E97="YP Contract",if(N$1=$H97,500000,if(N$1=($H97+1),1000000,if(N$1=($H97+2),1500000,"")))))))) -> 0 | O97: =if($E97="","",if($E97="Dropped",if(and(O$1<=$I97,O$1>=$H97),if(Year($D97)=O$1,$F97*0.8,if((year($D97)+1)=O$1,$F97*0.6,$F97*0.4)) ,""),if($E97="Minors",0,if($E97="FA Contract",if(and(O$1<=$I97,O$1>=$H97),$F97,""),if($E97="YP Contract",if(O$1=$H97,500000,if(O$1=($H97+1),1000000,if(O$1=($H97+2),1500000,"")))))))) -> 0 | P97: =if($E97="","",if($E97="Dropped",if(and(P$1<=$I97,P$1>=$H97),if(Year($D97)=P$1,$F97*0.8,if((year($D97)+1)=P$1,$F97*0.6,$F97*0.4)) ,""),if($E97="Minors",0,if($E97="FA Contract",if(and(P$1<=$I97,P$1>=$H97),$F97,""),if($E97="YP Contract",if(P$1=$H97,500000,if(P$1=($H97+1),1000000,if(P$1=($H97+2),1500000,"")))))))) -> 0
A98: Ryan Sloan | B98: Brian Frederick | C98: 45694 | E98: Minors | F98: YP | G98: YP | I98: =if(H98="","",if(or($E98="FA Contract",$E98="Dropped"),$H98+$G98-1,if($E98="YP Contract",$H98+2,if(and($E98="Minors",$G98<>"YP"),$H98+$G98-1,if(and($E98="Minors",$G98="YP"),$H98+2,""))))) | J98: 33100000 | K98: =if($E98="","",if($E98="Dropped",if(and(K$1<=$I98,K$1>=$H98),if(Year($D98)=K$1,$F98*0.8,if((year($D98)+1)=K$1,$F98*0.6,$F98*0.4)) ,""),if($E98="Minors",0,if($E98="FA Contract",if(and(K$1<=$I98,K$1>=$H98),$F98,""),if($E98="YP Contract",if(K$1=$H98,500000,if(K$1=($H98+1),1000000,if(K$1=($H98+2),1500000,"")))))))) -> 0 | L98: =if($E98="","",if($E98="Dropped",if(and(L$1<=$I98,L$1>=$H98),if(Year($D98)=L$1,$F98*0.8,if((year($D98)+1)=L$1,$F98*0.6,$F98*0.4)) ,""),if($E98="Minors",0,if($E98="FA Contract",if(and(L$1<=$I98,L$1>=$H98),$F98,""),if($E98="YP Contract",if(L$1=$H98,500000,if(L$1=($H98+1),1000000,if(L$1=($H98+2),1500000,"")))))))) -> 0 | M98: =if($E98="","",if($E98="Dropped",if(and(M$1<=$I98,M$1>=$H98),if(Year($D98)=M$1,$F98*0.8,if((year($D98)+1)=M$1,$F98*0.6,$F98*0.4)) ,""),if($E98="Minors",0,if($E98="FA Contract",if(and(M$1<=$I98,M$1>=$H98),$F98,""),if($E98="YP Contract",if(M$1=$H98,500000,if(M$1=($H98+1),1000000,if(M$1=($H98+2),1500000,"")))))))) -> 0 | N98: =if($E98="","",if($E98="Dropped",if(and(N$1<=$I98,N$1>=$H98),if(Year($D98)=N$1,$F98*0.8,if((year($D98)+1)=N$1,$F98*0.6,$F98*0.4)) ,""),if($E98="Minors",0,if($E98="FA Contract",if(and(N$1<=$I98,N$1>=$H98),$F98,""),if($E98="YP Contract",if(N$1=$H98,500000,if(N$1=($H98+1),1000000,if(N$1=($H98+2),1500000,"")))))))) -> 0 | O98: =if($E98="","",if($E98="Dropped",if(and(O$1<=$I98,O$1>=$H98),if(Year($D98)=O$1,$F98*0.8,if((year($D98)+1)=O$1,$F98*0.6,$F98*0.4)) ,""),if($E98="Minors",0,if($E98="FA Contract",if(and(O$1<=$I98,O$1>=$H98),$F98,""),if($E98="YP Contract",if(O$1=$H98,500000,if(O$1=($H98+1),1000000,if(O$1=($H98+2),1500000,"")))))))) -> 0 | P98: =if($E98="","",if($E98="Dropped",if(and(P$1<=$I98,P$1>=$H98),if(Year($D98)=P$1,$F98*0.8,if((year($D98)+1)=P$1,$F98*0.6,$F98*0.4)) ,""),if($E98="Minors",0,if($E98="FA Contract",if(and(P$1<=$I98,P$1>=$H98),$F98,""),if($E98="YP Contract",if(P$1=$H98,500000,if(P$1=($H98+1),1000000,if(P$1=($H98+2),1500000,"")))))))) -> 0
A99: Travis Bazzana | B99: Brian Frederick | C99: 45685 | E99: Minors | F99: YP | G99: YP | I99: =if(H99="","",if(or($E99="FA Contract",$E99="Dropped"),$H99+$G99-1,if($E99="YP Contract",$H99+2,if(and($E99="Minors",$G99<>"YP"),$H99+$G99-1,if(and($E99="Minors",$G99="YP"),$H99+2,""))))) | J99: 33100000 | K99: =if($E99="","",if($E99="Dropped",if(and(K$1<=$I99,K$1>=$H99),if(Year($D99)=K$1,$F99*0.8,if((year($D99)+1)=K$1,$F99*0.6,$F99*0.4)) ,""),if($E99="Minors",0,if($E99="FA Contract",if(and(K$1<=$I99,K$1>=$H99),$F99,""),if($E99="YP Contract",if(K$1=$H99,500000,if(K$1=($H99+1),1000000,if(K$1=($H99+2),1500000,"")))))))) -> 0 | L99: =if($E99="","",if($E99="Dropped",if(and(L$1<=$I99,L$1>=$H99),if(Year($D99)=L$1,$F99*0.8,if((year($D99)+1)=L$1,$F99*0.6,$F99*0.4)) ,""),if($E99="Minors",0,if($E99="FA Contract",if(and(L$1<=$I99,L$1>=$H99),$F99,""),if($E99="YP Contract",if(L$1=$H99,500000,if(L$1=($H99+1),1000000,if(L$1=($H99+2),1500000,"")))))))) -> 0 | M99: =if($E99="","",if($E99="Dropped",if(and(M$1<=$I99,M$1>=$H99),if(Year($D99)=M$1,$F99*0.8,if((year($D99)+1)=M$1,$F99*0.6,$F99*0.4)) ,""),if($E99="Minors",0,if($E99="FA Contract",if(and(M$1<=$I99,M$1>=$H99),$F99,""),if($E99="YP Contract",if(M$1=$H99,500000,if(M$1=($H99+1),1000000,if(M$1=($H99+2),1500000,"")))))))) -> 0 | N99: =if($E99="","",if($E99="Dropped",if(and(N$1<=$I99,N$1>=$H99),if(Year($D99)=N$1,$F99*0.8,if((year($D99)+1)=N$1,$F99*0.6,$F99*0.4)) ,""),if($E99="Minors",0,if($E99="FA Contract",if(and(N$1<=$I99,N$1>=$H99),$F99,""),if($E99="YP Contract",if(N$1=$H99,500000,if(N$1=($H99+1),1000000,if(N$1=($H99+2),1500000,"")))))))) -> 0 | O99: =if($E99="","",if($E99="Dropped",if(and(O$1<=$I99,O$1>=$H99),if(Year($D99)=O$1,$F99*0.8,if((year($D99)+1)=O$1,$F99*0.6,$F99*0.4)) ,""),if($E99="Minors",0,if($E99="FA Contract",if(and(O$1<=$I99,O$1>=$H99),$F99,""),if($E99="YP Contract",if(O$1=$H99,500000,if(O$1=($H99+1),1000000,if(O$1=($H99+2),1500000,"")))))))) -> 0 | P99: =if($E99="","",if($E99="Dropped",if(and(P$1<=$I99,P$1>=$H99),if(Year($D99)=P$1,$F99*0.8,if((year($D99)+1)=P$1,$F99*0.6,$F99*0.4)) ,""),if($E99="Minors",0,if($E99="FA Contract",if(and(P$1<=$I99,P$1>=$H99),$F99,""),if($E99="YP Contract",if(P$1=$H99,500000,if(P$1=($H99+1),1000000,if(P$1=($H99+2),1500000,"")))))))) -> 0
A100: Gerrit Cole | B100: Ethan Gobetz | C100: 45318 | E100: FA Contract | F100: 25100000 | G100: 5 | H100: 2024 | I100: =if(H100="","",if(or($E100="FA Contract",$E100="Dropped"),$H100+$G100-1,if($E100="YP Contract",$H100+2,if(and($E100="Minors",$G100<>"YP"),$H100+$G100-1,if(and($E100="Minors",$G100="YP"),$H100+2,""))))) -> 2028 | J100: 33100000 | K100: =if($E100="","",if($E100="Dropped",if(and(K$1<=$I100,K$1>=$H100),if(Year($D100)=K$1,$F100*0.8,if((year($D100)+1)=K$1,$F100*0.6,$F100*0.4)) ,""),if($E100="Minors",0,if($E100="FA Contract",if(and(K$1<=$I100,K$1>=$H100),$F100,""),if($E100="YP Contract",if(K$1=$H100,500000,if(K$1=($H100+1),1000000,if(K$1=($H100+2),1500000,"")))))))) -> 25100000 | L100: =if($E100="","",if($E100="Dropped",if(and(L$1<=$I100,L$1>=$H100),if(Year($D100)=L$1,$F100*0.8,if((year($D100)+1)=L$1,$F100*0.6,$F100*0.4)) ,""),if($E100="Minors",0,if($E100="FA Contract",if(and(L$1<=$I100,L$1>=$H100),$F100,""),if($E100="YP Contract",if(L$1=$H100,500000,if(L$1=($H100+1),1000000,if(L$1=($H100+2),1500000,"")))))))) -> 25100000 | M100: =if($E100="","",if($E100="Dropped",if(and(M$1<=$I100,M$1>=$H100),if(Year($D100)=M$1,$F100*0.8,if((year($D100)+1)=M$1,$F100*0.6,$F100*0.4)) ,""),if($E100="Minors",0,if($E100="FA Contract",if(and(M$1<=$I100,M$1>=$H100),$F100,""),if($E100="YP Contract",if(M$1=$H100,500000,if(M$1=($H100+1),1000000,if(M$1=($H100+2),1500000,"")))))))) -> 25100000 | N100: =if($E100="","",if($E100="Dropped",if(and(N$1<=$I100,N$1>=$H100),if(Year($D100)=N$1,$F100*0.8,if((year($D100)+1)=N$1,$F100*0.6,$F100*0.4)) ,""),if($E100="Minors",0,if($E100="FA Contract",if(and(N$1<=$I100,N$1>=$H100),$F100,""),if($E100="YP Contract",if(N$1=$H100,500000,if(N$1=($H100+1),1000000,if(N$1=($H100+2),1500000,"")))))))) -> 25100000 | O100: =if($E100="","",if($E100="Dropped",if(and(O$1<=$I100,O$1>=$H100),if(Year($D100)=O$1,$F100*0.8,if((year($D100)+1)=O$1,$F100*0.6,$F100*0.4)) ,""),if($E100="Minors",0,if($E100="FA Contract",if(and(O$1<=$I100,O$1>=$H100),$F100,""),if($E100="YP Contract",if(O$1=$H100,500000,if(O$1=($H100+1),1000000,if(O$1=($H100+2),1500000,"")))))))) | P100: =if($E100="","",if($E100="Dropped",if(and(P$1<=$I100,P$1>=$H100),if(Year($D100)=P$1,$F100*0.8,if((year($D100)+1)=P$1,$F100*0.6,$F100*0.4)) ,""),if($E100="Minors",0,if($E100="FA Contract",if(and(P$1<=$I100,P$1>=$H100),$F100,""),if($E100="YP Contract",if(P$1=$H100,500000,if(P$1=($H100+1),1000000,if(P$1=($H100+2),1500000,""))))))))
A101: Pete Alonso | B101: Ethan Gobetz | C101: 45318 | E101: FA Contract | F101: 20000000 | G101: 2 | H101: 2024 | I101: =if(H101="","",if(or($E101="FA Contract",$E101="Dropped"),$H101+$G101-1,if($E101="YP Contract",$H101+2,if(and($E101="Minors",$G101<>"YP"),$H101+$G101-1,if(and($E101="Minors",$G101="YP"),$H101+2,""))))) -> 2025 | J101: 33100000 | K101: =if($E101="","",if($E101="Dropped",if(and(K$1<=$I101,K$1>=$H101),if(Year($D101)=K$1,$F101*0.8,if((year($D101)+1)=K$1,$F101*0.6,$F101*0.4)) ,""),if($E101="Minors",0,if($E101="FA Contract",if(and(K$1<=$I101,K$1>=$H101),$F101,""),if($E101="YP Contract",if(K$1=$H101,500000,if(K$1=($H101+1),1000000,if(K$1=($H101+2),1500000,"")))))))) -> 20000000 | L101: =if($E101="","",if($E101="Dropped",if(and(L$1<=$I101,L$1>=$H101),if(Year($D101)=L$1,$F101*0.8,if((year($D101)+1)=L$1,$F101*0.6,$F101*0.4)) ,""),if($E101="Minors",0,if($E101="FA Contract",if(and(L$1<=$I101,L$1>=$H101),$F101,""),if($E101="YP Contract",if(L$1=$H101,500000,if(L$1=($H101+1),1000000,if(L$1=($H101+2),1500000,"")))))))) | M101: =if($E101="","",if($E101="Dropped",if(and(M$1<=$I101,M$1>=$H101),if(Year($D101)=M$1,$F101*0.8,if((year($D101)+1)=M$1,$F101*0.6,$F101*0.4)) ,""),if($E101="Minors",0,if($E101="FA Contract",if(and(M$1<=$I101,M$1>=$H101),$F101,""),if($E101="YP Contract",if(M$1=$H101,500000,if(M$1=($H101+1),1000000,if(M$1=($H101+2),1500000,"")))))))) | N101: =if($E101="","",if($E101="Dropped",if(and(N$1<=$I101,N$1>=$H101),if(Year($D101)=N$1,$F101*0.8,if((year($D101)+1)=N$1,$F101*0.6,$F101*0.4)) ,""),if($E101="Minors",0,if($E101="FA Contract",if(and(N$1<=$I101,N$1>=$H101),$F101,""),if($E101="YP Contract",if(N$1=$H101,500000,if(N$1=($H101+1),1000000,if(N$1=($H101+2),1500000,"")))))))) | O101: =if($E101="","",if($E101="Dropped",if(and(O$1<=$I101,O$1>=$H101),if(Year($D101)=O$1,$F101*0.8,if((year($D101)+1)=O$1,$F101*0.6,$F101*0.4)) ,""),if($E101="Minors",0,if($E101="FA Contract",if(and(O$1<=$I101,O$1>=$H101),$F101,""),if($E101="YP Contract",if(O$1=$H101,500000,if(O$1=($H101+1),1000000,if(O$1=($H101+2),1500000,"")))))))) | P101: =if($E101="","",if($E101="Dropped",if(and(P$1<=$I101,P$1>=$H101),if(Year($D101)=P$1,$F101*0.8,if((year($D101)+1)=P$1,$F101*0.6,$F101*0.4)) ,""),if($E101="Minors",0,if($E101="FA Contract",if(and(P$1<=$I101,P$1>=$H101),$F101,""),if($E101="YP Contract",if(P$1=$H101,500000,if(P$1=($H101+1),1000000,if(P$1=($H101+2),1500000,""))))))))
